Workbook

Sheet Projects
A1: Project ID | B1: Project Name | C1: Program | D1: Theme | E1: Portfolio Category | F1: Business Unit | G1: Sponsor | H1: Delivery Lead | I1: PM | J1: Priority | K1: Investment Type | L1: Delivery Method | M1: Funding Type | N1: Governance Channel | O1: Financial Year | P1: Start Date | Q1: End Date | R1: Go Live Date | S1: Progress % | T1: Approved Funding | U1: CAPEX | V1: OPEX | W1: Total Funding | X1: Actual Spend | Y1: Forecast At Completion | Z1: Remaining Budget | AA1: Forecast Variance | AB1: Contingency | AC1: Benefits Forecast | AD1: Benefits Realised | AE1: Benefits Remaining | AF1: Benefit Realisation % | AG1: Budget | AH1: Actual Cost | AI1: Forecast | AJ1: Status | AK1: RAG
A2: PRJ001 | B2: Customer Portal | C2: Digital Transformation | D2: Digital & Applications | E2: Business Strategic | F2: Wholesale | G2: CTO | H2: Alex Brown | I2: John Smith | J2: P2 - High | K2: Transform | L2: Hybrid | M2: CAPEX | N2: Channel B (>$200K) | O2: FY25-26 | P2: 45702 | Q2: 46094 | R2: 46067 | S2: 74 | T2: 2593765 | U2: 1319588 | V2: 1274177 | W2: =U2+V2 | X2: 937070 | Y2: 2407335 | Z2: =T2-X2 | AA2: =T2-Y2 | AB2: 259376 | AC2: 6550938 | AD2: 2659810 | AE2: =AC2-AD2 | AF2: =IFERROR(AD2/AC2,0) | AG2: 2593765 | AH2: 937070 | AI2: 2407335 | AJ2: Completed | AK2: Green
A3: PRJ002 | B3: Cloud Migration | C3: Digital Transformation | D3: Cyber Security | E3: CAPEX | F3: Retail | G3: COO | H3: Carlos Diaz | I3: Mike Johnson | J3: P3 - Medium | K3: Run | L3: Agile | M3: CAPEX | N3: Channel B (>$200K) | O3: FY25 | P3: 45737 | Q3: 45937 | R3: 45889 | S3: 40 | T3: 1851915 | U3: 1106272 | V3: 745643 | W3: =U3+V3 | X3: 1714568 | Y3: 2065964 | Z3: =T3-X3 | AA3: =T3-Y3 | AB3: 185192 | AC3: 2754514 | AD3: 698458 | AE3: =AC3-AD3 | AF3: =IFERROR(AD3/AC3,0) | AG3: 1851915 | AH3: 1714568 | AI3: 2065964 | AJ3: Pipeline | AK3: Green
A4: PRJ003 | B4: Data Platform | C4: Cyber Security | D4: Data & Analytics | E4: Business Strategic | F4: Retail | G4: CFO | H4: Carlos Diaz | I4: John Smith | J4: P4 - Low | K4: Grow | L4: Agile | M4: Mixed | N4: Channel B (>$200K) | O4: FY25-26 | P4: 45756 | Q4: 46206 | R4: 46202 | S4: 78 | T4: 3895151 | U4: 2463632 | V4: 1431519 | W4: =U4+V4 | X4: 2432283 | Y4: 4441608 | Z4: =T4-X4 | AA4: =T4-Y4 | AB4: 389515 | AC4: 9010791 | AD4: 4658796 | AE4: =AC4-AD4 | AF4: =IFERROR(AD4/AC4,0) | AG4: 3895151 | AH4: 2432283 | AI4: 4441608 | AJ4: Active | AK4: Green
A5: PRJ004 | B5: AI Assistant | C5: Data & AI | D5: Data & Analytics | E5: IT Strategic | F5: HR | G5: CTO | H5: Jane Doe | I5: Priya Patel | J5: P3 - Medium | K5: Run | L5: Waterfall | M5: OPEX | N5: Channel B (>$200K) | O5: FY25-27 | P5: 45931 | Q5: 46394 | R5: 46379 | S5: 26 | T5: 1543706 | U5: 885049 | V5: 658657 | W5: =U5+V5 | X5: 545899 | Y5: 1818222 | Z5: =T5-X5 | AA5: =T5-Y5 | AB5: 154371 | AC5: 3653124 | AD5: 1335139 | AE5: =AC5-AD5 | AF5: =IFERROR(AD5/AC5,0) | AG5: 1543706 | AH5: 545899 | AI5: 1818222 | AJ5: Active | AK5: Green
A6: PRJ005 | B6: Network Refresh | C6: Cyber Security | D6: Data & Analytics | E6: Unfunded | F6: Wholesale | G6: CFO | H6: Priya Patel | I6: Alex Brown | J6: P3 - Medium | K6: Transform | L6: Hybrid | M6: Unfunded | N6: Channel B (>$200K) | O6: FY25-27 | P6: 45860 | Q6: 46402 | R6: 46344 | S6: 68 | T6: 1664543 | U6: 870832 | V6: 793711 | W6: =U6+V6 | X6: 1610411 | Y6: 1745295 | Z6: =T6-X6 | AA6: =T6-Y6 | AB6: 166454 | AC6: 4148450 | AD6: 529242 | AE6: =AC6-AD6 | AF6: =IFERROR(AD6/AC6,0) | AG6: 1664543 | AH6: 1610411 | AI6: 1745295 | AJ6: Completed | AK6: Amber
A7: PRJ006 | B7: Cyber Security Program | C7: Customer Experience | D7: Infrastructure | E7: Unfunded | F7: Technology | G7: CMO | H7: Alex Brown | I7: Sarah Lee | J7: P3 - Medium | K7: Transform | L7: Waterfall | M7: Unfunded | N7: Channel B (>$200K) | O7: FY25-26 | P7: 45736 | Q7: 46147 | R7: 46137 | S7: 19 | T7: 1657662 | U7: 956077 | V7: 701585 | W7: =U7+V7 | X7: 1736667 | Y7: 1704631 | Z7: =T7-X7 | AA7: =T7-Y7 | AB7: 165766 | AC7: 2260449 | AD7: 63902 | AE7: =AC7-AD7 | AF7: =IFERROR(AD7/AC7,0) | AG7: 1657662 | AH7: 1736667 | AI7: 1704631 | AJ7: Active | AK7: Red
A8: PRJ007 | B8: CRM Upgrade | C8: Digital Transformation | D8: Data & Analytics | E8: IT Strategic | F8: Marketing | G8: CTO | H8: Alex Brown | I8: Jane Doe | J8: P2 - High | K8: Grow | L8: Waterfall | M8: Mixed | N8: Channel B (>$200K) | O8: FY25-26 | P8: 45792 | Q8: 46379 | R8: 46347 | S8: 5 | T8: 3550675 | U8: 2708481 | V8: 842194 | W8: =U8+V8 | X8: 2947660 | Y8: 3440822 | Z8: =T8-X8 | AA8: =T8-Y8 | AB8: 355068 | AC8: 6136632 | AD8: 582334 | AE8: =AC8-AD8 | AF8: =IFERROR(AD8/AC8,0) | AG8: 3550675 | AH8: 2947660 | AI8: 3440822 | AJ8: Pipeline | AK8: Amber
A9: PRJ008 | B9: Mobile App | C9: Data & AI | D9: Infrastructure | E9: Business Strategic | F9: Marketing | G9: CTO | H9: Carlos Diaz | I9: Jane Doe | J9: P2 - High | K9: Transform | L9: Agile | M9: CAPEX | N9: Channel B (>$200K) | O9: FY25 | P9: 45780 | Q9: 45899 | R9: 45884 | S9: 44 | T9: 3682125 | U9: 2612949 | V9: 1069176 | W9: =U9+V9 | X9: 2077364 | Y9: 3273975 | Z9: =T9-X9 | AA9: =T9-Y9 | AB9: 368212 | AC9: 6824323 | AD9: 4034491 | AE9: =AC9-AD9 | AF9: =IFERROR(AD9/AC9,0) | AG9: 3682125 | AH9: 2077364 | AI9: 3273975 | AJ9: Pipeline | AK9: Green
A10: PRJ009 | B10: ERP Modernisation | C10: Customer Experience | D10: Cyber Security | E10: CAPEX | F10: Retail | G10: CFO | H10: Jane Doe | I10: John Smith | J10: P3 - Medium | K10: Run | L10: Hybrid | M10: OPEX | N10: Channel B (>$200K) | O10: FY26 | P10: 46023 | Q10: 46272 | R10: 46247 | S10: 30 | T10: 1133721 | U10: 913044 | V10: 220677 | W10: =U10+V10 | X10: 569106 | Y10: 1047705 | Z10: =T10-X10 | AA10: =T10-Y10 | AB10: 113372 | AC10: 2461006 | AD10: 1077819 | AE10: =AC10-AD10 | AF10: =IFERROR(AD10/AC10,0) | AG10: 1133721 | AH10: 569106 | AI10: 1047705 | AJ10: Pipeline | AK10: Green
A11: PRJ010 | B11: Workforce Enablement | C11: Data & AI | D11: Digital & Applications | E11: CAPEX | F11: Finance | G11: CFO | H11: Priya Patel | I11: Alex Brown | J11: P4 - Low | K11: Run | L11: Agile | M11: Mixed | N11: Channel B (>$200K) | O11: FY25-26 | P11: 45694 | Q11: 46047 | R11: 46032 | S11: 47 | T11: 2394916 | U11: 1203486 | V11: 1191430 | W11: =U11+V11 | X11: 1849950 | Y11: 2085028 | Z11: =T11-X11 | AA11: =T11-Y11 | AB11: 239492 | AC11: 3164452 | AD11: 59643 | AE11: =AC11-AD11 | AF11: =IFERROR(AD11/AC11,0) | AG11: 2394916 | AH11: 1849950 | AI11: 2085028 | AJ11: Completed | AK11: Green
A12: PRJ011 | B12: IoT Initiative | C12: Cloud Migration | D12: Infrastructure | E12: Unfunded | F12: Wholesale | G12: CFO | H12: Jane Doe | I12: Alex Brown | J12: P4 - Low | K12: Run | L12: Agile | M12: Unfunded | N12: Channel B (>$200K) | O12: FY25-26 | P12: 45988 | Q12: 46128 | R12: 46125 | S12: 88 | T12: 467871 | U12: 341847 | V12: 126024 | W12: =U12+V12 | X12: 204264 | Y12: 465010 | Z12: =T12-X12 | AA12: =T12-Y12 | AB12: 46787 | AC12: 1288941 | AD12: 41894 | AE12: =AC12-AD12 | AF12: =IFERROR(AD12/AC12,0) | AG12: 467871 | AH12: 204264 | AI12: 465010 | AJ12: Active | AK12: Green
A13: PRJ012 | B13: Analytics Platform | C13: Cyber Security | D13: Cyber Security | E13: Business Strategic | F13: Technology | G13: CMO | H13: Jane Doe | I13: Carlos Diaz | J13: P4 - Low | K13: Run | L13: Waterfall | M13: CAPEX | N13: Channel B (>$200K) | O13: FY25-27 | P13: 45934 | Q13: 46452 | R13: 46452 | S13: 88 | T13: 1904249 | U13: 1534958 | V13: 369291 | W13: =U13+V13 | X13: 326799 | Y13: 2157148 | Z13: =T13-X13 | AA13: =T13-Y13 | AB13: 190425 | AC13: 5219052 | AD13: 306594 | AE13: =AC13-AD13 | AF13: =IFERROR(AD13/AC13,0) | AG13: 1904249 | AH13: 326799 | AI13: 2157148 | AJ13: Completed | AK13: Green
... A41: PRJ040 | B41: Zero-Trust Net | C41: Customer Experience | D41: Digital & Applications | E41: CAPEX | F41: Technology | G41: CIO | H41: Alex Brown | I41: Jane Doe | J41: P2 - High | K41: Grow | L41: Waterfall | M41: Mixed | N41: Channel B (>$200K) | O41: FY25-26 | P41: 45694 | Q41: 46135 | R41: 46121 | S41: 63 | T41: 1693219 | U41: 1255149 | V41: 438070 | W41: =U41+V41 | X41: 925203 | Y41: 1458579 | Z41: =T41-X41 | AA41: =T41-Y41 | AB41: 169322 | AC41: 2909947 | AD41: 493617 | AE41: =AC41-AD41 | AF41: =IFERROR(AD41/AC41,0) | AG41: 1693219 | AH41: 925203 | AI41: 1458579 | AJ41: Active | AK41: Green

Sheet Roadmap
A1: Project ID | B1: Month | C1: Year | D1: Phase | E1: Status
A2: PRJ001 | B2: Mar | C2: 2025 | D2: Design | E2: Completed
A3: PRJ001 | B3: Apr | C3: 2025 | D3: Build | E3: Completed
A4: PRJ001 | B4: May | C4: 2025 | D4: Deploy | E4: Completed
A5: PRJ001 | B5: Jun | C5: 2025 | D5: Deploy | E5: Completed
A6: PRJ001 | B6: Jul | C6: 2025 | D6: Build | E6: Completed
A7: PRJ001 | B7: Aug | C7: 2025 | D7: Test | E7: Completed
A8: PRJ001 | B8: Sep | C8: 2025 | D8: Discovery | E8: Completed
A9: PRJ001 | B9: Oct | C9: 2025 | D9: Test | E9: Completed
A10: PRJ001 | B10: Nov | C10: 2025 | D10: Build | E10: Completed
A11: PRJ001 | B11: Dec | C11: 2025 | D11: Test | E11: Completed
A12: PRJ001 | B12: Jan | C12: 2026 | D12: Build | E12: Completed
A13: PRJ001 | B13: Feb | C13: 2026 | D13: Deploy | E13: Completed
... A483: PRJ040 | B483: Apr | C483: 2026 | D483: Build | E483: Active

Sheet Risks
A1: Risk ID | B1: Project ID | C1: Description | D1: Probability | E1: Impact | F1: Velocity | G1: Owner | H1: Mitigation Plan | I1: Status
A2: R001 | B2: PRJ028 | C2: Vendor delay impacting milestone | D2: Medium | E2: High | F2: Medium | G2: John Smith | H2: Increase staffing | I2: Open
A3: R002 | B3: PRJ010 | C3: Stakeholder alignment risk | D3: Low | E3: Low | F3: Medium | G3: Carlos Diaz | H3: Increase staffing | I3: Mitigated
A4: R003 | B4: PRJ008 | C4: Scope creep | D4: High | E4: Medium | F4: Medium | G4: Carlos Diaz | H4: Increase staffing | I4: Open
A5: R004 | B5: PRJ039 | C5: Scope creep | D5: Low | E5: Medium | F5: Medium | G5: Priya Patel | H5: Rebaseline budget | I5: Mitigated
A6: R005 | B6: PRJ023 | C6: Vendor delay impacting milestone | D6: Low | E6: Medium | F6: Fast | G6: Priya Patel | H6: Patch & monitoring | I6: Open
A7: R006 | B7: PRJ010 | C7: Vendor delay impacting milestone | D7: Low | E7: Medium | F7: Medium | G7: Sarah Lee | H7: Patch & monitoring | I7: Mitigated
A8: R007 | B8: PRJ011 | C8: Integration risk | D8: Medium | E8: High | F8: Fast | G8: Alex Brown | H8: Add buffer | I8: Open
A9: R008 | B9: PRJ010 | C9: Resource shortage | D9: High | E9: Low | F9: Fast | G9: John Smith | H9: Rebaseline budget | I9: Closed
A10: R009 | B10: PRJ028 | C10: Stakeholder alignment risk | D10: High | E10: Critical | F10: Medium | G10: Mike Johnson | H10: Engage vendor | I10: Open
A11: R010 | B11: PRJ023 | C11: Regulatory change | D11: Low | E11: High | F11: Fast | G11: Priya Patel | H11: Increase staffing | I11: Closed
A12: R011 | B12: PRJ034 | C12: Scope creep | D12: Low | E12: Medium | F12: Medium | G12: Alex Brown | H12: Add buffer | I12: Open
... A61: R060 | B61: PRJ026 | C61: Stakeholder alignment risk | D61: Medium | E61: High | F61: Slow | G61: Sarah Lee | H61: Stakeholder workshop | I61: Closed

Sheet RAID
A1: RAID ID | B1: Project ID | C1: Type | D1: Description | E1: Probability | F1: Impact | G1: RAG | H1: Owner | I1: Target Resolution Date | J1: Mitigation | K1: Status
A2: RAID001 | B2: PRJ024 | C2: Assumption | D2: Regulatory deadline | E2: Low | F2: Critical | G2: Green | H2: Sarah Lee | I2: 46236 | J2: Contingency plan | K2: Closed
A3: RAID002 | B3: PRJ019 | C3: Assumption | D3: Cloud provider outage risk | E3: Low | F3: High | G3: Red | H3: Mike Johnson | I3: 46160 | J3: Re-baseline | K3: Closed
A4: RAID003 | B4: PRJ028 | C4: Issue | D4: Staff turnover | E4: Medium | F4: High | G4: Amber | H4: John Smith | I4: 46268 | J4: Vendor escalation | K4: Closed
A5: RAID004 | B5: PRJ028 | C5: Assumption | D5: Staff turnover | E5: Low | F5: Low | G5: Red | H5: Priya Patel | I5: 46185 | J5: Vendor escalation | K5: Closed
A6: RAID005 | B6: PRJ011 | C6: Risk | D6: Test data not available | E6: High | F6: Critical | G6: Green | H6: Jane Doe | I6: 46099 | J6: Contingency plan | K6: Closed
A7: RAID006 | B7: PRJ024 | C7: Assumption | D7: Depends on procurement signoff | E7: High | F7: Low | G7: Red | H7: Jane Doe | I7: 46255 | J7: Re-baseline | K7: In Progress
A8: RAID007 | B8: PRJ024 | C8: Dependency | D8: Regulatory deadline | E8: Low | F8: Medium | G8: Red | H8: Mike Johnson | I8: 46183 | J8: Vendor escalation | K8: Closed
A9: RAID008 | B9: PRJ018 | C9: Issue | D9: Cloud provider outage risk | E9: Low | F9: Medium | G9: Amber | H9: Alex Brown | I9: 46181 | J9: Add buffer | K9: Open
A10: RAID009 | B10: PRJ017 | C10: Assumption | D10: Staff turnover | E10: Medium | F10: Medium | G10: Red | H10: Mike Johnson | I10: 46259 | J10: Re-baseline | K10: Open
A11: RAID010 | B11: PRJ008 | C11: Issue | D11: Regulatory deadline | E11: Low | F11: Critical | G11: Green | H11: Priya Patel | I11: 46195 | J11: Active monitoring | K11: Closed
A12: RAID011 | B12: PRJ021 | C12: Assumption | D12: Staff turnover | E12: Low | F12: High | G12: Amber | H12: Carlos Diaz | I12: 46122 | J12: Contingency plan | K12: In Progress
A13: RAID012 | B13: PRJ033 | C13: Issue | D13: Cloud provider outage risk | E13: Low | F13: Medium | G13: Green | H13: Carlos Diaz | I13: 46208 | J13: Active monitoring | K13: In Progress
... A81: RAID080 | B81: PRJ036 | C81: Issue | D81: Depends on procurement signoff | E81: Low | F81: High | G81: Amber | H81: John Smith | I81: 46136 | J81: Contingency plan | K81: Closed

Sheet StageGates
A1: Project ID | B1: Project Name | C1: Governance Channel | D1: Stage | E1: Next Gate | F1: Gate Status | G1: Status | H1: Gate Owner | I1: Planned Gate Date | J1: Actual Gate Date | K1: Gate Outcome | L1: Gate Comments | M1: Checklist Complete % | N1: Days Late | O1: _Key
A2: PRJ001 | B2: =IFERROR(VLOOKUP(A2,Projects!$A:$AK,2,FALSE()),"") | C2: =IFERROR(VLOOKUP(A2,Projects!$A:$AK,14,FALSE()),"") | D2: Discovery | E2: =IFERROR(INDEX(_Stages!$A$1:$A$8,MIN(MATCH(D2,_Stages!$A$1:$A$8,0)+1,8)),"") | F2: Approved | G2: Complete | H2: CTO | I2: 45702 | J2: 45717 | K2: Conditional | L2: Approved with conditions | M2: 100 | N2: 15 | O2: =A2&"|"&D2
A3: PRJ001 | B3: =IFERROR(VLOOKUP(A3,Projects!$A:$AK,2,FALSE()),"") | C3: =IFERROR(VLOOKUP(A3,Projects!$A:$AK,14,FALSE()),"") | D3: Business Case / Seed Funding | E3: =IFERROR(INDEX(_Stages!$A$1:$A$8,MIN(MATCH(D3,_Stages!$A$1:$A$8,0)+1,8)),"") | F3: Pending Approval | G3: In Progress | H3: CTO | I3: 45762 | L3: Awaiting sponsor sign-off | M3: 89 | N3: 0 | O3: =A3&"|"&D3
A4: PRJ001 | B4: =IFERROR(VLOOKUP(A4,Projects!$A:$AK,2,FALSE()),"") | C4: =IFERROR(VLOOKUP(A4,Projects!$A:$AK,14,FALSE()),"") | D4: Design | E4: =IFERROR(INDEX(_Stages!$A$1:$A$8,MIN(MATCH(D4,_Stages!$A$1:$A$8,0)+1,8)),"") | F4: Not Started | G4: Not Started | H4: CTO | I4: 45822 | L4: On track | M4: 0 | N4: 0 | O4: =A4&"|"&D4
A5: PRJ001 | B5: =IFERROR(VLOOKUP(A5,Projects!$A:$AK,2,FALSE()),"") | C5: =IFERROR(VLOOKUP(A5,Projects!$A:$AK,14,FALSE()),"") | D5: Business Case / Full Funding | E5: =IFERROR(INDEX(_Stages!$A$1:$A$8,MIN(MATCH(D5,_Stages!$A$1:$A$8,0)+1,8)),"") | F5: Not Started | G5: Not Started | H5: CTO | I5: 45882 | L5: Awaiting sponsor sign-off | M5: 0 | N5: 0 | O5: =A5&"|"&D5
A6: PRJ001 | B6: =IFERROR(VLOOKUP(A6,Projects!$A:$AK,2,FALSE()),"") | C6: =IFERROR(VLOOKUP(A6,Projects!$A:$AK,14,FALSE()),"") | D6: Build | E6: =IFERROR(INDEX(_Stages!$A$1:$A$8,MIN(MATCH(D6,_Stages!$A$1:$A$8,0)+1,8)),"") | F6: Not Started | G6: Not Started | H6: CTO | I6: 45942 | L6: Awaiting sponsor sign-off | M6: 0 | N6: 0 | O6: =A6&"|"&D6
A7: PRJ001 | B7: =IFERROR(VLOOKUP(A7,Projects!$A:$AK,2,FALSE()),"") | C7: =IFERROR(VLOOKUP(A7,Projects!$A:$AK,14,FALSE()),"") | D7: Testing | E7: =IFERROR(INDEX(_Stages!$A$1:$A$8,MIN(MATCH(D7,_Stages!$A$1:$A$8,0)+1,8)),"") | F7: Not Started | G7: Not Started | H7: CTO | I7: 46002 | L7: On track | M7: 0 | N7: 0 | O7: =A7&"|"&D7
A8: PRJ001 | B8: =IFERROR(VLOOKUP(A8,Projects!$A:$AK,2,FALSE()),"") | C8: =IFERROR(VLOOKUP(A8,Projects!$A:$AK,14,FALSE()),"") | D8: Deployment | E8: =IFERROR(INDEX(_Stages!$A$1:$A$8,MIN(MATCH(D8,_Stages!$A$1:$A$8,0)+1,8)),"") | F8: Not Started | G8: Not Started | H8: CTO | I8: 46062 | M8: 0 | N8: 0 | O8: =A8&"|"&D8
A9: PRJ001 | B9: =IFERROR(VLOOKUP(A9,Projects!$A:$AK,2,FALSE()),"") | C9: =IFERROR(VLOOKUP(A9,Projects!$A:$AK,14,FALSE()),"") | D9: Handover | E9: =IFERROR(INDEX(_Stages!$A$1:$A$8,MIN(MATCH(D9,_Stages!$A$1:$A$8,0)+1,8)),"") | F9: Not Started | G9: Not Started | H9: CTO | I9: 46122 | L9: Awaiting sponsor sign-off | M9: 0 | N9: 0 | O9: =A9&"|"&D9
A10: PRJ002 | B10: =IFERROR(VLOOKUP(A10,Projects!$A:$AK,2,FALSE()),"") | C10: =IFERROR(VLOOKUP(A10,Projects!$A:$AK,14,FALSE()),"") | D10: Discovery | E10: =IFERROR(INDEX(_Stages!$A$1:$A$8,MIN(MATCH(D10,_Stages!$A$1:$A$8,0)+1,8)),"") | F10: Approved | G10: Complete | H10: COO | I10: 45737 | J10: 45745 | K10: Rework | L10: On track | M10: 100 | N10: 8 | O10: =A10&"|"&D10
A11: PRJ002 | B11: =IFERROR(VLOOKUP(A11,Projects!$A:$AK,2,FALSE()),"") | C11: =IFERROR(VLOOKUP(A11,Projects!$A:$AK,14,FALSE()),"") | D11: Business Case / Seed Funding | E11: =IFERROR(INDEX(_Stages!$A$1:$A$8,MIN(MATCH(D11,_Stages!$A$1:$A$8,0)+1,8)),"") | F11: Approved | G11: Complete | H11: COO | I11: 45797 | J11: 45784 | K11: Conditional | L11: Approved with conditions | M11: 100 | N11: 0 | O11: =A11&"|"&D11
A12: PRJ002 | B12: =IFERROR(VLOOKUP(A12,Projects!$A:$AK,2,FALSE()),"") | C12: =IFERROR(VLOOKUP(A12,Projects!$A:$AK,14,FALSE()),"") | D12: Design | E12: =IFERROR(INDEX(_Stages!$A$1:$A$8,MIN(MATCH(D12,_Stages!$A$1:$A$8,0)+1,8)),"") | F12: Approved | G12: Complete | H12: COO | I12: 45857 | J12: 45843 | K12: Rework | L12: On track | M12: 100 | N12: 0 | O12: =A12&"|"&D12
A13: PRJ002 | B13: =IFERROR(VLOOKUP(A13,Projects!$A:$AK,2,FALSE()),"") | C13: =IFERROR(VLOOKUP(A13,Projects!$A:$AK,14,FALSE()),"") | D13: Business Case / Full Funding | E13: =IFERROR(INDEX(_Stages!$A$1:$A$8,MIN(MATCH(D13,_Stages!$A$1:$A$8,0)+1,8)),"") | F13: Pending Approval | G13: In Progress | H13: COO | I13: 45917 | L13: Approved with conditions | M13: 61 | N13: 0 | O13: =A13&"|"&D13
A14: PRJ002 | B14: =IFERROR(VLOOKUP(A14,Projects!$A:$AK,2,FALSE()),"") | C14: =IFERROR(VLOOKUP(A14,Projects!$A:$AK,14,FALSE()),"") | D14: Build | E14: =IFERROR(INDEX(_Stages!$A$1:$A$8,MIN(MATCH(D14,_Stages!$A$1:$A$8,0)+1,8)),"") | F14: Not Started | G14: Not Started | H14: COO | I14: 45977 | L14: On track | M14: 0 | N14: 0 | O14: =A14&"|"&D14
A15: PRJ002 | B15: =IFERROR(VLOOKUP(A15,Projects!$A:$AK,2,FALSE()),"") | C15: =IFERROR(VLOOKUP(A15,Projects!$A:$AK,14,FALSE()),"") | D15: Testing | E15: =IFERROR(INDEX(_Stages!$A$1:$A$8,MIN(MATCH(D15,_Stages!$A$1:$A$8,0)+1,8)),"") | F15: Not Started | G15: Not Started | H15: COO | I15: 46037 | L15: Approved with conditions | M15: 0 | N15: 0 | O15: =A15&"|"&D15
A16: PRJ002 | B16: =IFERROR(VLOOKUP(A16,Projects!$A:$AK,2,FALSE()),"") | C16: =IFERROR(VLOOKUP(A16,Projects!$A:$AK,14,FALSE()),"") | D16: Deployment | E16: =IFERROR(INDEX(_Stages!$A$1:$A$8,MIN(MATCH(D16,_Stages!$A$1:$A$8,0)+1,8)),"") | F16: Not Started | G16: Not Started | H16: COO | I16: 46097 | L16: Awaiting sponsor sign-off | M16: 0 | N16: 0 | O16: =A16&"|"&D16
A17: PRJ002 | B17: =IFERROR(VLOOKUP(A17,Projects!$A:$AK,2,FALSE()),"") | C17: =IFERROR(VLOOKUP(A17,Projects!$A:$AK,14,FALSE()),"") | D17: Handover | E17: =IFERROR(INDEX(_Stages!$A$1:$A$8,MIN(MATCH(D17,_Stages!$A$1:$A$8,0)+1,8)),"") | F17: Not Started | G17: Not Started | H17: COO | I17: 46157 | L17: On track | M17: 0 | N17: 0 | O17: =A17&"|"&D17
A18: PRJ003 | B18: =IFERROR(VLOOKUP(A18,Projects!$A:$AK,2,FALSE()),"") | C18: =IFERROR(VLOOKUP(A18,Projects!$A:$AK,14,FALSE()),"") | D18: Discovery | E18: =IFERROR(INDEX(_Stages!$A$1:$A$8,MIN(MATCH(D18,_Stages!$A$1:$A$8,0)+1,8)),"") | F18: Approved | G18: Complete | H18: CFO | I18: 45756 | J18: 45770 | K18: Conditional | L18: Awaiting sponsor sign-off | M18: 100 | N18: 14 | O18: =A18&"|"&D18
A19: PRJ003 | B19: =IFERROR(VLOOKUP(A19,Projects!$A:$AK,2,FALSE()),"") | C19: =IFERROR(VLOOKUP(A19,Projects!$A:$AK,14,FALSE()),"") | D19: Business Case / Seed Funding | E19: =IFERROR(INDEX(_Stages!$A$1:$A$8,MIN(MATCH(D19,_Stages!$A$1:$A$8,0)+1,8)),"") | F19: Approved | G19: Complete | H19: CFO | I19: 45816 | J19: 45811 | K19: Conditional | L19: On track | M19: 100 | N19: 0 | O19: =A19&"|"&D19
A20: PRJ003 | B20: =IFERROR(VLOOKUP(A20,Projects!$A:$AK,2,FALSE()),"") | C20: =IFERROR(VLOOKUP(A20,Projects!$A:$AK,14,FALSE()),"") | D20: Design | E20: =IFERROR(INDEX(_Stages!$A$1:$A$8,MIN(MATCH(D20,_Stages!$A$1:$A$8,0)+1,8)),"") | F20: Approved | G20: Complete | H20: CFO | I20: 45876 | J20: 45872 | K20: Proceed | M20: 100 | N20: 0 | O20: =A20&"|"&D20
A21: PRJ003 | B21: =IFERROR(VLOOKUP(A21,Projects!$A:$AK,2,FALSE()),"") | C21: =IFERROR(VLOOKUP(A21,Projects!$A:$AK,14,FALSE()),"") | D21: Business Case / Full Funding | E21: =IFERROR(INDEX(_Stages!$A$1:$A$8,MIN(MATCH(D21,_Stages!$A$1:$A$8,0)+1,8)),"") | F21: Approved | G21: Complete | H21: CFO | I21: 45936 | J21: 45925 | K21: Proceed | M21: 100 | N21: 0 | O21: =A21&"|"&D21
A22: PRJ003 | B22: =IFERROR(VLOOKUP(A22,Projects!$A:$AK,2,FALSE()),"") | C22: =IFERROR(VLOOKUP(A22,Projects!$A:$AK,14,FALSE()),"") | D22: Build | E22: =IFERROR(INDEX(_Stages!$A$1:$A$8,MIN(MATCH(D22,_Stages!$A$1:$A$8,0)+1,8)),"") | F22: Approved | G22: Complete | H22: CFO | I22: 45996 | J22: 46007 | K22: Conditional | L22: Approved with conditions | M22: 100 | N22: 11 | O22: =A22&"|"&D22
A23: PRJ003 | B23: =IFERROR(VLOOKUP(A23,Projects!$A:$AK,2,FALSE()),"") | C23: =IFERROR(VLOOKUP(A23,Projects!$A:$AK,14,FALSE()),"") | D23: Testing | E23: =IFERROR(INDEX(_Stages!$A$1:$A$8,MIN(MATCH(D23,_Stages!$A$1:$A$8,0)+1,8)),"") | F23: Approved | G23: Complete | H23: CFO | I23: 46056 | J23: 46045 | K23: Conditional | M23: 100 | N23: 0 | O23: =A23&"|"&D23
A24: PRJ003 | B24: =IFERROR(VLOOKUP(A24,Projects!$A:$AK,2,FALSE()),"") | C24: =IFERROR(VLOOKUP(A24,Projects!$A:$AK,14,FALSE()),"") | D24: Deployment | E24: =IFERROR(INDEX(_Stages!$A$1:$A$8,MIN(MATCH(D24,_Stages!$A$1:$A$8,0)+1,8)),"") | F24: Approved | G24: Complete | H24: CFO | I24: 46116 | J24: 46114 | K24: Held | L24: Awaiting sponsor sign-off | M24: 100 | N24: 0 | O24: =A24&"|"&D24
A25: PRJ003 | B25: =IFERROR(VLOOKUP(A25,Projects!$A:$AK,2,FALSE()),"") | C25: =IFERROR(VLOOKUP(A25,Projects!$A:$AK,14,FALSE()),"") | D25: Handover | E25: =IFERROR(INDEX(_Stages!$A$1:$A$8,MIN(MATCH(D25,_Stages!$A$1:$A$8,0)+1,8)),"") | F25: In Progress | G25: In Progress | H25: CFO | I25: 46176 | L25: On track | M25: 41 | N25: 0 | O25: =A25&"|"&D25
A26: PRJ004 | B26: =IFERROR(VLOOKUP(A26,Projects!$A:$AK,2,FALSE()),"") | C26: =IFERROR(VLOOKUP(A26,Projects!$A:$AK,14,FALSE()),"") | D26: Discovery | E26: =IFERROR(INDEX(_Stages!$A$1:$A$8,MIN(MATCH(D26,_Stages!$A$1:$A$8,0)+1,8)),"") | F26: In Progress | G26: In Progress | H26: CTO | I26: 45931 | M26: 41 | N26: 0 | O26: =A26&"|"&D26
A27: PRJ004 | B27: =IFERROR(VLOOKUP(A27,Projects!$A:$AK,2,FALSE()),"") | C27: =IFERROR(VLOOKUP(A27,Projects!$A:$AK,14,FALSE()),"") | D27: Business Case / Seed Funding | E27: =IFERROR(INDEX(_Stages!$A$1:$A$8,MIN(MATCH(D27,_Stages!$A$1:$A$8,0)+1,8)),"") | F27: Not Started | G27: Not Started | H27: CTO | I27: 45991 | L27: Awaiting sponsor sign-off | M27: 0 | N27: 0 | O27: =A27&"|"&D27
A28: PRJ004 | B28: =IFERROR(VLOOKUP(A28,Projects!$A:$AK,2,FALSE()),"") | C28: =IFERROR(VLOOKUP(A28,Projects!$A:$AK,14,FALSE()),"") | D28: Design | E28: =IFERROR(INDEX(_Stages!$A$1:$A$8,MIN(MATCH(D28,_Stages!$A$1:$A$8,0)+1,8)),"") | F28: Not Started | G28: Not Started | H28: CTO | I28: 46051 | L28: Awaiting sponsor sign-off | M28: 0 | N28: 0 | O28: =A28&"|"&D28
A29: PRJ004 | B29: =IFERROR(VLOOKUP(A29,Projects!$A:$AK,2,FALSE()),"") | C29: =IFERROR(VLOOKUP(A29,Projects!$A:$AK,14,FALSE()),"") | D29: Business Case / Full Funding | E29: =IFERROR(INDEX(_Stages!$A$1:$A$8,MIN(MATCH(D29,_Stages!$A$1:$A$8,0)+1,8)),"") | F29: Not Started | G29: Not Started | H29: CTO | I29: 46111 | L29: On track | M29: 0 | N29: 0 | O29: =A29&"|"&D29
A30: PRJ004 | B30: =IFERROR(VLOOKUP(A30,Projects!$A:$AK,2,FALSE()),"") | C30: =IFERROR(VLOOKUP(A30,Projects!$A:$AK,14,FALSE()),"") | D30: Build | E30: =IFERROR(INDEX(_Stages!$A$1:$A$8,MIN(MATCH(D30,_Stages!$A$1:$A$8,0)+1,8)),"") | F30: Not Started | G30: Not Started | H30: CTO | I30: 46171 | M30: 0 | N30: 0 | O30: =A30&"|"&D30
A31: PRJ004 | B31: =IFERROR(VLOOKUP(A31,Projects!$A:$AK,2,FALSE()),"") | C31: =IFERROR(VLOOKUP(A31,Projects!$A:$AK,14,FALSE()),"") | D31: Testing | E31: =IFERROR(INDEX(_Stages!$A$1:$A$8,MIN(MATCH(D31,_Stages!$A$1:$A$8,0)+1,8)),"") | F31: Not Started | G31: Not Started | H31: CTO | I31: 46231 | L31: Approved with conditions | M31: 0 | N31: 0 | O31: =A31&"|"&D31
A32: PRJ004 | B32: =IFERROR(VLOOKUP(A32,Projects!$A:$AK,2,FALSE()),"") | C32: =IFERROR(VLOOKUP(A32,Projects!$A:$AK,14,FALSE()),"") | D32: Deployment | E32: =IFERROR(INDEX(_Stages!$A$1:$A$8,MIN(MATCH(D32,_Stages!$A$1:$A$8,0)+1,8)),"") | F32: Not Started | G32: Not Started | H32: CTO | I32: 46291 | L32: Approved with conditions | M32: 0 | N32: 0 | O32: =A32&"|"&D32
A33: PRJ004 | B33: =IFERROR(VLOOKUP(A33,Projects!$A:$AK,2,FALSE()),"") | C33: =IFERROR(VLOOKUP(A33,Projects!$A:$AK,14,FALSE()),"") | D33: Handover | E33: =IFERROR(INDEX(_Stages!$A$1:$A$8,MIN(MATCH(D33,_Stages!$A$1:$A$8,0)+1,8)),"") | F33: Not Started | G33: Not Started | H33: CTO | I33: 46351 | L33: Awaiting sponsor sign-off | M33: 0 | N33: 0 | O33: =A33&"|"&D33
A34: PRJ005 | B34: =IFERROR(VLOOKUP(A34,Projects!$A:$AK,2,FALSE()),"") | C34: =IFERROR(VLOOKUP(A34,Projects!$A:$AK,14,FALSE()),"") | D34: Discovery | E34: =IFERROR(INDEX(_Stages!$A$1:$A$8,MIN(MATCH(D34,_Stages!$A$1:$A$8,0)+1,8)),"") | F34: Approved | G34: Complete | H34: CFO | I34: 45860 | J34: 45862 | K34: Held | M34: 100 | N34: 2 | O34: =A34&"|"&D34
A35: PRJ005 | B35: =IFERROR(VLOOKUP(A35,Projects!$A:$AK,2,FALSE()),"") | C35: =IFERROR(VLOOKUP(A35,Projects!$A:$AK,14,FALSE()),"") | D35: Business Case / Seed Funding | E35: =IFERROR(INDEX(_Stages!$A$1:$A$8,MIN(MATCH(D35,_Stages!$A$1:$A$8,0)+1,8)),"") | F35: Approved | G35: Complete | H35: CFO | I35: 45920 | J35: 45928 | K35: Held | L35: On track | M35: 100 | N35: 8 | O35: =A35&"|"&D35
A36: PRJ005 | B36: =IFERROR(VLOOKUP(A36,Projects!$A:$AK,2,FALSE()),"") | C36: =IFERROR(VLOOKUP(A36,Projects!$A:$AK,14,FALSE()),"") | D36: Design | E36: =IFERROR(INDEX(_Stages!$A$1:$A$8,MIN(MATCH(D36,_Stages!$A$1:$A$8,0)+1,8)),"") | F36: Approved | G36: Complete | H36: CFO | I36: 45980 | J36: 46001 | K36: Conditional | L36: Approved with conditions | M36: 100 | N36: 21 | O36: =A36&"|"&D36
A37: PRJ005 | B37: =IFERROR(VLOOKUP(A37,Projects!$A:$AK,2,FALSE()),"") | C37: =IFERROR(VLOOKUP(A37,Projects!$A:$AK,14,FALSE()),"") | D37: Business Case / Full Funding | E37: =IFERROR(INDEX(_Stages!$A$1:$A$8,MIN(MATCH(D37,_Stages!$A$1:$A$8,0)+1,8)),"") | F37: Approved | G37: Complete | H37: CFO | I37: 46040 | J37: 46044 | K37: Proceed | M37: 100 | N37: 4 | O37: =A37&"|"&D37
A38: PRJ005 | B38: =IFERROR(VLOOKUP(A38,Projects!$A:$AK,2,FALSE()),"") | C38: =IFERROR(VLOOKUP(A38,Projects!$A:$AK,14,FALSE()),"") | D38: Build | E38: =IFERROR(INDEX(_Stages!$A$1:$A$8,MIN(MATCH(D38,_Stages!$A$1:$A$8,0)+1,8)),"") | F38: Approved | G38: Complete | H38: CFO | I38: 46100 | J38: 46090 | K38: Held | L38: On track | M38: 100 | N38: 0 | O38: =A38&"|"&D38
A39: PRJ005 | B39: =IFERROR(VLOOKUP(A39,Projects!$A:$AK,2,FALSE()),"") | C39: =IFERROR(VLOOKUP(A39,Projects!$A:$AK,14,FALSE()),"") | D39: Testing | E39: =IFERROR(INDEX(_Stages!$A$1:$A$8,MIN(MATCH(D39,_Stages!$A$1:$A$8,0)+1,8)),"") | F39: In Progress | G39: In Progress | H39: CFO | I39: 46160 | M39: 80 | N39: 0 | O39: =A39&"|"&D39
A40: PRJ005 | B40: =IFERROR(VLOOKUP(A40,Projects!$A:$AK,2,FALSE()),"") | C40: =IFERROR(VLOOKUP(A40,Projects!$A:$AK,14,FALSE()),"") | D40: Deployment | E40: =IFERROR(INDEX(_Stages!$A$1:$A$8,MIN(MATCH(D40,_Stages!$A$1:$A$8,0)+1,8)),"") | F40: Not Started | G40: Not Started | H40: CFO | I40: 46220 | L40: Approved with conditions | M40: 0 | N40: 0 | O40: =A40&"|"&D40
A41: PRJ005 | B41: =IFERROR(VLOOKUP(A41,Projects!$A:$AK,2,FALSE()),"") | C41: =IFERROR(VLOOKUP(A41,Projects!$A:$AK,14,FALSE()),"") | D41: Handover | E41: =IFERROR(INDEX(_Stages!$A$1:$A$8,MIN(MATCH(D41,_Stages!$A$1:$A$8,0)+1,8)),"") | F41: Not Started | G41: Not Started | H41: CFO | I41: 46280 | L41: On track | M41: 0 | N41: 0 | O41: =A41&"|"&D41
A42: PRJ006 | B42: =IFERROR(VLOOKUP(A42,Projects!$A:$AK,2,FALSE()),"") | C42: =IFERROR(VLOOKUP(A42,Projects!$A:$AK,14,FALSE()),"") | D42: Discovery | E42: =IFERROR(INDEX(_Stages!$A$1:$A$8,MIN(MATCH(D42,_Stages!$A$1:$A$8,0)+1,8)),"") | F42: Approved | G42: Complete | H42: CMO | I42: 45736 | J42: 45762 | K42: Rework | M42: 100 | N42: 26 | O42: =A42&"|"&D42
A43: PRJ006 | B43: =IFERROR(VLOOKUP(A43,Projects!$A:$AK,2,FALSE()),"") | C43: =IFERROR(VLOOKUP(A43,Projects!$A:$AK,14,FALSE()),"") | D43: Business Case / Seed Funding | E43: =IFERROR(INDEX(_Stages!$A$1:$A$8,MIN(MATCH(D43,_Stages!$A$1:$A$8,0)+1,8)),"") | F43: Approved | G43: Complete | H43: CMO | I43: 45796 | J43: 45814 | K43: Proceed | L43: Approved with conditions | M43: 100 | N43: 18 | O43: =A43&"|"&D43
A44: PRJ006 | B44: =IFERROR(VLOOKUP(A44,Projects!$A:$AK,2,FALSE()),"") | C44: =IFERROR(VLOOKUP(A44,Projects!$A:$AK,14,FALSE()),"") | D44: Design | E44: =IFERROR(INDEX(_Stages!$A$1:$A$8,MIN(MATCH(D44,_Stages!$A$1:$A$8,0)+1,8)),"") | F44: Approved | G44: Complete | H44: CMO | I44: 45856 | J44: 45854 | K44: Held | L44: Awaiting sponsor sign-off | M44: 100 | N44: 0 | O44: =A44&"|"&D44
A45: PRJ006 | B45: =IFERROR(VLOOKUP(A45,Projects!$A:$AK,2,FALSE()),"") | C45: =IFERROR(VLOOKUP(A45,Projects!$A:$AK,14,FALSE()),"") | D45: Business Case / Full Funding | E45: =IFERROR(INDEX(_Stages!$A$1:$A$8,MIN(MATCH(D45,_Stages!$A$1:$A$8,0)+1,8)),"") | F45: Approved | G45: Complete | H45: CMO | I45: 45916 | J45: 45903 | K45: Proceed | L45: Awaiting sponsor sign-off | M45: 100 | N45: 0 | O45: =A45&"|"&D45
A46: PRJ006 | B46: =IFERROR(VLOOKUP(A46,Projects!$A:$AK,2,FALSE()),"") | C46: =IFERROR(VLOOKUP(A46,Projects!$A:$AK,14,FALSE()),"") | D46: Build | E46: =IFERROR(INDEX(_Stages!$A$1:$A$8,MIN(MATCH(D46,_Stages!$A$1:$A$8,0)+1,8)),"") | F46: Approved | G46: Complete | H46: CMO | I46: 45976 | J46: 45995 | K46: Proceed | L46: Approved with conditions | M46: 100 | N46: 19 | O46: =A46&"|"&D46
A47: PRJ006 | B47: =IFERROR(VLOOKUP(A47,Projects!$A:$AK,2,FALSE()),"") | C47: =IFERROR(VLOOKUP(A47,Projects!$A:$AK,14,FALSE()),"") | D47: Testing | E47: =IFERROR(INDEX(_Stages!$A$1:$A$8,MIN(MATCH(D47,_Stages!$A$1:$A$8,0)+1,8)),"") | F47: Approved | G47: Complete | H47: CMO | I47: 46036 | J47: 46041 | K47: Proceed | L47: Approved with conditions | M47: 100 | N47: 5 | O47: =A47&"|"&D47
A48: PRJ006 | B48: =IFERROR(VLOOKUP(A48,Projects!$A:$AK,2,FALSE()),"") | C48: =IFERROR(VLOOKUP(A48,Projects!$A:$AK,14,FALSE()),"") | D48: Deployment | E48: =IFERROR(INDEX(_Stages!$A$1:$A$8,MIN(MATCH(D48,_Stages!$A$1:$A$8,0)+1,8)),"") | F48: Pending Approval | G48: In Progress | H48: CMO | I48: 46096 | L48: On track | M48: 44 | N48: 0 | O48: =A48&"|"&D48
A49: PRJ006 | B49: =IFERROR(VLOOKUP(A49,Projects!$A:$AK,2,FALSE()),"") | C49: =IFERROR(VLOOKUP(A49,Projects!$A:$AK,14,FALSE()),"") | D49: Handover | E49: =IFERROR(INDEX(_Stages!$A$1:$A$8,MIN(MATCH(D49,_Stages!$A$1:$A$8,0)+1,8)),"") | F49: Not Started | G49: Not Started | H49: CMO | I49: 46156 | L49: Approved with conditions | M49: 0 | N49: 0 | O49: =A49&"|"&D49
A50: PRJ007 | B50: =IFERROR(VLOOKUP(A50,Projects!$A:$AK,2,FALSE()),"") | C50: =IFERROR(VLOOKUP(A50,Projects!$A:$AK,14,FALSE()),"") | D50: Discovery | E50: =IFERROR(INDEX(_Stages!$A$1:$A$8,MIN(MATCH(D50,_Stages!$A$1:$A$8,0)+1,8)),"") | F50: Approved | G50: Complete | H50: CTO | I50: 45792 | J50: 45813 | K50: Held | L50: Awaiting sponsor sign-off | M50: 100 | N50: 21 | O50: =A50&"|"&D50
A51: PRJ007 | B51: =IFERROR(VLOOKUP(A51,Projects!$A:$AK,2,FALSE()),"") | C51: =IFERROR(VLOOKUP(A51,Projects!$A:$AK,14,FALSE()),"") | D51: Business Case / Seed Funding | E51: =IFERROR(INDEX(_Stages!$A$1:$A$8,MIN(MATCH(D51,_Stages!$A$1:$A$8,0)+1,8)),"") | F51: Approved | G51: Complete | H51: CTO | I51: 45852 | J51: 45861 | K51: Conditional | M51: 100 | N51: 9 | O51: =A51&"|"&D51
A52: PRJ007 | B52: =IFERROR(VLOOKUP(A52,Projects!$A:$AK,2,FALSE()),"") | C52: =IFERROR(VLOOKUP(A52,Projects!$A:$AK,14,FALSE()),"") | D52: Design | E52: =IFERROR(INDEX(_Stages!$A$1:$A$8,MIN(MATCH(D52,_Stages!$A$1:$A$8,0)+1,8)),"") | F52: Approved | G52: Complete | H52: CTO | I52: 45912 | J52: 45929 | K52: Rework | M52: 100 | N52: 17 | O52: =A52&"|"&D52
A53: PRJ007 | B53: =IFERROR(VLOOKUP(A53,Projects!$A:$AK,2,FALSE()),"") | C53: =IFERROR(VLOOKUP(A53,Projects!$A:$AK,14,FALSE()),"") | D53: Business Case / Full Funding | E53: =IFERROR(INDEX(_Stages!$A$1:$A$8,MIN(MATCH(D53,_Stages!$A$1:$A$8,0)+1,8)),"") | F53: In Progress | G53: In Progress | H53: CTO | I53: 45972 | L53: Approved with conditions | M53: 93 | N53: 0 | O53: =A53&"|"&D53
A54: PRJ007 | B54: =IFERROR(VLOOKUP(A54,Projects!$A:$AK,2,FALSE()),"") | C54: =IFERROR(VLOOKUP(A54,Projects!$A:$AK,14,FALSE()),"") | D54: Build | E54: =IFERROR(INDEX(_Stages!$A$1:$A$8,MIN(MATCH(D54,_Stages!$A$1:$A$8,0)+1,8)),"") | F54: Not Started | G54: Not Started | H54: CTO | I54: 46032 | L54: Awaiting sponsor sign-off | M54: 0 | N54: 0 | O54: =A54&"|"&D54
A55: PRJ007 | B55: =IFERROR(VLOOKUP(A55,Projects!$A:$AK,2,FALSE()),"") | C55: =IFERROR(VLOOKUP(A55,Projects!$A:$AK,14,FALSE()),"") | D55: Testing | E55: =IFERROR(INDEX(_Stages!$A$1:$A$8,MIN(MATCH(D55,_Stages!$A$1:$A$8,0)+1,8)),"") | F55: Not Started | G55: Not Started | H55: CTO | I55: 46092 | L55: On track | M55: 0 | N55: 0 | O55: =A55&"|"&D55
A56: PRJ007 | B56: =IFERROR(VLOOKUP(A56,Projects!$A:$AK,2,FALSE()),"") | C56: =IFERROR(VLOOKUP(A56,Projects!$A:$AK,14,FALSE()),"") | D56: Deployment | E56: =IFERROR(INDEX(_Stages!$A$1:$A$8,MIN(MATCH(D56,_Stages!$A$1:$A$8,0)+1,8)),"") | F56: Not Started | G56: Not Started | H56: CTO | I56: 46152 | M56: 0 | N56: 0 | O56: =A56&"|"&D56
A57: PRJ007 | B57: =IFERROR(VLOOKUP(A57,Projects!$A:$AK,2,FALSE()),"") | C57: =IFERROR(VLOOKUP(A57,Projects!$A:$AK,14,FALSE()),"") | D57: Handover | E57: =IFERROR(INDEX(_Stages!$A$1:$A$8,MIN(MATCH(D57,_Stages!$A$1:$A$8,0)+1,8)),"") | F57: Not Started | G57: Not Started | H57: CTO | I57: 46212 | L57: Awaiting sponsor sign-off | M57: 0 | N57: 0 | O57: =A57&"|"&D57
A58: PRJ008 | B58: =IFERROR(VLOOKUP(A58,Projects!$A:$AK,2,FALSE()),"") | C58: =IFERROR(VLOOKUP(A58,Projects!$A:$AK,14,FALSE()),"") | D58: Discovery | E58: =IFERROR(INDEX(_Stages!$A$1:$A$8,MIN(MATCH(D58,_Stages!$A$1:$A$8,0)+1,8)),"") | F58: Approved | G58: Complete | H58: CTO | I58: 45780 | J58: 45796 | K58: Conditional | L58: Awaiting sponsor sign-off | M58: 100 | N58: 16 | O58: =A58&"|"&D58
A59: PRJ008 | B59: =IFERROR(VLOOKUP(A59,Projects!$A:$AK,2,FALSE()),"") | C59: =IFERROR(VLOOKUP(A59,Projects!$A:$AK,14,FALSE()),"") | D59: Business Case / Seed Funding | E59: =IFERROR(INDEX(_Stages!$A$1:$A$8,MIN(MATCH(D59,_Stages!$A$1:$A$8,0)+1,8)),"") | F59: Approved | G59: Complete | H59: CTO | I59: 45840 | J59: 45860 | K59: Held | L59: On track | M59: 100 | N59: 20 | O59: =A59&"|"&D59
A60: PRJ008 | B60: =IFERROR(VLOOKUP(A60,Projects!$A:$AK,2,FALSE()),"") | C60: =IFERROR(VLOOKUP(A60,Projects!$A:$AK,14,FALSE()),"") | D60: Design | E60: =IFERROR(INDEX(_Stages!$A$1:$A$8,MIN(MATCH(D60,_Stages!$A$1:$A$8,0)+1,8)),"") | F60: Approved | G60: Complete | H60: CTO | I60: 45900 | J60: 45896 | K60: Held | M60: 100 | N60: 0 | O60: =A60&"|"&D60
A61: PRJ008 | B61: =IFERROR(VLOOKUP(A61,Projects!$A:$AK,2,FALSE()),"") | C61: =IFERROR(VLOOKUP(A61,Projects!$A:$AK,14,FALSE()),"") | D61: Business Case / Full Funding | E61: =IFERROR(INDEX(_Stages!$A$1:$A$8,MIN(MATCH(D61,_Stages!$A$1:$A$8,0)+1,8)),"") | F61: Approved | G61: Complete | H61: CTO | I61: 45960 | J61: 45984 | K61: Rework | L61: Approved with conditions | M61: 100 | N61: 24 | O61: =A61&"|"&D61
A62: PRJ008 | B62: =IFERROR(VLOOKUP(A62,Projects!$A:$AK,2,FALSE()),"") | C62: =IFERROR(VLOOKUP(A62,Projects!$A:$AK,14,FALSE()),"") | D62: Build | E62: =IFERROR(INDEX(_Stages!$A$1:$A$8,MIN(MATCH(D62,_Stages!$A$1:$A$8,0)+1,8)),"") | F62: Approved | G62: Complete | H62: CTO | I62: 46020 | J62: 46050 | K62: Proceed | M62: 100 | N62: 30 | O62: =A62&"|"&D62
A63: PRJ008 | B63: =IFERROR(VLOOKUP(A63,Projects!$A:$AK,2,FALSE()),"") | C63: =IFERROR(VLOOKUP(A63,Projects!$A:$AK,14,FALSE()),"") | D63: Testing | E63: =IFERROR(INDEX(_Stages!$A$1:$A$8,MIN(MATCH(D63,_Stages!$A$1:$A$8,0)+1,8)),"") | F63: Approved | G63: Complete | H63: CTO | I63: 46080 | J63: 46082 | K63: Conditional | L63: On track | M63: 100 | N63: 2 | O63: =A63&"|"&D63
A64: PRJ008 | B64: =IFERROR(VLOOKUP(A64,Projects!$A:$AK,2,FALSE()),"") | C64: =IFERROR(VLOOKUP(A64,Projects!$A:$AK,14,FALSE()),"") | D64: Deployment | E64: =IFERROR(INDEX(_Stages!$A$1:$A$8,MIN(MATCH(D64,_Stages!$A$1:$A$8,0)+1,8)),"") | F64: Approved | G64: Complete | H64: CTO | I64: 46140 | J64: 46170 | K64: Conditional | L64: On track | M64: 100 | N64: 30 | O64: =A64&"|"&D64
A65: PRJ008 | B65: =IFERROR(VLOOKUP(A65,Projects!$A:$AK,2,FALSE()),"") | C65: =IFERROR(VLOOKUP(A65,Projects!$A:$AK,14,FALSE()),"") | D65: Handover | E65: =IFERROR(INDEX(_Stages!$A$1:$A$8,MIN(MATCH(D65,_Stages!$A$1:$A$8,0)+1,8)),"") | F65: In Progress | G65: In Progress | H65: CTO | I65: 46200 | M65: 45 | N65: 0 | O65: =A65&"|"&D65
A66: PRJ009 | B66: =IFERROR(VLOOKUP(A66,Projects!$A:$AK,2,FALSE()),"") | C66: =IFERROR(VLOOKUP(A66,Projects!$A:$AK,14,FALSE()),"") | D66: Discovery | E66: =IFERROR(INDEX(_Stages!$A$1:$A$8,MIN(MATCH(D66,_Stages!$A$1:$A$8,0)+1,8)),"") | F66: In Progress | G66: In Progress | H66: CFO | I66: 46023 | L66: Awaiting sponsor sign-off | M66: 88 | N66: 0 | O66: =A66&"|"&D66
A67: PRJ009 | B67: =IFERROR(VLOOKUP(A67,Projects!$A:$AK,2,FALSE()),"") | C67: =IFERROR(VLOOKUP(A67,Projects!$A:$AK,14,FALSE()),"") | D67: Business Case / Seed Funding | E67: =IFERROR(INDEX(_Stages!$A$1:$A$8,MIN(MATCH(D67,_Stages!$A$1:$A$8,0)+1,8)),"") | F67: Not Started | G67: Not Started | H67: CFO | I67: 46083 | M67: 0 | N67: 0 | O67: =A67&"|"&D67
A68: PRJ009 | B68: =IFERROR(VLOOKUP(A68,Projects!$A:$AK,2,FALSE()),"") | C68: =IFERROR(VLOOKUP(A68,Projects!$A:$AK,14,FALSE()),"") | D68: Design | E68: =IFERROR(INDEX(_Stages!$A$1:$A$8,MIN(MATCH(D68,_Stages!$A$1:$A$8,0)+1,8)),"") | F68: Not Started | G68: Not Started | H68: CFO | I68: 46143 | M68: 0 | N68: 0 | O68: =A68&"|"&D68
A69: PRJ009 | B69: =IFERROR(VLOOKUP(A69,Projects!$A:$AK,2,FALSE()),"") | C69: =IFERROR(VLOOKUP(A69,Projects!$A:$AK,14,FALSE()),"") | D69: Business Case / Full Funding | E69: =IFERROR(INDEX(_Stages!$A$1:$A$8,MIN(MATCH(D69,_Stages!$A$1:$A$8,0)+1,8)),"") | F69: Not Started | G69: Not Started | H69: CFO | I69: 46203 | L69: On track | M69: 0 | N69: 0 | O69: =A69&"|"&D69
A70: PRJ009 | B70: =IFERROR(VLOOKUP(A70,Projects!$A:$AK,2,FALSE()),"") | C70: =IFERROR(VLOOKUP(A70,Projects!$A:$AK,14,FALSE()),"") | D70: Build | E70: =IFERROR(INDEX(_Stages!$A$1:$A$8,MIN(MATCH(D70,_Stages!$A$1:$A$8,0)+1,8)),"") | F70: Not Started | G70: Not Started | H70: CFO | I70: 46263 | L70: On track | M70: 0 | N70: 0 | O70: =A70&"|"&D70
A71: PRJ009 | B71: =IFERROR(VLOOKUP(A71,Projects!$A:$AK,2,FALSE()),"") | C71: =IFERROR(VLOOKUP(A71,Projects!$A:$AK,14,FALSE()),"") | D71: Testing | E71: =IFERROR(INDEX(_Stages!$A$1:$A$8,MIN(MATCH(D71,_Stages!$A$1:$A$8,0)+1,8)),"") | F71: Not Started | G71: Not Started | H71: CFO | I71: 46323 | M71: 0 | N71: 0 | O71: =A71&"|"&D71
A72: PRJ009 | B72: =IFERROR(VLOOKUP(A72,Projects!$A:$AK,2,FALSE()),"") | C72: =IFERROR(VLOOKUP(A72,Projects!$A:$AK,14,FALSE()),"") | D72: Deployment | E72: =IFERROR(INDEX(_Stages!$A$1:$A$8,MIN(MATCH(D72,_Stages!$A$1:$A$8,0)+1,8)),"") | F72: Not Started | G72: Not Started | H72: CFO | I72: 46383 | L72: Awaiting sponsor sign-off | M72: 0 | N72: 0 | O72: =A72&"|"&D72
A73: PRJ009 | B73: =IFERROR(VLOOKUP(A73,Projects!$A:$AK,2,FALSE()),"") | C73: =IFERROR(VLOOKUP(A73,Projects!$A:$AK,14,FALSE()),"") | D73: Handover | E73: =IFERROR(INDEX(_Stages!$A$1:$A$8,MIN(MATCH(D73,_Stages!$A$1:$A$8,0)+1,8)),"") | F73: Not Started | G73: Not Started | H73: CFO | I73: 46443 | M73: 0 | N73: 0 | O73: =A73&"|"&D73
A74: PRJ010 | B74: =IFERROR(VLOOKUP(A74,Projects!$A:$AK,2,FALSE()),"") | C74: =IFERROR(VLOOKUP(A74,Projects!$A:$AK,14,FALSE()),"") | D74: Discovery | E74: =IFERROR(INDEX(_Stages!$A$1:$A$8,MIN(MATCH(D74,_Stages!$A$1:$A$8,0)+1,8)),"") | F74: Approved | G74: Complete | H74: CFO | I74: 45694 | J74: 45703 | K74: Proceed | L74: Awaiting sponsor sign-off | M74: 100 | N74: 9 | O74: =A74&"|"&D74
A75: PRJ010 | B75: =IFERROR(VLOOKUP(A75,Projects!$A:$AK,2,FALSE()),"") | C75: =IFERROR(VLOOKUP(A75,Projects!$A:$AK,14,FALSE()),"") | D75: Business Case / Seed Funding | E75: =IFERROR(INDEX(_Stages!$A$1:$A$8,MIN(MATCH(D75,_Stages!$A$1:$A$8,0)+1,8)),"") | F75: Approved | G75: Complete | H75: CFO | I75: 45754 | J75: 45765 | K75: Held | M75: 100 | N75: 11 | O75: =A75&"|"&D75
A76: PRJ010 | B76: =IFERROR(VLOOKUP(A76,Projects!$A:$AK,2,FALSE()),"") | C76: =IFERROR(VLOOKUP(A76,Projects!$A:$AK,14,FALSE()),"") | D76: Design | E76: =IFERROR(INDEX(_Stages!$A$1:$A$8,MIN(MATCH(D76,_Stages!$A$1:$A$8,0)+1,8)),"") | F76: Approved | G76: Complete | H76: CFO | I76: 45814 | J76: 45834 | K76: Conditional | L76: Approved with conditions | M76: 100 | N76: 20 | O76: =A76&"|"&D76
A77: PRJ010 | B77: =IFERROR(VLOOKUP(A77,Projects!$A:$AK,2,FALSE()),"") | C77: =IFERROR(VLOOKUP(A77,Projects!$A:$AK,14,FALSE()),"") | D77: Business Case / Full Funding | E77: =IFERROR(INDEX(_Stages!$A$1:$A$8,MIN(MATCH(D77,_Stages!$A$1:$A$8,0)+1,8)),"") | F77: Approved | G77: Complete | H77: CFO | I77: 45874 | J77: 45902 | K77: Held | L77: Approved with conditions | M77: 100 | N77: 28 | O77: =A77&"|"&D77
A78: PRJ010 | B78: =IFERROR(VLOOKUP(A78,Projects!$A:$AK,2,FALSE()),"") | C78: =IFERROR(VLOOKUP(A78,Projects!$A:$AK,14,FALSE()),"") | D78: Build | E78: =IFERROR(INDEX(_Stages!$A$1:$A$8,MIN(MATCH(D78,_Stages!$A$1:$A$8,0)+1,8)),"") | F78: Approved | G78: Complete | H78: CFO | I78: 45934 | J78: 45927 | K78: Rework | L78: Awaiting sponsor sign-off | M78: 100 | N78: 0 | O78: =A78&"|"&D78
A79: PRJ010 | B79: =IFERROR(VLOOKUP(A79,Projects!$A:$AK,2,FALSE()),"") | C79: =IFERROR(VLOOKUP(A79,Projects!$A:$AK,14,FALSE()),"") | D79: Testing | E79: =IFERROR(INDEX(_Stages!$A$1:$A$8,MIN(MATCH(D79,_Stages!$A$1:$A$8,0)+1,8)),"") | F79: In Progress | G79: In Progress | H79: CFO | I79: 45994 | L79: Approved with conditions | M79: 44 | N79: 0 | O79: =A79&"|"&D79
A80: PRJ010 | B80: =IFERROR(VLOOKUP(A80,Projects!$A:$AK,2,FALSE()),"") | C80: =IFERROR(VLOOKUP(A80,Projects!$A:$AK,14,FALSE()),"") | D80: Deployment | E80: =IFERROR(INDEX(_Stages!$A$1:$A$8,MIN(MATCH(D80,_Stages!$A$1:$A$8,0)+1,8)),"") | F80: Not Started | G80: Not Started | H80: CFO | I80: 46054 | L80: On track | M80: 0 | N80: 0 | O80: =A80&"|"&D80
A81: PRJ010 | B81: =IFERROR(VLOOKUP(A81,Projects!$A:$AK,2,FALSE()),"") | C81: =IFERROR(VLOOKUP(A81,Projects!$A:$AK,14,FALSE()),"") | D81: Handover | E81: =IFERROR(INDEX(_Stages!$A$1:$A$8,MIN(MATCH(D81,_Stages!$A$1:$A$8,0)+1,8)),"") | F81: Not Started | G81: Not Started | H81: CFO | I81: 46114 | L81: On track | M81: 0 | N81: 0 | O81: =A81&"|"&D81
A82: PRJ011 | B82: =IFERROR(VLOOKUP(A82,Projects!$A:$AK,2,FALSE()),"") | C82: =IFERROR(VLOOKUP(A82,Projects!$A:$AK,14,FALSE()),"") | D82: Discovery | E82: =IFERROR(INDEX(_Stages!$A$1:$A$8,MIN(MATCH(D82,_Stages!$A$1:$A$8,0)+1,8)),"") | F82: Approved | G82: Complete | H82: CFO | I82: 45988 | J82: 46003 | K82: Proceed | L82: Awaiting sponsor sign-off | M82: 100 | N82: 15 | O82: =A82&"|"&D82
A83: PRJ011 | B83: =IFERROR(VLOOKUP(A83,Projects!$A:$AK,2,FALSE()),"") | C83: =IFERROR(VLOOKUP(A83,Projects!$A:$AK,14,FALSE()),"") | D83: Business Case / Seed Funding | E83: =IFERROR(INDEX(_Stages!$A$1:$A$8,MIN(MATCH(D83,_Stages!$A$1:$A$8,0)+1,8)),"") | F83: Approved | G83: Complete | H83: CFO | I83: 46048 | J83: 46049 | K83: Conditional | L83: On track | M83: 100 | N83: 1 | O83: =A83&"|"&D83
A84: PRJ011 | B84: =IFERROR(VLOOKUP(A84,Projects!$A:$AK,2,FALSE()),"") | C84: =IFERROR(VLOOKUP(A84,Projects!$A:$AK,14,FALSE()),"") | D84: Design | E84: =IFERROR(INDEX(_Stages!$A$1:$A$8,MIN(MATCH(D84,_Stages!$A$1:$A$8,0)+1,8)),"") | F84: Approved | G84: Complete | H84: CFO | I84: 46108 | J84: 46131 | K84: Conditional | L84: On track | M84: 100 | N84: 23 | O84: =A84&"|"&D84
A85: PRJ011 | B85: =IFERROR(VLOOKUP(A85,Projects!$A:$AK,2,FALSE()),"") | C85: =IFERROR(VLOOKUP(A85,Projects!$A:$AK,14,FALSE()),"") | D85: Business Case / Full Funding | E85: =IFERROR(INDEX(_Stages!$A$1:$A$8,MIN(MATCH(D85,_Stages!$A$1:$A$8,0)+1,8)),"") | F85: Approved | G85: Complete | H85: CFO | I85: 46168 | J85: 46159 | K85: Conditional | L85: Awaiting sponsor sign-off | M85: 100 | N85: 0 | O85: =A85&"|"&D85
A86: PRJ011 | B86: =IFERROR(VLOOKUP(A86,Projects!$A:$AK,2,FALSE()),"") | C86: =IFERROR(VLOOKUP(A86,Projects!$A:$AK,14,FALSE()),"") | D86: Build | E86: =IFERROR(INDEX(_Stages!$A$1:$A$8,MIN(MATCH(D86,_Stages!$A$1:$A$8,0)+1,8)),"") | F86: In Progress | G86: In Progress | H86: CFO | I86: 46228 | L86: Awaiting sponsor sign-off | M86: 93 | N86: 0 | O86: =A86&"|"&D86
A87: PRJ011 | B87: =IFERROR(VLOOKUP(A87,Projects!$A:$AK,2,FALSE()),"") | C87: =IFERROR(VLOOKUP(A87,Projects!$A:$AK,14,FALSE()),"") | D87: Testing | E87: =IFERROR(INDEX(_Stages!$A$1:$A$8,MIN(MATCH(D87,_Stages!$A$1:$A$8,0)+1,8)),"") | F87: Not Started | G87: Not Started | H87: CFO | I87: 46288 | L87: On track | M87: 0 | N87: 0 | O87: =A87&"|"&D87
A88: PRJ011 | B88: =IFERROR(VLOOKUP(A88,Projects!$A:$AK,2,FALSE()),"") | C88: =IFERROR(VLOOKUP(A88,Projects!$A:$AK,14,FALSE()),"") | D88: Deployment | E88: =IFERROR(INDEX(_Stages!$A$1:$A$8,MIN(MATCH(D88,_Stages!$A$1:$A$8,0)+1,8)),"") | F88: Not Started | G88: Not Started | H88: CFO | I88: 46348 | L88: On track | M88: 0 | N88: 0 | O88: =A88&"|"&D88
A89: PRJ011 | B89: =IFERROR(VLOOKUP(A89,Projects!$A:$AK,2,FALSE()),"") | C89: =IFERROR(VLOOKUP(A89,Projects!$A:$AK,14,FALSE()),"") | D89: Handover | E89: =IFERROR(INDEX(_Stages!$A$1:$A$8,MIN(MATCH(D89,_Stages!$A$1:$A$8,0)+1,8)),"") | F89: Not Started | G89: Not Started | H89: CFO | I89: 46408 | L89: On track | M89: 0 | N89: 0 | O89: =A89&"|"&D89
A90: PRJ012 | B90: =IFERROR(VLOOKUP(A90,Projects!$A:$AK,2,FALSE()),"") | C90: =IFERROR(VLOOKUP(A90,Projects!$A:$AK,14,FALSE()),"") | D90: Discovery | E90: =IFERROR(INDEX(_Stages!$A$1:$A$8,MIN(MATCH(D90,_Stages!$A$1:$A$8,0)+1,8)),"") | F90: Approved | G90: Complete | H90: CMO | I90: 45934 | J90: 45938 | K90: Rework | L90: Approved with conditions | M90: 100 | N90: 4 | O90: =A90&"|"&D90
A91: PRJ012 | B91: =IFERROR(VLOOKUP(A91,Projects!$A:$AK,2,FALSE()),"") | C91: =IFERROR(VLOOKUP(A91,Projects!$A:$AK,14,FALSE()),"") | D91: Business Case / Seed Funding | E91: =IFERROR(INDEX(_Stages!$A$1:$A$8,MIN(MATCH(D91,_Stages!$A$1:$A$8,0)+1,8)),"") | F91: Approved | G91: Complete | H91: CMO | I91: 45994 | J91: 46009 | K91: Rework | L91: Approved with conditions | M91: 100 | N91: 15 | O91: =A91&"|"&D91
A92: PRJ012 | B92: =IFERROR(VLOOKUP(A92,Projects!$A:$AK,2,FALSE()),"") | C92: =IFERROR(VLOOKUP(A92,Projects!$A:$AK,14,FALSE()),"") | D92: Design | E92: =IFERROR(INDEX(_Stages!$A$1:$A$8,MIN(MATCH(D92,_Stages!$A$1:$A$8,0)+1,8)),"") | F92: In Progress | G92: In Progress | H92: CMO | I92: 46054 | L92: Awaiting sponsor sign-off | M92: 87 | N92: 0 | O92: =A92&"|"&D92
A93: PRJ012 | B93: =IFERROR(VLOOKUP(A93,Projects!$A:$AK,2,FALSE()),"") | C93: =IFERROR(VLOOKUP(A93,Projects!$A:$AK,14,FALSE()),"") | D93: Business Case / Full Funding | E93: =IFERROR(INDEX(_Stages!$A$1:$A$8,MIN(MATCH(D93,_Stages!$A$1:$A$8,0)+1,8)),"") | F93: Not Started | G93: Not Started | H93: CMO | I93: 46114 | L93: On track | M93: 0 | N93: 0 | O93: =A93&"|"&D93
A94: PRJ012 | B94: =IFERROR(VLOOKUP(A94,Projects!$A:$AK,2,FALSE()),"") | C94: =IFERROR(VLOOKUP(A94,Projects!$A:$AK,14,FALSE()),"") | D94: Build | E94: =IFERROR(INDEX(_Stages!$A$1:$A$8,MIN(MATCH(D94,_Stages!$A$1:$A$8,0)+1,8)),"") | F94: Not Started | G94: Not Started | H94: CMO | I94: 46174 | L94: Approved with conditions | M94: 0 | N94: 0 | O94: =A94&"|"&D94
A95: PRJ012 | B95: =IFERROR(VLOOKUP(A95,Projects!$A:$AK,2,FALSE()),"") | C95: =IFERROR(VLOOKUP(A95,Projects!$A:$AK,14,FALSE()),"") | D95: Testing | E95: =IFERROR(INDEX(_Stages!$A$1:$A$8,MIN(MATCH(D95,_Stages!$A$1:$A$8,0)+1,8)),"") | F95: Not Started | G95: Not Started | H95: CMO | I95: 46234 | L95: On track | M95: 0 | N95: 0 | O95: =A95&"|"&D95
A96: PRJ012 | B96: =IFERROR(VLOOKUP(A96,Projects!$A:$AK,2,FALSE()),"") | C96: =IFERROR(VLOOKUP(A96,Projects!$A:$AK,14,FALSE()),"") | D96: Deployment | E96: =IFERROR(INDEX(_Stages!$A$1:$A$8,MIN(MATCH(D96,_Stages!$A$1:$A$8,0)+1,8)),"") | F96: Not Started | G96: Not Started | H96: CMO | I96: 46294 | L96: On track | M96: 0 | N96: 0 | O96: =A96&"|"&D96
A97: PRJ012 | B97: =IFERROR(VLOOKUP(A97,Projects!$A:$AK,2,FALSE()),"") | C97: =IFERROR(VLOOKUP(A97,Projects!$A:$AK,14,FALSE()),"") | D97: Handover | E97: =IFERROR(INDEX(_Stages!$A$1:$A$8,MIN(MATCH(D97,_Stages!$A$1:$A$8,0)+1,8)),"") | F97: Not Started | G97: Not Started | H97: CMO | I97: 46354 | M97: 0 | N97: 0 | O97: =A97&"|"&D97
A98: PRJ013 | B98: =IFERROR(VLOOKUP(A98,Projects!$A:$AK,2,FALSE()),"") | C98: =IFERROR(VLOOKUP(A98,Projects!$A:$AK,14,FALSE()),"") | D98: Discovery | E98: =IFERROR(INDEX(_Stages!$A$1:$A$8,MIN(MATCH(D98,_Stages!$A$1:$A$8,0)+1,8)),"") | F98: Approved | G98: Complete | H98: CTO | I98: 45996 | J98: 46018 | K98: Conditional | M98: 100 | N98: 22 | O98: =A98&"|"&D98
A99: PRJ013 | B99: =IFERROR(VLOOKUP(A99,Projects!$A:$AK,2,FALSE()),"") | C99: =IFERROR(VLOOKUP(A99,Projects!$A:$AK,14,FALSE()),"") | D99: Business Case / Seed Funding | E99: =IFERROR(INDEX(_Stages!$A$1:$A$8,MIN(MATCH(D99,_Stages!$A$1:$A$8,0)+1,8)),"") | F99: Approved | G99: Complete | H99: CTO | I99: 46056 | J99: 46070 | K99: Conditional | L99: On track | M99: 100 | N99: 14 | O99: =A99&"|"&D99
A100: PRJ013 | B100: =IFERROR(VLOOKUP(A100,Projects!$A:$AK,2,FALSE()),"") | C100: =IFERROR(VLOOKUP(A100,Projects!$A:$AK,14,FALSE()),"") | D100: Design | E100: =IFERROR(INDEX(_Stages!$A$1:$A$8,MIN(MATCH(D100,_Stages!$A$1:$A$8,0)+1,8)),"") | F100: Approved | G100: Complete | H100: CTO | I100: 46116 | J100: 46119 | K100: Proceed | L100: On track | M100: 100 | N100: 3 | O100: =A100&"|"&D100
...

Sheet Financials
A1: Project ID | B1: Month | C1: CAPEX | D1: OPEX | E1: Actual | F1: Forecast | G1: Variance | H1: Planned Value | I1: Earned Value
A2: PRJ001 | B2: Jan | C2: =IFERROR(VLOOKUP(A2,Projects!$A:$AK,21,FALSE())/12,0) | D2: =IFERROR(VLOOKUP(A2,Projects!$A:$AK,22,FALSE())/12,0) | E2: 261933 | F2: 301306 | G2: =F2-E2 | H2: 251156 | I2: 195289
A3: PRJ001 | B3: Feb | C3: =IFERROR(VLOOKUP(A3,Projects!$A:$AK,21,FALSE())/12,0) | D3: =IFERROR(VLOOKUP(A3,Projects!$A:$AK,22,FALSE())/12,0) | E3: 231778 | F3: 225033 | G3: =F3-E3 | H3: 192576 | I3: 147431
A4: PRJ001 | B4: Mar | C4: =IFERROR(VLOOKUP(A4,Projects!$A:$AK,21,FALSE())/12,0) | D4: =IFERROR(VLOOKUP(A4,Projects!$A:$AK,22,FALSE())/12,0) | E4: 174362 | F4: 182142 | G4: =F4-E4 | H4: 135066 | I4: 165831
A5: PRJ001 | B5: Apr | C5: =IFERROR(VLOOKUP(A5,Projects!$A:$AK,21,FALSE())/12,0) | D5: =IFERROR(VLOOKUP(A5,Projects!$A:$AK,22,FALSE())/12,0) | E5: 272440 | F5: 283263 | G5: =F5-E5 | H5: 203135 | I5: 213717
A6: PRJ001 | B6: May | C6: =IFERROR(VLOOKUP(A6,Projects!$A:$AK,21,FALSE())/12,0) | D6: =IFERROR(VLOOKUP(A6,Projects!$A:$AK,22,FALSE())/12,0) | E6: 237193 | F6: 204783 | G6: =F6-E6 | H6: 223895 | I6: 154098
A7: PRJ001 | B7: Jun | C7: =IFERROR(VLOOKUP(A7,Projects!$A:$AK,21,FALSE())/12,0) | D7: =IFERROR(VLOOKUP(A7,Projects!$A:$AK,22,FALSE())/12,0) | E7: 222203 | F7: 317214 | G7: =F7-E7 | H7: 276980 | I7: 191631
A8: PRJ001 | B8: Jul | C8: =IFERROR(VLOOKUP(A8,Projects!$A:$AK,21,FALSE())/12,0) | D8: =IFERROR(VLOOKUP(A8,Projects!$A:$AK,22,FALSE())/12,0) | E8: 245586 | F8: 292094 | G8: =F8-E8 | H8: 208528 | I8: 227833
A9: PRJ001 | B9: Aug | C9: =IFERROR(VLOOKUP(A9,Projects!$A:$AK,21,FALSE())/12,0) | D9: =IFERROR(VLOOKUP(A9,Projects!$A:$AK,22,FALSE())/12,0) | E9: 239886 | F9: 257711 | G9: =F9-E9 | H9: 271464 | I9: 259232
A10: PRJ001 | B10: Sep | C10: =IFERROR(VLOOKUP(A10,Projects!$A:$AK,21,FALSE())/12,0) | D10: =IFERROR(VLOOKUP(A10,Projects!$A:$AK,22,FALSE())/12,0) | E10: 164832 | F10: 179916 | G10: =F10-E10 | H10: 165087 | I10: 134079
A11: PRJ001 | B11: Oct | C11: =IFERROR(VLOOKUP(A11,Projects!$A:$AK,21,FALSE())/12,0) | D11: =IFERROR(VLOOKUP(A11,Projects!$A:$AK,22,FALSE())/12,0) | E11: 175825 | F11: 157796 | G11: =F11-E11 | H11: 137163 | I11: 147237
A12: PRJ001 | B12: Nov | C12: =IFERROR(VLOOKUP(A12,Projects!$A:$AK,21,FALSE())/12,0) | D12: =IFERROR(VLOOKUP(A12,Projects!$A:$AK,22,FALSE())/12,0) | E12: 227590 | F12: 270516 | G12: =F12-E12 | H12: 274054 | I12: 288863
A13: PRJ001 | B13: Dec | C13: =IFERROR(VLOOKUP(A13,Projects!$A:$AK,21,FALSE())/12,0) | D13: =IFERROR(VLOOKUP(A13,Projects!$A:$AK,22,FALSE())/12,0) | E13: 291696 | F13: 322783 | G13: =F13-E13 | H13: 247640 | I13: 276531
... A481: PRJ040 | B481: Dec | C481: =IFERROR(VLOOKUP(A481,Projects!$A:$AK,21,FALSE())/12,0) | D481: =IFERROR(VLOOKUP(A481,Projects!$A:$AK,22,FALSE())/12,0) | E481: 175890 | F481: 175479 | G481: =F481-E481 | H481: 157845 | I481: 150862

Sheet Resources
A1: Resource | B1: Skill | C1: Role | D1: Project ID | E1: Project | F1: Month | G1: Allocation % | H1: Capacity %
A2: Resource 01 | B2: BA | C2: Analyst | D2: PRJ022 | E2: DevOps Tools | F2: 45748 | G2: 25 | H2: 100
A3: Resource 01 | B3: BA | C3: Analyst | D3: PRJ022 | E3: DevOps Tools | F3: 45778 | G3: 25 | H3: 100
A4: Resource 01 | B4: BA | C4: Analyst | D4: PRJ022 | E4: DevOps Tools | F4: 45809 | G4: 25 | H4: 100
A5: Resource 01 | B5: BA | C5: Analyst | D5: PRJ022 | E5: DevOps Tools | F5: 45839 | G5: 40 | H5: 100
A6: Resource 01 | B6: BA | C6: Analyst | D6: PRJ022 | E6: DevOps Tools | F6: 45870 | G6: 35 | H6: 100
A7: Resource 01 | B7: BA | C7: Analyst | D7: PRJ022 | E7: DevOps Tools | F7: 45901 | G7: 35 | H7: 100
A8: Resource 01 | B8: BA | C8: Analyst | D8: PRJ022 | E8: DevOps Tools | F8: 45931 | G8: 35 | H8: 100
A9: Resource 01 | B9: BA | C9: Analyst | D9: PRJ022 | E9: DevOps Tools | F9: 45962 | G9: 15 | H9: 100
A10: Resource 01 | B10: BA | C10: Analyst | D10: PRJ022 | E10: DevOps Tools | F10: 45992 | G10: 40 | H10: 100
A11: Resource 01 | B11: BA | C11: Analyst | D11: PRJ022 | E11: DevOps Tools | F11: 46023 | G11: 0 | H11: 100
A12: Resource 01 | B12: BA | C12: Analyst | D12: PRJ040 | E12: Zero-Trust Net | F12: 45689 | G12: 90 | H12: 100
A13: Resource 01 | B13: BA | C13: Analyst | D13: PRJ040 | E13: Zero-Trust Net | F13: 45717 | G13: 50 | H13: 100
... A768: Resource 30 | B768: Data | C768: Analyst | D768: PRJ021 | E768: Data Warehouse | F768: 45809 | G768: 100 | H768: 100

Sheet Dependencies
A1: From Project | B1: To Project | C1: Dependency Type | D1: Status | E1: Impact
A2: PRJ027 | B2: PRJ022 | C2: Shared Resource | D2: Healthy | E2: Low
A3: PRJ017 | B3: PRJ033 | C3: Finish-Start | D3: At Risk | E3: Medium
A4: PRJ039 | B4: PRJ036 | C4: Blocks | D4: At Risk | E4: High
A5: PRJ002 | B5: PRJ004 | C5: Start-Start | D5: Blocked | E5: Medium
A6: PRJ009 | B6: PRJ001 | C6: Shared Resource | D6: Healthy | E6: High
A7: PRJ020 | B7: PRJ021 | C7: Finish-Start | D7: Healthy | E7: Low
A8: PRJ016 | B8: PRJ034 | C8: Start-Start | D8: Blocked | E8: High
A9: PRJ027 | B9: PRJ021 | C9: Shared Resource | D9: At Risk | E9: High
A10: PRJ009 | B10: PRJ017 | C10: Start-Start | D10: Blocked | E10: High
A11: PRJ021 | B11: PRJ019 | C11: Start-Start | D11: Healthy | E11: Medium
A12: PRJ024 | B12: PRJ012 | C12: Shared Resource | D12: At Risk | E12: High
... A41: PRJ011 | B41: PRJ030 | C41: Shared Resource | D41: Healthy | E41: Medium

Sheet Pipeline
A1: Idea ID | B1: Name | C1: Submitter | D1: Strategic Fit (1-5) | E1: Value (1-5) | F1: Risk (1-5) | G1: Effort (1-5) | H1: Priority Score | I1: Decision | J1: Est. Budget ($K)
A2: IDEA008 | B2: Quantum Pilot | C2: Priya Patel | D2: 4 | E2: 4 | F2: 3 | G2: 5 | H2: =(D2*0.3+E2*0.4-F2*0.15-G2*0.15)*20 | I2: New | J2: 724
A3: IDEA004 | B3: Edge Analytics | C3: Alex Brown | D3: 5 | E3: 2 | F3: 5 | G3: 1 | H3: =(D3*0.3+E3*0.4-F3*0.15-G3*0.15)*20 | I3: Parked | J3: 419
A4: IDEA009 | B4: SaaS Rationalisation | C4: Priya Patel | D4: 1 | E4: 5 | F4: 4 | G4: 3 | H4: =(D4*0.3+E4*0.4-F4*0.15-G4*0.15)*20 | I4: Parked | J4: 314
A5: IDEA007 | B5: Citizen Dev Studio | C5: John Smith | D5: 1 | E5: 3 | F5: 2 | G5: 1 | H5: =(D5*0.3+E5*0.4-F5*0.15-G5*0.15)*20 | I5: Rejected | J5: 1751
A6: IDEA005 | B6: Green IT | C6: Priya Patel | D6: 4 | E6: 1 | F6: 2 | G6: 4 | H6: =(D6*0.3+E6*0.4-F6*0.15-G6*0.15)*20 | I6: New | J6: 1867
A7: IDEA001 | B7: Process Automation v2 | C7: Sarah Lee | D7: 1 | E7: 4 | F7: 3 | G7: 5 | H7: =(D7*0.3+E7*0.4-F7*0.15-G7*0.15)*20 | I7: Rejected | J7: 1059
A8: IDEA006 | B8: ESG Data Hub | C8: Sarah Lee | D8: 3 | E8: 1 | F8: 3 | G8: 1 | H8: =(D8*0.3+E8*0.4-F8*0.15-G8*0.15)*20 | I8: Approved | J8: 1259
A9: IDEA003 | B9: ML Ops Platform | C9: Carlos Diaz | D9: 3 | E9: 2 | F9: 2 | G9: 5 | H9: =(D9*0.3+E9*0.4-F9*0.15-G9*0.15)*20 | I9: Approved | J9: 1203
A10: IDEA002 | B10: Customer 360 | C10: John Smith | D10: 1 | E10: 2 | F10: 1 | G10: 3 | H10: =(D10*0.3+E10*0.4-F10*0.15-G10*0.15)*20 | I10: Under Review | J10: 1828
A11: IDEA010 | B11: Zero Trust v2 | C11: Carlos Diaz | D11: 2 | E11: 1 | F11: 3 | G11: 3 | H11: =(D11*0.3+E11*0.4-F11*0.15-G11*0.15)*20 | I11: New | J11: 1573

Sheet CostBenefit
A1: Project ID | B1: Project Name | C1: Program | D1: Year Offset | E1: Year | F1: CAPEX | G1: OPEX | H1: Total Cost | I1: Benefit Recurring | J1: Benefit One-Off | K1: Total Benefit | L1: Net Benefit | M1: Benefit Type | N1: Benefit Category | O1: Confidence %
A2: PRJ001 | B2: =IFERROR(VLOOKUP(A2,Projects!$A:$AK,2,FALSE()),"") | C2: =IFERROR(VLOOKUP(A2,Projects!$A:$AK,3,FALSE()),"") | D2: 0 | E2: =IFERROR(YEAR(VLOOKUP(A2,Projects!$A:$AK,16,FALSE()))+D2,D2) | F2: =IFERROR(VLOOKUP(A2,Projects!$A:$AK,21,FALSE()),"") | G2: =IFERROR(VLOOKUP(A2,Projects!$A:$AK,22,FALSE()),"") | H2: =F2+G2 | I2: 0 | J2: 0 | K2: =I2+J2 | L2: =K2-H2 | M2: Recurring | N2: Compliance | O2: 70
A3: PRJ001 | B3: =IFERROR(VLOOKUP(A3,Projects!$A:$AK,2,FALSE()),"") | C3: =IFERROR(VLOOKUP(A3,Projects!$A:$AK,3,FALSE()),"") | D3: 1 | E3: =IFERROR(YEAR(VLOOKUP(A3,Projects!$A:$AK,16,FALSE()))+D3,D3) | F3: =IFERROR(VLOOKUP(A3,Projects!$A:$AK,21,FALSE()),"") | G3: =IFERROR(VLOOKUP(A3,Projects!$A:$AK,22,FALSE()),"") | H3: =F3+G3 | I3: 738473 | J3: 0 | K3: =I3+J3 | L3: =K3-H3 | M3: Recurring | N3: Compliance | O3: 70
A4: PRJ001 | B4: =IFERROR(VLOOKUP(A4,Projects!$A:$AK,2,FALSE()),"") | C4: =IFERROR(VLOOKUP(A4,Projects!$A:$AK,3,FALSE()),"") | D4: 2 | E4: =IFERROR(YEAR(VLOOKUP(A4,Projects!$A:$AK,16,FALSE()))+D4,D4) | F4: =IFERROR(VLOOKUP(A4,Projects!$A:$AK,21,FALSE()),"") | G4: =IFERROR(VLOOKUP(A4,Projects!$A:$AK,22,FALSE()),"") | H4: =F4+G4 | I4: 807665 | J4: 0 | K4: =I4+J4 | L4: =K4-H4 | M4: Recurring | N4: Compliance | O4: 70
A5: PRJ001 | B5: =IFERROR(VLOOKUP(A5,Projects!$A:$AK,2,FALSE()),"") | C5: =IFERROR(VLOOKUP(A5,Projects!$A:$AK,3,FALSE()),"") | D5: 3 | E5: =IFERROR(YEAR(VLOOKUP(A5,Projects!$A:$AK,16,FALSE()))+D5,D5) | F5: =IFERROR(VLOOKUP(A5,Projects!$A:$AK,21,FALSE()),"") | G5: =IFERROR(VLOOKUP(A5,Projects!$A:$AK,22,FALSE()),"") | H5: =F5+G5 | I5: 859774 | J5: 0 | K5: =I5+J5 | L5: =K5-H5 | M5: Recurring | N5: Compliance | O5: 80
A6: PRJ001 | B6: =IFERROR(VLOOKUP(A6,Projects!$A:$AK,2,FALSE()),"") | C6: =IFERROR(VLOOKUP(A6,Projects!$A:$AK,3,FALSE()),"") | D6: 4 | E6: =IFERROR(YEAR(VLOOKUP(A6,Projects!$A:$AK,16,FALSE()))+D6,D6) | F6: =IFERROR(VLOOKUP(A6,Projects!$A:$AK,21,FALSE()),"") | G6: =IFERROR(VLOOKUP(A6,Projects!$A:$AK,22,FALSE()),"") | H6: =F6+G6 | I6: 833860 | J6: 0 | K6: =I6+J6 | L6: =K6-H6 | M6: Recurring | N6: Compliance | O6: 60
A7: PRJ002 | B7: =IFERROR(VLOOKUP(A7,Projects!$A:$AK,2,FALSE()),"") | C7: =IFERROR(VLOOKUP(A7,Projects!$A:$AK,3,FALSE()),"") | D7: 0 | E7: =IFERROR(YEAR(VLOOKUP(A7,Projects!$A:$AK,16,FALSE()))+D7,D7) | F7: =IFERROR(VLOOKUP(A7,Projects!$A:$AK,21,FALSE()),"") | G7: =IFERROR(VLOOKUP(A7,Projects!$A:$AK,22,FALSE()),"") | H7: =F7+G7 | I7: 0 | J7: 0 | K7: =I7+J7 | L7: =K7-H7 | M7: Recurring | N7: Compliance | O7: 90
A8: PRJ002 | B8: =IFERROR(VLOOKUP(A8,Projects!$A:$AK,2,FALSE()),"") | C8: =IFERROR(VLOOKUP(A8,Projects!$A:$AK,3,FALSE()),"") | D8: 1 | E8: =IFERROR(YEAR(VLOOKUP(A8,Projects!$A:$AK,16,FALSE()))+D8,D8) | F8: =IFERROR(VLOOKUP(A8,Projects!$A:$AK,21,FALSE()),"") | G8: =IFERROR(VLOOKUP(A8,Projects!$A:$AK,22,FALSE()),"") | H8: =F8+G8 | I8: 653868 | J8: 0 | K8: =I8+J8 | L8: =K8-H8 | M8: Recurring | N8: Compliance | O8: 70
A9: PRJ002 | B9: =IFERROR(VLOOKUP(A9,Projects!$A:$AK,2,FALSE()),"") | C9: =IFERROR(VLOOKUP(A9,Projects!$A:$AK,3,FALSE()),"") | D9: 2 | E9: =IFERROR(YEAR(VLOOKUP(A9,Projects!$A:$AK,16,FALSE()))+D9,D9) | F9: =IFERROR(VLOOKUP(A9,Projects!$A:$AK,21,FALSE()),"") | G9: =IFERROR(VLOOKUP(A9,Projects!$A:$AK,22,FALSE()),"") | H9: =F9+G9 | I9: 563363 | J9: 0 | K9: =I9+J9 | L9: =K9-H9 | M9: Recurring | N9: Compliance | O9: 80
A10: PRJ002 | B10: =IFERROR(VLOOKUP(A10,Projects!$A:$AK,2,FALSE()),"") | C10: =IFERROR(VLOOKUP(A10,Projects!$A:$AK,3,FALSE()),"") | D10: 3 | E10: =IFERROR(YEAR(VLOOKUP(A10,Projects!$A:$AK,16,FALSE()))+D10,D10) | F10: =IFERROR(VLOOKUP(A10,Projects!$A:$AK,21,FALSE()),"") | G10: =IFERROR(VLOOKUP(A10,Projects!$A:$AK,22,FALSE()),"") | H10: =F10+G10 | I10: 731003 | J10: 0 | K10: =I10+J10 | L10: =K10-H10 | M10: Recurring | N10: Compliance | O10: 70
A11: PRJ002 | B11: =IFERROR(VLOOKUP(A11,Projects!$A:$AK,2,FALSE()),"") | C11: =IFERROR(VLOOKUP(A11,Projects!$A:$AK,3,FALSE()),"") | D11: 4 | E11: =IFERROR(YEAR(VLOOKUP(A11,Projects!$A:$AK,16,FALSE()))+D11,D11) | F11: =IFERROR(VLOOKUP(A11,Projects!$A:$AK,21,FALSE()),"") | G11: =IFERROR(VLOOKUP(A11,Projects!$A:$AK,22,FALSE()),"") | H11: =F11+G11 | I11: 730897 | J11: 0 | K11: =I11+J11 | L11: =K11-H11 | M11: Recurring | N11: Compliance | O11: 60
A12: PRJ003 | B12: =IFERROR(VLOOKUP(A12,Projects!$A:$AK,2,FALSE()),"") | C12: =IFERROR(VLOOKUP(A12,Projects!$A:$AK,3,FALSE()),"") | D12: 0 | E12: =IFERROR(YEAR(VLOOKUP(A12,Projects!$A:$AK,16,FALSE()))+D12,D12) | F12: =IFERROR(VLOOKUP(A12,Projects!$A:$AK,21,FALSE()),"") | G12: =IFERROR(VLOOKUP(A12,Projects!$A:$AK,22,FALSE()),"") | H12: =F12+G12 | I12: 0 | J12: 0 | K12: =I12+J12 | L12: =K12-H12 | M12: Recurring | N12: Risk Avoidance | O12: 70
A13: PRJ003 | B13: =IFERROR(VLOOKUP(A13,Projects!$A:$AK,2,FALSE()),"") | C13: =IFERROR(VLOOKUP(A13,Projects!$A:$AK,3,FALSE()),"") | D13: 1 | E13: =IFERROR(YEAR(VLOOKUP(A13,Projects!$A:$AK,16,FALSE()))+D13,D13) | F13: =IFERROR(VLOOKUP(A13,Projects!$A:$AK,21,FALSE()),"") | G13: =IFERROR(VLOOKUP(A13,Projects!$A:$AK,22,FALSE()),"") | H13: =F13+G13 | I13: 2114749 | J13: 0 | K13: =I13+J13 | L13: =K13-H13 | M13: Recurring | N13: Risk Avoidance | O13: 90
... A201: PRJ040 | B201: =IFERROR(VLOOKUP(A201,Projects!$A:$AK,2,FALSE()),"") | C201: =IFERROR(VLOOKUP(A201,Projects!$A:$AK,3,FALSE()),"") | D201: 4 | E201: =IFERROR(YEAR(VLOOKUP(A201,Projects!$A:$AK,16,FALSE()))+D201,D201) | F201: =IFERROR(VLOOKUP(A201,Projects!$A:$AK,21,FALSE()),"") | G201: =IFERROR(VLOOKUP(A201,Projects!$A:$AK,22,FALSE()),"") | H201: =F201+G201 | I201: 0 | J201: 0 | K201: =I201+J201 | L201: =K201-H201 | M201: One-Off | N201: Compliance | O201: 70

Sheet Benefits
A1: Benefit ID | B1: Project ID | C1: Project Name | D1: Description | E1: Category | F1: Target Value | G1: Realised Value | H1: Benefits Remaining | I1: Realisation % | J1: Owner | K1: Start Date | L1: End Date | M1: Status
A2: BEN001 | B2: PRJ001 | C2: =IFERROR(VLOOKUP(B2,Projects!$A:$AK,2,FALSE()),"") | D2: Process cycle-time reduction | E2: Cost Reduction | F2: 569626 | G2: 250989 | H2: =F2-G2 | I2: =IFERROR(G2/F2,0) | J2: Carlos Diaz | K2: =IFERROR(VLOOKUP(B2,Projects!$A:$AK,16,FALSE()),"") | L2: =IFERROR(VLOOKUP(B2,Projects!$A:$AK,17,FALSE()),"") | M2: At Risk
A3: BEN002 | B3: PRJ001 | C3: =IFERROR(VLOOKUP(B3,Projects!$A:$AK,2,FALSE()),"") | D3: Risk loss avoidance | E3: Compliance | F3: 497551 | G3: 28353 | H3: =F3-G3 | I3: =IFERROR(G3/F3,0) | J3: Alex Brown | K3: =IFERROR(VLOOKUP(B3,Projects!$A:$AK,16,FALSE()),"") | L3: =IFERROR(VLOOKUP(B3,Projects!$A:$AK,17,FALSE()),"") | M3: At Risk
A4: BEN003 | B4: PRJ002 | C4: =IFERROR(VLOOKUP(B4,Projects!$A:$AK,2,FALSE()),"") | D4: Regulatory compliance achievement | E4: Customer Experience | F4: 1527159 | G4: 400095 | H4: =F4-G4 | I4: =IFERROR(G4/F4,0) | J4: Jane Doe | K4: =IFERROR(VLOOKUP(B4,Projects!$A:$AK,16,FALSE()),"") | L4: =IFERROR(VLOOKUP(B4,Projects!$A:$AK,17,FALSE()),"") | M4: Realised
A5: BEN004 | B5: PRJ002 | C5: =IFERROR(VLOOKUP(B5,Projects!$A:$AK,2,FALSE()),"") | D5: Risk loss avoidance | E5: Customer Experience | F5: 1098404 | G5: 371599 | H5: =F5-G5 | I5: =IFERROR(G5/F5,0) | J5: Mike Johnson | K5: =IFERROR(VLOOKUP(B5,Projects!$A:$AK,16,FALSE()),"") | L5: =IFERROR(VLOOKUP(B5,Projects!$A:$AK,17,FALSE()),"") | M5: Planned
A6: BEN005 | B6: PRJ002 | C6: =IFERROR(VLOOKUP(B6,Projects!$A:$AK,2,FALSE()),"") | D6: Risk loss avoidance | E6: Cost Reduction | F6: 493679 | G6: 309250 | H6: =F6-G6 | I6: =IFERROR(G6/F6,0) | J6: Sarah Lee | K6: =IFERROR(VLOOKUP(B6,Projects!$A:$AK,16,FALSE()),"") | L6: =IFERROR(VLOOKUP(B6,Projects!$A:$AK,17,FALSE()),"") | M6: At Risk
A7: BEN006 | B7: PRJ003 | C7: =IFERROR(VLOOKUP(B7,Projects!$A:$AK,2,FALSE()),"") | D7: Process cycle-time reduction | E7: Productivity Improvement | F7: 1185604 | G7: 776392 | H7: =F7-G7 | I7: =IFERROR(G7/F7,0) | J7: Alex Brown | K7: =IFERROR(VLOOKUP(B7,Projects!$A:$AK,16,FALSE()),"") | L7: =IFERROR(VLOOKUP(B7,Projects!$A:$AK,17,FALSE()),"") | M7: Planned
A8: BEN007 | B8: PRJ003 | C8: =IFERROR(VLOOKUP(B8,Projects!$A:$AK,2,FALSE()),"") | D8: Revenue growth from new channel | E8: Risk Reduction | F8: 660591 | G8: 239910 | H8: =F8-G8 | I8: =IFERROR(G8/F8,0) | J8: John Smith | K8: =IFERROR(VLOOKUP(B8,Projects!$A:$AK,16,FALSE()),"") | L8: =IFERROR(VLOOKUP(B8,Projects!$A:$AK,17,FALSE()),"") | M8: Realised
A9: BEN008 | B9: PRJ004 | C9: =IFERROR(VLOOKUP(B9,Projects!$A:$AK,2,FALSE()),"") | D9: Process cycle-time reduction | E9: Customer Experience | F9: 957187 | G9: 289792 | H9: =F9-G9 | I9: =IFERROR(G9/F9,0) | J9: Mike Johnson | K9: =IFERROR(VLOOKUP(B9,Projects!$A:$AK,16,FALSE()),"") | L9: =IFERROR(VLOOKUP(B9,Projects!$A:$AK,17,FALSE()),"") | M9: Planned
A10: BEN009 | B10: PRJ004 | C10: =IFERROR(VLOOKUP(B10,Projects!$A:$AK,2,FALSE()),"") | D10: Customer NPS uplift | E10: Revenue Increase | F10: 441175 | G10: 72200 | H10: =F10-G10 | I10: =IFERROR(G10/F10,0) | J10: Mike Johnson | K10: =IFERROR(VLOOKUP(B10,Projects!$A:$AK,16,FALSE()),"") | L10: =IFERROR(VLOOKUP(B10,Projects!$A:$AK,17,FALSE()),"") | M10: Planned
A11: BEN010 | B11: PRJ005 | C11: =IFERROR(VLOOKUP(B11,Projects!$A:$AK,2,FALSE()),"") | D11: Headcount cost avoidance | E11: Productivity Improvement | F11: 1860551 | G11: 128167 | H11: =F11-G11 | I11: =IFERROR(G11/F11,0) | J11: John Smith | K11: =IFERROR(VLOOKUP(B11,Projects!$A:$AK,16,FALSE()),"") | L11: =IFERROR(VLOOKUP(B11,Projects!$A:$AK,17,FALSE()),"") | M11: Realised
A12: BEN011 | B12: PRJ005 | C12: =IFERROR(VLOOKUP(B12,Projects!$A:$AK,2,FALSE()),"") | D12: Process cycle-time reduction | E12: Compliance | F12: 473628 | G12: 109157 | H12: =F12-G12 | I12: =IFERROR(G12/F12,0) | J12: Carlos Diaz | K12: =IFERROR(VLOOKUP(B12,Projects!$A:$AK,16,FALSE()),"") | L12: =IFERROR(VLOOKUP(B12,Projects!$A:$AK,17,FALSE()),"") | M12: In Progress
A13: BEN012 | B13: PRJ006 | C13: =IFERROR(VLOOKUP(B13,Projects!$A:$AK,2,FALSE()),"") | D13: Customer NPS uplift | E13: Compliance | F13: 1247665 | G13: 120407 | H13: =F13-G13 | I13: =IFERROR(G13/F13,0) | J13: Alex Brown | K13: =IFERROR(VLOOKUP(B13,Projects!$A:$AK,16,FALSE()),"") | L13: =IFERROR(VLOOKUP(B13,Projects!$A:$AK,17,FALSE()),"") | M13: Realised
... A81: BEN080 | B81: PRJ040 | C81: =IFERROR(VLOOKUP(B81,Projects!$A:$AK,2,FALSE()),"") | D81: Process cycle-time reduction | E81: Revenue Increase | F81: 656939 | G81: 173701 | H81: =F81-G81 | I81: =IFERROR(G81/F81,0) | J81: Mike Johnson | K81: =IFERROR(VLOOKUP(B81,Projects!$A:$AK,16,FALSE()),"") | L81: =IFERROR(VLOOKUP(B81,Projects!$A:$AK,17,FALSE()),"") | M81: In Progress

Sheet Decisions
A1: Decision ID | B1: Type | C1: Project ID | D1: Program | E1: Description | F1: Required By | G1: Owner | H1: Due Date | I1: Priority | J1: Status | K1: Outcome | L1: Approval Date
A2: DEC001 | B2: General | D2: =IFERROR(VLOOKUP(C2,Projects!$A:$AK,3,FALSE()),"") | E2: Approve full project funding | F2: CIO | G2: Mike Johnson | H2: 46146 | I2: =IFERROR(VLOOKUP(C2,Projects!$A:$AK,10,FALSE()),"") | J2: Closed
A3: DEC002 | B3: Project | C3: PRJ007 | D3: =IFERROR(VLOOKUP(C3,Projects!$A:$AK,3,FALSE()),"") | E3: Approve architecture pattern | F3: CIO | G3: Sarah Lee | H3: 46226 | I3: =IFERROR(VLOOKUP(C3,Projects!$A:$AK,10,FALSE()),"") | J3: Closed
A4: DEC003 | B4: SteerCo | C4: PRJ032 | D4: =IFERROR(VLOOKUP(C4,Projects!$A:$AK,3,FALSE()),"") | E4: Defer benefits realisation date | F4: COO | G4: Alex Brown | H4: 46218 | I4: =IFERROR(VLOOKUP(C4,Projects!$A:$AK,10,FALSE()),"") | J4: Approved
A5: DEC004 | B5: Architecture | C5: PRJ021 | D5: =IFERROR(VLOOKUP(C5,Projects!$A:$AK,3,FALSE()),"") | E5: Cut scope of MVP | F5: CMO | G5: Sarah Lee | H5: 46118 | I5: =IFERROR(VLOOKUP(C5,Projects!$A:$AK,10,FALSE()),"") | J5: Open
A6: DEC005 | B6: Architecture | C6: PRJ007 | D6: =IFERROR(VLOOKUP(C6,Projects!$A:$AK,3,FALSE()),"") | E6: Re-baseline schedule | F6: CMO | G6: Priya Patel | H6: 46115 | I6: =IFERROR(VLOOKUP(C6,Projects!$A:$AK,10,FALSE()),"") | J6: Open
A7: DEC006 | B7: Program | C7: PRJ034 | D7: =IFERROR(VLOOKUP(C7,Projects!$A:$AK,3,FALSE()),"") | E7: Accept residual risk | F7: CFO | G7: Mike Johnson | H7: 46178 | I7: =IFERROR(VLOOKUP(C7,Projects!$A:$AK,10,FALSE()),"") | J7: Closed
A8: DEC007 | B8: General | C8: PRJ033 | D8: =IFERROR(VLOOKUP(C8,Projects!$A:$AK,3,FALSE()),"") | E8: Accept residual risk | F8: CFO | G8: John Smith | H8: 46199 | I8: =IFERROR(VLOOKUP(C8,Projects!$A:$AK,10,FALSE()),"") | J8: Approved
A9: DEC008 | B9: Architecture | C9: PRJ003 | D9: =IFERROR(VLOOKUP(C9,Projects!$A:$AK,3,FALSE()),"") | E9: Accept residual risk | F9: CMO | G9: Jane Doe | H9: 46028 | I9: =IFERROR(VLOOKUP(C9,Projects!$A:$AK,10,FALSE()),"") | J9: Rejected
A10: DEC009 | B10: Program | C10: PRJ023 | D10: =IFERROR(VLOOKUP(C10,Projects!$A:$AK,3,FALSE()),"") | E10: Re-baseline schedule | F10: CIO | G10: Priya Patel | H10: 46126 | I10: =IFERROR(VLOOKUP(C10,Projects!$A:$AK,10,FALSE()),"") | J10: Approved
A11: DEC010 | B11: Funding | C11: PRJ010 | D11: =IFERROR(VLOOKUP(C11,Projects!$A:$AK,3,FALSE()),"") | E11: Choose vendor for cloud migration | F11: CMO | G11: Carlos Diaz | H11: 46179 | I11: =IFERROR(VLOOKUP(C11,Projects!$A:$AK,10,FALSE()),"") | J11: Approved
A12: DEC011 | B12: General | C12: PRJ011 | D12: =IFERROR(VLOOKUP(C12,Projects!$A:$AK,3,FALSE()),"") | E12: Approve full project funding | F12: CMO | G12: Priya Patel | H12: 46237 | I12: =IFERROR(VLOOKUP(C12,Projects!$A:$AK,10,FALSE()),"") | J12: In Review
A13: DEC012 | B13: Funding | C13: PRJ011 | D13: =IFERROR(VLOOKUP(C13,Projects!$A:$AK,3,FALSE()),"") | E13: Approve full project funding | F13: CMO | G13: Priya Patel | H13: 46086 | I13: =IFERROR(VLOOKUP(C13,Projects!$A:$AK,10,FALSE()),"") | J13: In Review
A14: DEC013 | B14: Risk | C14: PRJ018 | D14: =IFERROR(VLOOKUP(C14,Projects!$A:$AK,3,FALSE()),"") | E14: Accept residual risk | F14: COO | G14: Priya Patel | H14: 46107 | I14: =IFERROR(VLOOKUP(C14,Projects!$A:$AK,10,FALSE()),"") | J14: Open
A15: DEC014 | B15: Portfolio | C15: PRJ035 | D15: =IFERROR(VLOOKUP(C15,Projects!$A:$AK,3,FALSE()),"") | E15: Approve full project funding | F15: COO | G15: Carlos Diaz | H15: 46194 | I15: =IFERROR(VLOOKUP(C15,Projects!$A:$AK,10,FALSE()),"") | J15: Closed
A16: DEC015 | B16: Program | D16: =IFERROR(VLOOKUP(C16,Projects!$A:$AK,3,FALSE()),"") | E16: Re-baseline schedule | F16: CMO | G16: Priya Patel | H16: 46220 | I16: =IFERROR(VLOOKUP(C16,Projects!$A:$AK,10,FALSE()),"") | J16: Closed
A17: DEC016 | B17: Risk | C17: PRJ015 | D17: =IFERROR(VLOOKUP(C17,Projects!$A:$AK,3,FALSE()),"") | E17: Cut scope of MVP | F17: CIO | G17: Mike Johnson | H17: 46243 | I17: =IFERROR(VLOOKUP(C17,Projects!$A:$AK,10,FALSE()),"") | J17: Open
A18: DEC017 | B18: Architecture | C18: PRJ038 | D18: =IFERROR(VLOOKUP(C18,Projects!$A:$AK,3,FALSE()),"") | E18: Accept residual risk | F18: CIO | G18: Alex Brown | H18: 46046 | I18: =IFERROR(VLOOKUP(C18,Projects!$A:$AK,10,FALSE()),"") | J18: In Review
A19: DEC018 | B19: Architecture | C19: PRJ025 | D19: =IFERROR(VLOOKUP(C19,Projects!$A:$AK,3,FALSE()),"") | E19: Cut scope of MVP | F19: CIO | G19: Alex Brown | H19: 46242 | I19: =IFERROR(VLOOKUP(C19,Projects!$A:$AK,10,FALSE()),"") | J19: In Review
A20: DEC019 | B20: Risk | C20: PRJ028 | D20: =IFERROR(VLOOKUP(C20,Projects!$A:$AK,3,FALSE()),"") | E20: Defer benefits realisation date | F20: COO | G20: Carlos Diaz | H20: 46240 | I20: =IFERROR(VLOOKUP(C20,Projects!$A:$AK,10,FALSE()),"") | J20: In Review
A21: DEC020 | B21: Funding | C21: PRJ007 | D21: =IFERROR(VLOOKUP(C21,Projects!$A:$AK,3,FALSE()),"") | E21: Approve full project funding | F21: CTO | G21: Carlos Diaz | H21: 46157 | I21: =IFERROR(VLOOKUP(C21,Projects!$A:$AK,10,FALSE()),"") | J21: Approved
A22: DEC021 | B22: SteerCo | C22: PRJ015 | D22: =IFERROR(VLOOKUP(C22,Projects!$A:$AK,3,FALSE()),"") | E22: Accept residual risk | F22: CMO | G22: Jane Doe | H22: 46061 | I22: =IFERROR(VLOOKUP(C22,Projects!$A:$AK,10,FALSE()),"") | J22: Approved
A23: DEC022 | B23: Project | C23: PRJ039 | D23: =IFERROR(VLOOKUP(C23,Projects!$A:$AK,3,FALSE()),"") | E23: Cut scope of MVP | F23: CTO | G23: Priya Patel | H23: 46061 | I23: =IFERROR(VLOOKUP(C23,Projects!$A:$AK,10,FALSE()),"") | J23: Approved
A24: DEC023 | B24: General | D24: =IFERROR(VLOOKUP(C24,Projects!$A:$AK,3,FALSE()),"") | E24: Re-baseline schedule | F24: COO | G24: Priya Patel | H24: 46241 | I24: =IFERROR(VLOOKUP(C24,Projects!$A:$AK,10,FALSE()),"") | J24: Open
A25: DEC024 | B25: Architecture | C25: PRJ010 | D25: =IFERROR(VLOOKUP(C25,Projects!$A:$AK,3,FALSE()),"") | E25: Defer benefits realisation date | F25: CFO | G25: Priya Patel | H25: 46231 | I25: =IFERROR(VLOOKUP(C25,Projects!$A:$AK,10,FALSE()),"") | J25: Open
A26: DEC025 | B26: Portfolio | C26: PRJ032 | D26: =IFERROR(VLOOKUP(C26,Projects!$A:$AK,3,FALSE()),"") | E26: Cut scope of MVP | F26: CFO | G26: John Smith | H26: 46245 | I26: =IFERROR(VLOOKUP(C26,Projects!$A:$AK,10,FALSE()),"") | J26: Rejected
A27: DEC026 | B27: Risk | D27: =IFERROR(VLOOKUP(C27,Projects!$A:$AK,3,FALSE()),"") | E27: Cut scope of MVP | F27: CMO | G27: Sarah Lee | H27: 46110 | I27: =IFERROR(VLOOKUP(C27,Projects!$A:$AK,10,FALSE()),"") | J27: Closed
A28: DEC027 | B28: SteerCo | C28: PRJ019 | D28: =IFERROR(VLOOKUP(C28,Projects!$A:$AK,3,FALSE()),"") | E28: Accept residual risk | F28: CTO | G28: Sarah Lee | H28: 46210 | I28: =IFERROR(VLOOKUP(C28,Projects!$A:$AK,10,FALSE()),"") | J28: In Review
A29: DEC028 | B29: Project | C29: PRJ020 | D29: =IFERROR(VLOOKUP(C29,Projects!$A:$AK,3,FALSE()),"") | E29: Accept residual risk | F29: CFO | G29: Alex Brown | H29: 46106 | I29: =IFERROR(VLOOKUP(C29,Projects!$A:$AK,10,FALSE()),"") | J29: Rejected
A30: DEC029 | B30: General | C30: PRJ019 | D30: =IFERROR(VLOOKUP(C30,Projects!$A:$AK,3,FALSE()),"") | E30: Choose vendor for cloud migration | F30: CFO | G30: Carlos Diaz | H30: 46202 | I30: =IFERROR(VLOOKUP(C30,Projects!$A:$AK,10,FALSE()),"") | J30: In Review
A31: DEC030 | B31: Project | C31: PRJ024 | D31: =IFERROR(VLOOKUP(C31,Projects!$A:$AK,3,FALSE()),"") | E31: Accept residual risk | F31: CFO | G31: Sarah Lee | H31: 46212 | I31: =IFERROR(VLOOKUP(C31,Projects!$A:$AK,10,FALSE()),"") | J31: In Review
A32: DEC031 | B32: Program | C32: PRJ023 | D32: =IFERROR(VLOOKUP(C32,Projects!$A:$AK,3,FALSE()),"") | E32: Choose vendor for cloud migration | F32: CIO | G32: John Smith | H32: 46038 | I32: =IFERROR(VLOOKUP(C32,Projects!$A:$AK,10,FALSE()),"") | J32: Approved
A33: DEC032 | B33: Risk | C33: PRJ010 | D33: =IFERROR(VLOOKUP(C33,Projects!$A:$AK,3,FALSE()),"") | E33: Choose vendor for cloud migration | F33: CIO | G33: John Smith | H33: 46175 | I33: =IFERROR(VLOOKUP(C33,Projects!$A:$AK,10,FALSE()),"") | J33: Rejected
A34: DEC033 | B34: SteerCo | C34: PRJ039 | D34: =IFERROR(VLOOKUP(C34,Projects!$A:$AK,3,FALSE()),"") | E34: Accept residual risk | F34: CMO | G34: Carlos Diaz | H34: 46149 | I34: =IFERROR(VLOOKUP(C34,Projects!$A:$AK,10,FALSE()),"") | J34: Open
A35: DEC034 | B35: General | D35: =IFERROR(VLOOKUP(C35,Projects!$A:$AK,3,FALSE()),"") | E35: Cut scope of MVP | F35: CMO | G35: Mike Johnson | H35: 46223 | I35: =IFERROR(VLOOKUP(C35,Projects!$A:$AK,10,FALSE()),"") | J35: Open
A36: DEC035 | B36: Program | C36: PRJ008 | D36: =IFERROR(VLOOKUP(C36,Projects!$A:$AK,3,FALSE()),"") | E36: Accept residual risk | F36: CTO | G36: Jane Doe | H36: 46053 | I36: =IFERROR(VLOOKUP(C36,Projects!$A:$AK,10,FALSE()),"") | J36: Closed
A37: DEC036 | B37: General | C37: PRJ018 | D37: =IFERROR(VLOOKUP(C37,Projects!$A:$AK,3,FALSE()),"") | E37: Defer benefits realisation date | F37: CTO | G37: Jane Doe | H37: 46170 | I37: =IFERROR(VLOOKUP(C37,Projects!$A:$AK,10,FALSE()),"") | J37: Rejected
A38: DEC037 | B38: Risk | C38: PRJ020 | D38: =IFERROR(VLOOKUP(C38,Projects!$A:$AK,3,FALSE()),"") | E38: Approve full project funding | F38: COO | G38: John Smith | H38: 46189 | I38: =IFERROR(VLOOKUP(C38,Projects!$A:$AK,10,FALSE()),"") | J38: Closed
A39: DEC038 | B39: Risk | C39: PRJ002 | D39: =IFERROR(VLOOKUP(C39,Projects!$A:$AK,3,FALSE()),"") | E39: Approve architecture pattern | F39: CTO | G39: Carlos Diaz | H39: 46071 | I39: =IFERROR(VLOOKUP(C39,Projects!$A:$AK,10,FALSE()),"") | J39: Rejected
A40: DEC039 | B40: Program | C40: PRJ014 | D40: =IFERROR(VLOOKUP(C40,Projects!$A:$AK,3,FALSE()),"") | E40: Choose vendor for cloud migration | F40: CTO | G40: Priya Patel | H40: 46040 | I40: =IFERROR(VLOOKUP(C40,Projects!$A:$AK,10,FALSE()),"") | J40: Open
A41: DEC040 | B41: General | C41: PRJ021 | D41: =IFERROR(VLOOKUP(C41,Projects!$A:$AK,3,FALSE()),"") | E41: Approve full project funding | F41: CFO | G41: Alex Brown | H41: 46166 | I41: =IFERROR(VLOOKUP(C41,Projects!$A:$AK,10,FALSE()),"") | J41: In Review

Sheet Actions
A1: Action ID | B1: Project ID | C1: Description | D1: Owner | E1: Due Date | F1: Priority | G1: Status | H1: Comments
A2: ACT001 | B2: PRJ017 | C2: Close out stage gate evidence | D2: Carlos Diaz | E2: 46029 | F2: High | G2: Complete
A3: ACT002 | B3: PRJ033 | C3: Publish SteerCo pack | D3: Mike Johnson | E3: 46028 | F3: Low | G3: Overdue
A4: ACT003 | B4: PRJ001 | C4: Update risk register | D4: Mike Johnson | E4: 46050 | F4: High | G4: Overdue
A5: ACT004 | B5: PRJ035 | C5: Resolve blocker on environment | D5: Jane Doe | E5: 46139 | F5: Low | G5: Overdue
A6: ACT005 | B6: PRJ021 | C6: Schedule architecture review | D6: Mike Johnson | E6: 46132 | F6: Low | G6: Complete
A7: ACT006 | B7: PRJ014 | C7: Submit funding paper | D7: John Smith | E7: 46144 | F7: Low | G7: Complete
A8: ACT007 | B8: PRJ016 | C8: Confirm vendor SOW | D8: Jane Doe | E8: 46216 | F8: High | G8: Overdue
A9: ACT008 | B9: PRJ009 | C9: Schedule architecture review | D9: Alex Brown | E9: 46083 | F9: High | G9: Overdue
A10: ACT009 | B10: PRJ018 | C10: Update risk register | D10: Priya Patel | E10: 46158 | F10: Low | G10: Overdue
A11: ACT010 | B11: PRJ036 | C11: Publish SteerCo pack | D11: Mike Johnson | E11: 46115 | F11: Medium | G11: Overdue
A12: ACT011 | B12: PRJ026 | C12: Resolve blocker on environment | D12: John Smith | E12: 46173 | F12: Medium | G12: Overdue
A13: ACT012 | B13: PRJ010 | C13: Schedule architecture review | D13: Jane Doe | E13: 46180 | F13: High | G13: Overdue
... A61: ACT060 | B61: PRJ032 | C61: Schedule architecture review | D61: Sarah Lee | E61: 46037 | F61: Low | G61: Overdue

Sheet Milestones
A1: Project ID | B1: Milestone | C1: Planned Date | D1: Forecast Date | E1: Actual Date | F1: Status | G1: Owner | H1: Source | I1: _Key
A2: PRJ001 | B2: Discovery | C2: =IFERROR(INDEX(StageGates!$I:$I,MATCH(I2,StageGates!$O:$O,0)),"") | D2: =IFERROR(INDEX(StageGates!$J:$J,MATCH(I2,StageGates!$O:$O,0)),"") | E2: =IFERROR(INDEX(StageGates!$J:$J,MATCH(I2,StageGates!$O:$O,0)),"") | F2: =IFERROR(INDEX(StageGates!$G:$G,MATCH(I2,StageGates!$O:$O,0)),"") | G2: =IFERROR(INDEX(StageGates!$H:$H,MATCH(I2,StageGates!$O:$O,0)),"") | H2: StageGate | I2: =A2&"|"&B2
A3: PRJ001 | B3: Business Case / Seed Funding | C3: =IFERROR(INDEX(StageGates!$I:$I,MATCH(I3,StageGates!$O:$O,0)),"") | D3: =IFERROR(INDEX(StageGates!$J:$J,MATCH(I3,StageGates!$O:$O,0)),"") | E3: =IFERROR(INDEX(StageGates!$J:$J,MATCH(I3,StageGates!$O:$O,0)),"") | F3: =IFERROR(INDEX(StageGates!$G:$G,MATCH(I3,StageGates!$O:$O,0)),"") | G3: =IFERROR(INDEX(StageGates!$H:$H,MATCH(I3,StageGates!$O:$O,0)),"") | H3: StageGate | I3: =A3&"|"&B3
A4: PRJ001 | B4: Design | C4: =IFERROR(INDEX(StageGates!$I:$I,MATCH(I4,StageGates!$O:$O,0)),"") | D4: =IFERROR(INDEX(StageGates!$J:$J,MATCH(I4,StageGates!$O:$O,0)),"") | E4: =IFERROR(INDEX(StageGates!$J:$J,MATCH(I4,StageGates!$O:$O,0)),"") | F4: =IFERROR(INDEX(StageGates!$G:$G,MATCH(I4,StageGates!$O:$O,0)),"") | G4: =IFERROR(INDEX(StageGates!$H:$H,MATCH(I4,StageGates!$O:$O,0)),"") | H4: StageGate | I4: =A4&"|"&B4
A5: PRJ001 | B5: Business Case / Full Funding | C5: =IFERROR(INDEX(StageGates!$I:$I,MATCH(I5,StageGates!$O:$O,0)),"") | D5: =IFERROR(INDEX(StageGates!$J:$J,MATCH(I5,StageGates!$O:$O,0)),"") | E5: =IFERROR(INDEX(StageGates!$J:$J,MATCH(I5,StageGates!$O:$O,0)),"") | F5: =IFERROR(INDEX(StageGates!$G:$G,MATCH(I5,StageGates!$O:$O,0)),"") | G5: =IFERROR(INDEX(StageGates!$H:$H,MATCH(I5,StageGates!$O:$O,0)),"") | H5: StageGate | I5: =A5&"|"&B5
A6: PRJ001 | B6: Build | C6: =IFERROR(INDEX(StageGates!$I:$I,MATCH(I6,StageGates!$O:$O,0)),"") | D6: =IFERROR(INDEX(StageGates!$J:$J,MATCH(I6,StageGates!$O:$O,0)),"") | E6: =IFERROR(INDEX(StageGates!$J:$J,MATCH(I6,StageGates!$O:$O,0)),"") | F6: =IFERROR(INDEX(StageGates!$G:$G,MATCH(I6,StageGates!$O:$O,0)),"") | G6: =IFERROR(INDEX(StageGates!$H:$H,MATCH(I6,StageGates!$O:$O,0)),"") | H6: StageGate | I6: =A6&"|"&B6
A7: PRJ001 | B7: Testing | C7: =IFERROR(INDEX(StageGates!$I:$I,MATCH(I7,StageGates!$O:$O,0)),"") | D7: =IFERROR(INDEX(StageGates!$J:$J,MATCH(I7,StageGates!$O:$O,0)),"") | E7: =IFERROR(INDEX(StageGates!$J:$J,MATCH(I7,StageGates!$O:$O,0)),"") | F7: =IFERROR(INDEX(StageGates!$G:$G,MATCH(I7,StageGates!$O:$O,0)),"") | G7: =IFERROR(INDEX(StageGates!$H:$H,MATCH(I7,StageGates!$O:$O,0)),"") | H7: StageGate | I7: =A7&"|"&B7
A8: PRJ001 | B8: Deployment | C8: =IFERROR(INDEX(StageGates!$I:$I,MATCH(I8,StageGates!$O:$O,0)),"") | D8: =IFERROR(INDEX(StageGates!$J:$J,MATCH(I8,StageGates!$O:$O,0)),"") | E8: =IFERROR(INDEX(StageGates!$J:$J,MATCH(I8,StageGates!$O:$O,0)),"") | F8: =IFERROR(INDEX(StageGates!$G:$G,MATCH(I8,StageGates!$O:$O,0)),"") | G8: =IFERROR(INDEX(StageGates!$H:$H,MATCH(I8,StageGates!$O:$O,0)),"") | H8: StageGate | I8: =A8&"|"&B8
A9: PRJ001 | B9: Handover | C9: =IFERROR(INDEX(StageGates!$I:$I,MATCH(I9,StageGates!$O:$O,0)),"") | D9: =IFERROR(INDEX(StageGates!$J:$J,MATCH(I9,StageGates!$O:$O,0)),"") | E9: =IFERROR(INDEX(StageGates!$J:$J,MATCH(I9,StageGates!$O:$O,0)),"") | F9: =IFERROR(INDEX(StageGates!$G:$G,MATCH(I9,StageGates!$O:$O,0)),"") | G9: =IFERROR(INDEX(StageGates!$H:$H,MATCH(I9,StageGates!$O:$O,0)),"") | H9: StageGate | I9: =A9&"|"&B9
A10: PRJ002 | B10: Discovery | C10: =IFERROR(INDEX(StageGates!$I:$I,MATCH(I10,StageGates!$O:$O,0)),"") | D10: =IFERROR(INDEX(StageGates!$J:$J,MATCH(I10,StageGates!$O:$O,0)),"") | E10: =IFERROR(INDEX(StageGates!$J:$J,MATCH(I10,StageGates!$O:$O,0)),"") | F10: =IFERROR(INDEX(StageGates!$G:$G,MATCH(I10,StageGates!$O:$O,0)),"") | G10: =IFERROR(INDEX(StageGates!$H:$H,MATCH(I10,StageGates!$O:$O,0)),"") | H10: StageGate | I10: =A10&"|"&B10
A11: PRJ002 | B11: Business Case / Seed Funding | C11: =IFERROR(INDEX(StageGates!$I:$I,MATCH(I11,StageGates!$O:$O,0)),"") | D11: =IFERROR(INDEX(StageGates!$J:$J,MATCH(I11,StageGates!$O:$O,0)),"") | E11: =IFERROR(INDEX(StageGates!$J:$J,MATCH(I11,StageGates!$O:$O,0)),"") | F11: =IFERROR(INDEX(StageGates!$G:$G,MATCH(I11,StageGates!$O:$O,0)),"") | G11: =IFERROR(INDEX(StageGates!$H:$H,MATCH(I11,StageGates!$O:$O,0)),"") | H11: StageGate | I11: =A11&"|"&B11
A12: PRJ002 | B12: Design | C12: =IFERROR(INDEX(StageGates!$I:$I,MATCH(I12,StageGates!$O:$O,0)),"") | D12: =IFERROR(INDEX(StageGates!$J:$J,MATCH(I12,StageGates!$O:$O,0)),"") | E12: =IFERROR(INDEX(StageGates!$J:$J,MATCH(I12,StageGates!$O:$O,0)),"") | F12: =IFERROR(INDEX(StageGates!$G:$G,MATCH(I12,StageGates!$O:$O,0)),"") | G12: =IFERROR(INDEX(StageGates!$H:$H,MATCH(I12,StageGates!$O:$O,0)),"") | H12: StageGate | I12: =A12&"|"&B12
A13: PRJ002 | B13: Business Case / Full Funding | C13: =IFERROR(INDEX(StageGates!$I:$I,MATCH(I13,StageGates!$O:$O,0)),"") | D13: =IFERROR(INDEX(StageGates!$J:$J,MATCH(I13,StageGates!$O:$O,0)),"") | E13: =IFERROR(INDEX(StageGates!$J:$J,MATCH(I13,StageGates!$O:$O,0)),"") | F13: =IFERROR(INDEX(StageGates!$G:$G,MATCH(I13,StageGates!$O:$O,0)),"") | G13: =IFERROR(INDEX(StageGates!$H:$H,MATCH(I13,StageGates!$O:$O,0)),"") | H13: StageGate | I13: =A13&"|"&B13
... A321: PRJ040 | B321: Handover | C321: =IFERROR(INDEX(StageGates!$I:$I,MATCH(I321,StageGates!$O:$O,0)),"") | D321: =IFERROR(INDEX(StageGates!$J:$J,MATCH(I321,StageGates!$O:$O,0)),"") | E321: =IFERROR(INDEX(StageGates!$J:$J,MATCH(I321,StageGates!$O:$O,0)),"") | F321: =IFERROR(INDEX(StageGates!$G:$G,MATCH(I321,StageGates!$O:$O,0)),"") | G321: =IFERROR(INDEX(StageGates!$H:$H,MATCH(I321,StageGates!$O:$O,0)),"") | H321: StageGate | I321: =A321&"|"&B321

Sheet PortfolioMovements
A1: Movement ID | B1: Project ID | C1: Project Name | D1: From Category | E1: To Category | F1: Moved By | G1: Moved On | H1: Reason
A2: MV001 | B2: PRJ009 | C2: ERP Modernisation | D2: CAPEX | E2: IT Strategic | F2: sponsor | G2: 46028 | H2: Promoted from unfunded to IT strategic
A3: MV002 | B3: PRJ009 | C3: ERP Modernisation | D3: Business Strategic | E3: IT Strategic | F3: admin | G3: 45875 | H3: Reclassified following strategy review
A4: MV003 | B4: PRJ023 | C4: Workforce Portal | D4: Business Strategic | E4: Unfunded | F4: admin | G4: 45856 | H4: De-funded; moved to unfunded backlog
A5: MV004 | B5: PRJ028 | C5: Mobile App 2 | D5: Business Strategic | E5: CAPEX | F5: governance | G5: 45917 | H5: De-funded; moved to unfunded backlog
A6: MV005 | B6: PRJ032 | C6: Compliance Hub | D6: Business Strategic | E6: CAPEX | F6: admin | G6: 46001 | H6: Reclassified following strategy review
A7: MV006 | B7: PRJ033 | C7: Risk Platform | D7: IT Strategic | E7: Business Strategic | F7: governance | G7: 46039 | H7: Funding approved — move to CAPEX
A8: MV007 | B8: PRJ017 | C8: App Modernisation | D8: IT Strategic | E8: Unfunded | F8: governance | G8: 45893 | H8: Promoted from unfunded to IT strategic
A9: MV008 | B9: PRJ007 | C9: CRM Upgrade | D9: IT Strategic | E9: Business Strategic | F9: sponsor | G9: 46004 | H9: Reclassified following strategy review
A10: MV009 | B10: PRJ015 | C10: Service Desk | D10: Business Strategic | E10: IT Strategic | F10: governance | G10: 45852 | H10: De-funded; moved to unfunded backlog
A11: MV010 | B11: PRJ013 | C11: API Gateway | D11: IT Strategic | E11: CAPEX | F11: admin | G11: 46000 | H11: Reclassified following strategy review

Sheet Prioritisation
A1: Project ID | B1: Project Name | C1: Strategic Alignment (1-5) | D1: Benefit Value (1-5) | E1: Risk Reduction (1-5) | F1: Compliance (1-5) | G1: Complexity (1-5) | H1: Score
A2: PRJ027 | B2: =IFERROR(VLOOKUP(A2,Projects!$A:$AK,2,FALSE()),"") | C2: 4 | D2: 5 | E2: 5 | F2: 3 | G2: 3 | H2: =(C2*0.3+D2*0.25+E2*0.2+F2*0.15-G2*0.1)*20
A3: PRJ011 | B3: =IFERROR(VLOOKUP(A3,Projects!$A:$AK,2,FALSE()),"") | C3: 3 | D3: 5 | E3: 5 | F3: 5 | G3: 3 | H3: =(C3*0.3+D3*0.25+E3*0.2+F3*0.15-G3*0.1)*20
A4: PRJ037 | B4: =IFERROR(VLOOKUP(A4,Projects!$A:$AK,2,FALSE()),"") | C4: 4 | D4: 3 | E4: 5 | F4: 5 | G4: 2 | H4: =(C4*0.3+D4*0.25+E4*0.2+F4*0.15-G4*0.1)*20
A5: PRJ034 | B5: =IFERROR(VLOOKUP(A5,Projects!$A:$AK,2,FALSE()),"") | C5: 4 | D5: 5 | E5: 3 | F5: 3 | G5: 1 | H5: =(C5*0.3+D5*0.25+E5*0.2+F5*0.15-G5*0.1)*20
A6: PRJ024 | B6: =IFERROR(VLOOKUP(A6,Projects!$A:$AK,2,FALSE()),"") | C6: 4 | D6: 5 | E6: 4 | F6: 4 | G6: 5 | H6: =(C6*0.3+D6*0.25+E6*0.2+F6*0.15-G6*0.1)*20
A7: PRJ039 | B7: =IFERROR(VLOOKUP(A7,Projects!$A:$AK,2,FALSE()),"") | C7: 5 | D7: 4 | E7: 2 | F7: 4 | G7: 2 | H7: =(C7*0.3+D7*0.25+E7*0.2+F7*0.15-G7*0.1)*20
A8: PRJ003 | B8: =IFERROR(VLOOKUP(A8,Projects!$A:$AK,2,FALSE()),"") | C8: 4 | D8: 1 | E8: 5 | F8: 4 | G8: 1 | H8: =(C8*0.3+D8*0.25+E8*0.2+F8*0.15-G8*0.1)*20
A9: PRJ016 | B9: =IFERROR(VLOOKUP(A9,Projects!$A:$AK,2,FALSE()),"") | C9: 3 | D9: 4 | E9: 2 | F9: 5 | G9: 2 | H9: =(C9*0.3+D9*0.25+E9*0.2+F9*0.15-G9*0.1)*20
A10: PRJ040 | B10: =IFERROR(VLOOKUP(A10,Projects!$A:$AK,2,FALSE()),"") | C10: 4 | D10: 3 | E10: 2 | F10: 4 | G10: 1 | H10: =(C10*0.3+D10*0.25+E10*0.2+F10*0.15-G10*0.1)*20
A11: PRJ036 | B11: =IFERROR(VLOOKUP(A11,Projects!$A:$AK,2,FALSE()),"") | C11: 3 | D11: 1 | E11: 5 | F11: 5 | G11: 1 | H11: =(C11*0.3+D11*0.25+E11*0.2+F11*0.15-G11*0.1)*20
A12: PRJ018 | B12: =IFERROR(VLOOKUP(A12,Projects!$A:$AK,2,FALSE()),"") | C12: 3 | D12: 5 | E12: 3 | F12: 3 | G12: 4 | H12: =(C12*0.3+D12*0.25+E12*0.2+F12*0.15-G12*0.1)*20
A13: PRJ020 | B13: =IFERROR(VLOOKUP(A13,Projects!$A:$AK,2,FALSE()),"") | C13: 5 | D13: 5 | E13: 1 | F13: 2 | G13: 5 | H13: =(C13*0.3+D13*0.25+E13*0.2+F13*0.15-G13*0.1)*20
... A41: PRJ006 | B41: =IFERROR(VLOOKUP(A41,Projects!$A:$AK,2,FALSE()),"") | C41: 2 | D41: 1 | E41: 1 | F41: 1 | G41: 3 | H41: =(C41*0.3+D41*0.25+E41*0.2+F41*0.15-G41*0.1)*20

Sheet Config
A1: Category | B1: Value | C1: Display Order | D1: Active
A2: Status | B2: Active | C2: 1 | D2: =TRUE()
A3: Status | B3: Active | C3: 2 | D3: =TRUE()
A4: Status | B4: Active | C4: 3 | D4: =TRUE()
A5: Status | B5: Completed | C5: 4 | D5: =TRUE()
A6: Status | B6: Pipeline | C6: 5 | D6: =TRUE()
A7: Status | B7: On Hold | C7: 6 | D7: =TRUE()
A8: Status | B8: Cancelled | C8: 7 | D8: =TRUE()
A9: RAG | B9: Green | C9: 1 | D9: =TRUE()
A10: RAG | B10: Amber | C10: 2 | D10: =TRUE()
A11: RAG | B11: Red | C11: 3 | D11: =TRUE()
A12: Priority | B12: P1 - Critical | C12: 1 | D12: =TRUE()
A13: Priority | B13: P2 - High | C13: 2 | D13: =TRUE()
... A86: Gate Status | B86: On Hold | C86: 7 | D86: =TRUE()
A87: Gate Outcome | C87: 1 | D87: =TRUE()
A88: Gate Outcome | B88: Proceed | C88: 2 | D88: =TRUE()
A89: Gate Outcome | B89: Conditional | C89: 3 | D89: =TRUE()
A90: Gate Outcome | B90: Rework | C90: 4 | D90: =TRUE()
A91: Gate Outcome | B91: Held | C91: 5 | D91: =TRUE()
A92: Decision Status | B92: Open | C92: 1 | D92: =TRUE()
A93: Decision Status | B93: In Review | C93: 2 | D93: =TRUE()
A94: Decision Status | B94: Approved | C94: 3 | D94: =TRUE()
A95: Decision Status | B95: Rejected | C95: 4 | D95: =TRUE()
A96: Decision Status | B96: Closed | C96: 5 | D96: =TRUE()
A97: Decision Type | B97: Project | C97: 1 | D97: =TRUE()
A98: Decision Type | B98: Program | C98: 2 | D98: =TRUE()
A99: Decision Type | B99: Portfolio | C99: 3 | D99: =TRUE()
... A167: Pipeline Decision | B167: Parked | C167: 5 | D167: =TRUE()

Sheet ConfigRules
A1: Key | B1: Value | C1: Type | D1: Description
A2: GOV_CHANNEL_THRESHOLD | B2: 200000 | C2: currency | D2: Approved $ at/below which a project is Channel A
A3: SCHEDULE_AMBER_VARIANCE | B3: -0.05 | C3: ratio | D3: Schedule variance worse than this → Amber
A4: SCHEDULE_RED_VARIANCE | B4: -0.1 | C4: ratio | D4: Schedule variance worse than this → Red
A5: FINANCIAL_AMBER_VARIANCE | B5: 0.05 | C5: ratio | D5: (Forecast-Approved)/Approved above → Amber
A6: FINANCIAL_RED_VARIANCE | B6: 0.1 | C6: ratio | D6: (Forecast-Approved)/Approved above → Red
A7: BENEFIT_GREEN_THRESHOLD | B7: 0.7 | C7: ratio | D7: Benefit realisation ≥ → Green
A8: BENEFIT_AMBER_THRESHOLD | B8: 0.3 | C8: ratio | D8: Benefit realisation ≥ → Amber (else Red)
A9: DELIVERY_AMBER_DAYS_LATE | B9: 1 | C9: int | D9: Stage gate days late ≥ → Amber
A10: DELIVERY_RED_DAYS_LATE | B10: 15 | C10: int | D10: Stage gate days late ≥ → Red
A11: UPCOMING_GATE_WINDOW_DAYS | B11: 30 | C11: int | D11: Window for 'upcoming stage gates' KPI
A12: PRIORITY_SCORE_WEIGHT_STRAT | B12: 0.3 | C12: ratio | D12: Prioritisation: strategic weight
A13: PRIORITY_SCORE_WEIGHT_BENEFIT | B13: 0.25 | C13: ratio | D13: Prioritisation: benefit weight
... A16: PRIORITY_SCORE_WEIGHT_CPLX | B16: 0.1 | C16: ratio | D16: Prioritisation: complexity penalty
A17: CURRENCY_SYMBOL | B17: $ | C17: text | D17: Symbol shown in KPI cards

Sheet Sprints
A1: Sprint ID | B1: Project ID | C1: Project Name | D1: Sprint # | E1: Sprint Name | F1: Start Date | G1: End Date | H1: Points Committed | I1: Points Completed | J1: Stories Committed | K1: Stories Completed | L1: Status | M1: Team
A2: SP0001 | B2: PRJ001 | C2: =IFERROR(VLOOKUP(B2,Projects!$A:$AK,2,FALSE()),"") | D2: 1 | E2: PRJ001 Sprint 1 | F2: =IFERROR(VLOOKUP(B2,Projects!$A:$AK,16,FALSE()),"") | G2: =IFERROR(VLOOKUP(B2,Projects!$A:$AK,17,FALSE()),"") | H2: 37 | I2: 39 | J2: 7 | K2: 7 | L2: Complete | M2: Alex Brown
A3: SP0002 | B3: PRJ001 | C3: =IFERROR(VLOOKUP(B3,Projects!$A:$AK,2,FALSE()),"") | D3: 2 | E3: PRJ001 Sprint 2 | F3: =IFERROR(VLOOKUP(B3,Projects!$A:$AK,16,FALSE()),"") | G3: =IFERROR(VLOOKUP(B3,Projects!$A:$AK,17,FALSE()),"") | H3: 37 | I3: 30 | J3: 7 | K3: 6 | L3: Complete | M3: Alex Brown
A4: SP0003 | B4: PRJ001 | C4: =IFERROR(VLOOKUP(B4,Projects!$A:$AK,2,FALSE()),"") | D4: 3 | E4: PRJ001 Sprint 3 | F4: =IFERROR(VLOOKUP(B4,Projects!$A:$AK,16,FALSE()),"") | G4: =IFERROR(VLOOKUP(B4,Projects!$A:$AK,17,FALSE()),"") | H4: 38 | I4: 41 | J4: 7 | K4: 8 | L4: Complete | M4: Alex Brown
A5: SP0004 | B5: PRJ001 | C5: =IFERROR(VLOOKUP(B5,Projects!$A:$AK,2,FALSE()),"") | D5: 4 | E5: PRJ001 Sprint 4 | F5: =IFERROR(VLOOKUP(B5,Projects!$A:$AK,16,FALSE()),"") | G5: =IFERROR(VLOOKUP(B5,Projects!$A:$AK,17,FALSE()),"") | H5: 37 | I5: 34 | J5: 7 | K5: 6 | L5: Complete | M5: Alex Brown
A6: SP0005 | B6: PRJ001 | C6: =IFERROR(VLOOKUP(B6,Projects!$A:$AK,2,FALSE()),"") | D6: 5 | E6: PRJ001 Sprint 5 | F6: =IFERROR(VLOOKUP(B6,Projects!$A:$AK,16,FALSE()),"") | G6: =IFERROR(VLOOKUP(B6,Projects!$A:$AK,17,FALSE()),"") | H6: 32 | I6: 29 | J6: 6 | K6: 5 | L6: Complete | M6: Alex Brown
A7: SP0006 | B7: PRJ001 | C7: =IFERROR(VLOOKUP(B7,Projects!$A:$AK,2,FALSE()),"") | D7: 6 | E7: PRJ001 Sprint 6 | F7: =IFERROR(VLOOKUP(B7,Projects!$A:$AK,16,FALSE()),"") | G7: =IFERROR(VLOOKUP(B7,Projects!$A:$AK,17,FALSE()),"") | H7: 37 | I7: 30 | J7: 7 | K7: 6 | L7: Complete | M7: Alex Brown
A8: SP0007 | B8: PRJ001 | C8: =IFERROR(VLOOKUP(B8,Projects!$A:$AK,2,FALSE()),"") | D8: 7 | E8: PRJ001 Sprint 7 | F8: =IFERROR(VLOOKUP(B8,Projects!$A:$AK,16,FALSE()),"") | G8: =IFERROR(VLOOKUP(B8,Projects!$A:$AK,17,FALSE()),"") | H8: 44 | I8: 38 | J8: 8 | K8: 7 | L8: Complete | M8: Alex Brown
A9: SP0008 | B9: PRJ001 | C9: =IFERROR(VLOOKUP(B9,Projects!$A:$AK,2,FALSE()),"") | D9: 8 | E9: PRJ001 Sprint 8 | F9: =IFERROR(VLOOKUP(B9,Projects!$A:$AK,16,FALSE()),"") | G9: =IFERROR(VLOOKUP(B9,Projects!$A:$AK,17,FALSE()),"") | H9: 34 | I9: 26 | J9: 6 | K9: 5 | L9: Complete | M9: Alex Brown
A10: SP0009 | B10: PRJ002 | C10: =IFERROR(VLOOKUP(B10,Projects!$A:$AK,2,FALSE()),"") | D10: 1 | E10: PRJ002 Sprint 1 | F10: =IFERROR(VLOOKUP(B10,Projects!$A:$AK,16,FALSE()),"") | G10: =IFERROR(VLOOKUP(B10,Projects!$A:$AK,17,FALSE()),"") | H10: 32 | I10: 27 | J10: 6 | K10: 5 | L10: Complete | M10: Carlos Diaz
A11: SP0010 | B11: PRJ002 | C11: =IFERROR(VLOOKUP(B11,Projects!$A:$AK,2,FALSE()),"") | D11: 2 | E11: PRJ002 Sprint 2 | F11: =IFERROR(VLOOKUP(B11,Projects!$A:$AK,16,FALSE()),"") | G11: =IFERROR(VLOOKUP(B11,Projects!$A:$AK,17,FALSE()),"") | H11: 33 | I11: 33 | J11: 6 | K11: 6 | L11: Complete | M11: Carlos Diaz
A12: SP0011 | B12: PRJ002 | C12: =IFERROR(VLOOKUP(B12,Projects!$A:$AK,2,FALSE()),"") | D12: 3 | E12: PRJ002 Sprint 3 | F12: =IFERROR(VLOOKUP(B12,Projects!$A:$AK,16,FALSE()),"") | G12: =IFERROR(VLOOKUP(B12,Projects!$A:$AK,17,FALSE()),"") | H12: 22 | I12: 26 | J12: 4 | K12: 5 | L12: Complete | M12: Carlos Diaz
A13: SP0012 | B13: PRJ002 | C13: =IFERROR(VLOOKUP(B13,Projects!$A:$AK,2,FALSE()),"") | D13: 4 | E13: PRJ002 Sprint 4 | F13: =IFERROR(VLOOKUP(B13,Projects!$A:$AK,16,FALSE()),"") | G13: =IFERROR(VLOOKUP(B13,Projects!$A:$AK,17,FALSE()),"") | H13: 23 | I13: 11 | J13: 4 | K13: 2 | L13: Complete | M13: Carlos Diaz
... A217: SP0216 | B217: PRJ038 | C217: =IFERROR(VLOOKUP(B217,Projects!$A:$AK,2,FALSE()),"") | D217: 8 | E217: PRJ038 Sprint 8 | F217: =IFERROR(VLOOKUP(B217,Projects!$A:$AK,16,FALSE()),"") | G217: =IFERROR(VLOOKUP(B217,Projects!$A:$AK,17,FALSE()),"") | H217: 41 | I217: 43 | J217: 8 | K217: 8 | L217: Complete | M217: Jane Doe

Sheet Releases
A1: Release ID | B1: Project ID | C1: Project Name | D1: Release Name | E1: Version | F1: Type | G1: Planned Date | H1: Actual Date | I1: Status | J1: Owner | K1: Environment | L1: Notes
A2: REL0001 | B2: PRJ001 | C2: =IFERROR(VLOOKUP(B2,Projects!$A:$AK,2,FALSE()),"") | D2: Customer Portal R1 | E2: 1.0.0 | F2: Patch | G2: 45780 | H2: 45781 | I2: Delivered | J2: Alex Brown | K2: Production
A3: REL0002 | B3: PRJ001 | C3: =IFERROR(VLOOKUP(B3,Projects!$A:$AK,2,FALSE()),"") | D3: Customer Portal R2 | E3: 2.0.0 | F3: Major | G3: 45858 | H3: 45854 | I3: Delivered | J3: Alex Brown | K3: UAT
A4: REL0003 | B4: PRJ001 | C4: =IFERROR(VLOOKUP(B4,Projects!$A:$AK,2,FALSE()),"") | D4: Customer Portal R3 | E4: 3.0.0 | F4: Patch | G4: 45937 | H4: 45942 | I4: Delivered | J4: Alex Brown | K4: Production
A5: REL0004 | B5: PRJ001 | C5: =IFERROR(VLOOKUP(B5,Projects!$A:$AK,2,FALSE()),"") | D5: Customer Portal R4 | E5: 4.0.0 | F5: Patch | G5: 46015 | H5: 46016 | I5: Delivered | J5: Alex Brown | K5: UAT
A6: REL0005 | B6: PRJ002 | C6: =IFERROR(VLOOKUP(B6,Projects!$A:$AK,2,FALSE()),"") | D6: Cloud Migration R1 | E6: 1.0.0 | F6: Minor | G6: 45777 | H6: 45787 | I6: Delivered | J6: Carlos Diaz | K6: Staging
A7: REL0006 | B7: PRJ002 | C7: =IFERROR(VLOOKUP(B7,Projects!$A:$AK,2,FALSE()),"") | D7: Cloud Migration R2 | E7: 2.0.0 | F7: Patch | G7: 45817 | H7: 45825 | I7: Delivered | J7: Carlos Diaz | K7: Staging
A8: REL0007 | B8: PRJ002 | C8: =IFERROR(VLOOKUP(B8,Projects!$A:$AK,2,FALSE()),"") | D8: Cloud Migration R3 | E8: 3.0.0 | F8: Major | G8: 45857 | H8: 45864 | I8: Delivered | J8: Carlos Diaz | K8: Staging
A9: REL0008 | B9: PRJ002 | C9: =IFERROR(VLOOKUP(B9,Projects!$A:$AK,2,FALSE()),"") | D9: Cloud Migration R4 | E9: 4.0.0 | F9: Major | G9: 45897 | H9: 45898 | I9: Delivered | J9: Carlos Diaz | K9: Staging
A10: REL0009 | B10: PRJ003 | C10: =IFERROR(VLOOKUP(B10,Projects!$A:$AK,2,FALSE()),"") | D10: Data Platform R1 | E10: 1.0.0 | F10: Patch | G10: 45906 | H10: 45911 | I10: Delivered | J10: Carlos Diaz | K10: Production
A11: REL0010 | B11: PRJ003 | C11: =IFERROR(VLOOKUP(B11,Projects!$A:$AK,2,FALSE()),"") | D11: Data Platform R2 | E11: 2.0.0 | F11: Hotfix | G11: 46056 | H11: 46055 | I11: Delivered | J11: Carlos Diaz | K11: Production
A12: REL0011 | B12: PRJ004 | C12: =IFERROR(VLOOKUP(B12,Projects!$A:$AK,2,FALSE()),"") | D12: AI Assistant R1 | E12: 1.0.0 | F12: Major | G12: 46023 | H12: 46028 | I12: Delivered | J12: Jane Doe | K12: Staging
A13: REL0012 | B13: PRJ004 | C13: =IFERROR(VLOOKUP(B13,Projects!$A:$AK,2,FALSE()),"") | D13: AI Assistant R2 | E13: 2.0.0 | F13: Patch | G13: 46116 | H13: 46124 | I13: Delivered | J13: Jane Doe | K13: Staging
A14: REL0013 | B14: PRJ004 | C14: =IFERROR(VLOOKUP(B14,Projects!$A:$AK,2,FALSE()),"") | D14: AI Assistant R3 | E14: 3.0.0 | F14: Hotfix | G14: 46208 | H14: 46203 | I14: Delivered | J14: Jane Doe | K14: Production
A15: REL0014 | B15: PRJ004 | C15: =IFERROR(VLOOKUP(B15,Projects!$A:$AK,2,FALSE()),"") | D15: AI Assistant R4 | E15: 4.0.0 | F15: Hotfix | G15: 46301 | I15: Planned | J15: Jane Doe | K15: Staging
A16: REL0015 | B16: PRJ005 | C16: =IFERROR(VLOOKUP(B16,Projects!$A:$AK,2,FALSE()),"") | D16: Network Refresh R1 | E16: 1.0.0 | F16: Minor | G16: 46131 | H16: 46127 | I16: Delivered | J16: Priya Patel | K16: Staging
A17: REL0016 | B17: PRJ006 | C17: =IFERROR(VLOOKUP(B17,Projects!$A:$AK,2,FALSE()),"") | D17: Cyber Security Program R1 | E17: 1.0.0 | F17: Minor | G17: 45873 | H17: 45881 | I17: Delivered | J17: Alex Brown | K17: Staging
A18: REL0017 | B18: PRJ006 | C18: =IFERROR(VLOOKUP(B18,Projects!$A:$AK,2,FALSE()),"") | D18: Cyber Security Program R2 | E18: 2.0.0 | F18: Minor | G18: 46010 | H18: 46017 | I18: Delivered | J18: Alex Brown | K18: UAT
A19: REL0018 | B19: PRJ007 | C19: =IFERROR(VLOOKUP(B19,Projects!$A:$AK,2,FALSE()),"") | D19: CRM Upgrade R1 | E19: 1.0.0 | F19: Major | G19: 45987 | H19: 45988 | I19: Delivered | J19: Alex Brown | K19: UAT
A20: REL0019 | B20: PRJ007 | C20: =IFERROR(VLOOKUP(B20,Projects!$A:$AK,2,FALSE()),"") | D20: CRM Upgrade R2 | E20: 2.0.0 | F20: Major | G20: 46183 | H20: 46189 | I20: Delivered | J20: Alex Brown | K20: UAT
A21: REL0020 | B21: PRJ008 | C21: =IFERROR(VLOOKUP(B21,Projects!$A:$AK,2,FALSE()),"") | D21: Mobile App R1 | E21: 1.0.0 | F21: Hotfix | G21: 45809 | H21: 45807 | I21: Delivered | J21: Carlos Diaz | K21: Staging
A22: REL0021 | B22: PRJ008 | C22: =IFERROR(VLOOKUP(B22,Projects!$A:$AK,2,FALSE()),"") | D22: Mobile App R2 | E22: 2.0.0 | F22: Hotfix | G22: 45839 | H22: 45848 | I22: Delivered | J22: Carlos Diaz | K22: UAT
A23: REL0022 | B23: PRJ008 | C23: =IFERROR(VLOOKUP(B23,Projects!$A:$AK,2,FALSE()),"") | D23: Mobile App R3 | E23: 3.0.0 | F23: Patch | G23: 45869 | H23: 45875 | I23: Delivered | J23: Carlos Diaz | K23: Staging
A24: REL0023 | B24: PRJ009 | C24: =IFERROR(VLOOKUP(B24,Projects!$A:$AK,2,FALSE()),"") | D24: ERP Modernisation R1 | E24: 1.0.0 | F24: Major | G24: 46072 | H24: 46077 | I24: Delivered | J24: Jane Doe | K24: Production
A25: REL0024 | B25: PRJ009 | C25: =IFERROR(VLOOKUP(B25,Projects!$A:$AK,2,FALSE()),"") | D25: ERP Modernisation R2 | E25: 2.0.0 | F25: Hotfix | G25: 46122 | H25: 46131 | I25: Delivered | J25: Jane Doe | K25: UAT
A26: REL0025 | B26: PRJ009 | C26: =IFERROR(VLOOKUP(B26,Projects!$A:$AK,2,FALSE()),"") | D26: ERP Modernisation R3 | E26: 3.0.0 | F26: Minor | G26: 46172 | H26: 46172 | I26: Delivered | J26: Jane Doe | K26: Staging
A27: REL0026 | B27: PRJ009 | C27: =IFERROR(VLOOKUP(B27,Projects!$A:$AK,2,FALSE()),"") | D27: ERP Modernisation R4 | E27: 4.0.0 | F27: Hotfix | G27: 46222 | I27: In Progress | J27: Jane Doe | K27: UAT
A28: REL0027 | B28: PRJ010 | C28: =IFERROR(VLOOKUP(B28,Projects!$A:$AK,2,FALSE()),"") | D28: Workforce Enablement R1 | E28: 1.0.0 | F28: Patch | G28: 45782 | H28: 45790 | I28: Delivered | J28: Priya Patel | K28: Staging
A29: REL0028 | B29: PRJ010 | C29: =IFERROR(VLOOKUP(B29,Projects!$A:$AK,2,FALSE()),"") | D29: Workforce Enablement R2 | E29: 2.0.0 | F29: Major | G29: 45870 | H29: 45868 | I29: Delivered | J29: Priya Patel | K29: Production
A30: REL0029 | B30: PRJ010 | C30: =IFERROR(VLOOKUP(B30,Projects!$A:$AK,2,FALSE()),"") | D30: Workforce Enablement R3 | E30: 3.0.0 | F30: Major | G30: 45958 | H30: 45955 | I30: Delivered | J30: Priya Patel | K30: Staging
A31: REL0030 | B31: PRJ011 | C31: =IFERROR(VLOOKUP(B31,Projects!$A:$AK,2,FALSE()),"") | D31: IoT Initiative R1 | E31: 1.0.0 | F31: Hotfix | G31: 46016 | H31: 46014 | I31: Delivered | J31: Jane Doe | K31: Staging
A32: REL0031 | B32: PRJ011 | C32: =IFERROR(VLOOKUP(B32,Projects!$A:$AK,2,FALSE()),"") | D32: IoT Initiative R2 | E32: 2.0.0 | F32: Hotfix | G32: 46044 | H32: 46042 | I32: Delivered | J32: Jane Doe | K32: Staging
A33: REL0032 | B33: PRJ011 | C33: =IFERROR(VLOOKUP(B33,Projects!$A:$AK,2,FALSE()),"") | D33: IoT Initiative R3 | E33: 3.0.0 | F33: Patch | G33: 46072 | H33: 46068 | I33: Delivered | J33: Jane Doe | K33: UAT
A34: REL0033 | B34: PRJ011 | C34: =IFERROR(VLOOKUP(B34,Projects!$A:$AK,2,FALSE()),"") | D34: IoT Initiative R4 | E34: 4.0.0 | F34: Minor | G34: 46100 | H34: 46101 | I34: Delivered | J34: Jane Doe | K34: UAT
A35: REL0034 | B35: PRJ012 | C35: =IFERROR(VLOOKUP(B35,Projects!$A:$AK,2,FALSE()),"") | D35: Analytics Platform R1 | E35: 1.0.0 | F35: Minor | G35: 46037 | H35: 46035 | I35: Delivered | J35: Jane Doe | K35: UAT
A36: REL0035 | B36: PRJ012 | C36: =IFERROR(VLOOKUP(B36,Projects!$A:$AK,2,FALSE()),"") | D36: Analytics Platform R2 | E36: 2.0.0 | F36: Patch | G36: 46141 | H36: 46139 | I36: Delivered | J36: Jane Doe | K36: UAT
A37: REL0036 | B37: PRJ012 | C37: =IFERROR(VLOOKUP(B37,Projects!$A:$AK,2,FALSE()),"") | D37: Analytics Platform R3 | E37: 3.0.0 | F37: Hotfix | G37: 46244 | I37: In Progress | J37: Jane Doe | K37: Staging
A38: REL0037 | B38: PRJ012 | C38: =IFERROR(VLOOKUP(B38,Projects!$A:$AK,2,FALSE()),"") | D38: Analytics Platform R4 | E38: 4.0.0 | F38: Hotfix | G38: 46348 | I38: Planned | J38: Jane Doe | K38: Production
A39: REL0038 | B39: PRJ013 | C39: =IFERROR(VLOOKUP(B39,Projects!$A:$AK,2,FALSE()),"") | D39: API Gateway R1 | E39: 1.0.0 | F39: Patch | G39: 46110 | H39: 46112 | I39: Delivered | J39: Priya Patel | K39: UAT
A40: REL0039 | B40: PRJ013 | C40: =IFERROR(VLOOKUP(B40,Projects!$A:$AK,2,FALSE()),"") | D40: API Gateway R2 | E40: 2.0.0 | F40: Patch | G40: 46224 | I40: In Progress | J40: Priya Patel | K40: UAT
A41: REL0040 | B41: PRJ013 | C41: =IFERROR(VLOOKUP(B41,Projects!$A:$AK,2,FALSE()),"") | D41: API Gateway R3 | E41: 3.0.0 | F41: Hotfix | G41: 46338 | I41: Planned | J41: Priya Patel | K41: Staging
A42: REL0041 | B42: PRJ014 | C42: =IFERROR(VLOOKUP(B42,Projects!$A:$AK,2,FALSE()),"") | D42: Identity Mgmt R1 | E42: 1.0.0 | F42: Hotfix | G42: 45824 | H42: 45819 | I42: Delivered | J42: Alex Brown | K42: Production
A43: REL0042 | B43: PRJ014 | C43: =IFERROR(VLOOKUP(B43,Projects!$A:$AK,2,FALSE()),"") | D43: Identity Mgmt R2 | E43: 2.0.0 | F43: Major | G43: 45955 | H43: 45950 | I43: Delivered | J43: Alex Brown | K43: Production
A44: REL0043 | B44: PRJ015 | C44: =IFERROR(VLOOKUP(B44,Projects!$A:$AK,2,FALSE()),"") | D44: Service Desk R1 | E44: 1.0.0 | F44: Patch | G44: 45892 | H44: 45897 | I44: Delivered | J44: John Smith | K44: Production
A45: REL0044 | B45: PRJ015 | C45: =IFERROR(VLOOKUP(B45,Projects!$A:$AK,2,FALSE()),"") | D45: Service Desk R2 | E45: 2.0.0 | F45: Minor | G45: 45973 | H45: 45981 | I45: Delivered | J45: John Smith | K45: Staging
A46: REL0045 | B46: PRJ015 | C46: =IFERROR(VLOOKUP(B46,Projects!$A:$AK,2,FALSE()),"") | D46: Service Desk R3 | E46: 3.0.0 | F46: Minor | G46: 46054 | H46: 46061 | I46: Delivered | J46: John Smith | K46: Staging
A47: REL0046 | B47: PRJ016 | C47: =IFERROR(VLOOKUP(B47,Projects!$A:$AK,2,FALSE()),"") | D47: Infrastructure Upg R1 | E47: 1.0.0 | F47: Hotfix | G47: 46064 | H47: 46060 | I47: Delivered | J47: John Smith | K47: Production
A48: REL0047 | B48: PRJ016 | C48: =IFERROR(VLOOKUP(B48,Projects!$A:$AK,2,FALSE()),"") | D48: Infrastructure Upg R2 | E48: 2.0.0 | F48: Minor | G48: 46136 | H48: 46143 | I48: Delivered | J48: John Smith | K48: UAT
A49: REL0048 | B49: PRJ016 | C49: =IFERROR(VLOOKUP(B49,Projects!$A:$AK,2,FALSE()),"") | D49: Infrastructure Upg R3 | E49: 3.0.0 | F49: Minor | G49: 46208 | H49: 46213 | I49: Delivered | J49: John Smith | K49: UAT
A50: REL0049 | B50: PRJ016 | C50: =IFERROR(VLOOKUP(B50,Projects!$A:$AK,2,FALSE()),"") | D50: Infrastructure Upg R4 | E50: 4.0.0 | F50: Minor | G50: 46280 | I50: Planned | J50: John Smith | K50: Production
A51: REL0050 | B51: PRJ017 | C51: =IFERROR(VLOOKUP(B51,Projects!$A:$AK,2,FALSE()),"") | D51: App Modernisation R1 | E51: 1.0.0 | F51: Hotfix | G51: 45843 | H51: 45841 | I51: Delivered | J51: Priya Patel | K51: Staging
A52: REL0051 | B52: PRJ017 | C52: =IFERROR(VLOOKUP(B52,Projects!$A:$AK,2,FALSE()),"") | D52: App Modernisation R2 | E52: 2.0.0 | F52: Minor | G52: 45981 | H52: 45984 | I52: Delivered | J52: Priya Patel | K52: UAT
A53: REL0052 | B53: PRJ018 | C53: =IFERROR(VLOOKUP(B53,Projects!$A:$AK,2,FALSE()),"") | D53: RPA Program R1 | E53: 1.0.0 | F53: Major | G53: 46080 | H53: 46077 | I53: Delivered | J53: Carlos Diaz | K53: Production
A54: REL0053 | B54: PRJ018 | C54: =IFERROR(VLOOKUP(B54,Projects!$A:$AK,2,FALSE()),"") | D54: RPA Program R2 | E54: 2.0.0 | F54: Major | G54: 46204 | H54: 46212 | I54: Delivered | J54: Carlos Diaz | K54: Staging
A55: REL0054 | B55: PRJ019 | C55: =IFERROR(VLOOKUP(B55,Projects!$A:$AK,2,FALSE()),"") | D55: Vendor Mgmt R1 | E55: 1.0.0 | F55: Major | G55: 45937 | H55: 45932 | I55: Delivered | J55: Carlos Diaz | K55: Staging
A56: REL0055 | B56: PRJ019 | C56: =IFERROR(VLOOKUP(B56,Projects!$A:$AK,2,FALSE()),"") | D56: Vendor Mgmt R2 | E56: 2.0.0 | F56: Major | G56: 46133 | H56: 46140 | I56: Delivered | J56: Carlos Diaz | K56: Staging
A57: REL0056 | B57: PRJ020 | C57: =IFERROR(VLOOKUP(B57,Projects!$A:$AK,2,FALSE()),"") | D57: Process Automation R1 | E57: 1.0.0 | F57: Patch | G57: 45806 | H57: 45815 | I57: Delivered | J57: Carlos Diaz | K57: Production
A58: REL0057 | B58: PRJ020 | C58: =IFERROR(VLOOKUP(B58,Projects!$A:$AK,2,FALSE()),"") | D58: Process Automation R2 | E58: 2.0.0 | F58: Minor | G58: 45840 | H58: 45842 | I58: Delivered | J58: Carlos Diaz | K58: UAT
A59: REL0058 | B59: PRJ021 | C59: =IFERROR(VLOOKUP(B59,Projects!$A:$AK,2,FALSE()),"") | D59: Data Warehouse R1 | E59: 1.0.0 | F59: Hotfix | G59: 45725 | H59: 45727 | I59: Delivered | J59: Alex Brown | K59: UAT
A60: REL0059 | B60: PRJ021 | C60: =IFERROR(VLOOKUP(B60,Projects!$A:$AK,2,FALSE()),"") | D60: Data Warehouse R2 | E60: 2.0.0 | F60: Patch | G60: 45773 | H60: 45769 | I60: Delivered | J60: Alex Brown | K60: Production
A61: REL0060 | B61: PRJ022 | C61: =IFERROR(VLOOKUP(B61,Projects!$A:$AK,2,FALSE()),"") | D61: DevOps Tools R1 | E61: 1.0.0 | F61: Major | G61: 45850 | H61: 45845 | I61: Delivered | J61: Priya Patel | K61: Production
A62: REL0061 | B62: PRJ022 | C62: =IFERROR(VLOOKUP(B62,Projects!$A:$AK,2,FALSE()),"") | D62: DevOps Tools R2 | E62: 2.0.0 | F62: Major | G62: 45942 | H62: 45951 | I62: Delivered | J62: Priya Patel | K62: Production
A63: REL0062 | B63: PRJ023 | C63: =IFERROR(VLOOKUP(B63,Projects!$A:$AK,2,FALSE()),"") | D63: Workforce Portal R1 | E63: 1.0.0 | F63: Patch | G63: 46100 | H63: 46104 | I63: Delivered | J63: Jane Doe | K63: Production
A64: REL0063 | B64: PRJ023 | C64: =IFERROR(VLOOKUP(B64,Projects!$A:$AK,2,FALSE()),"") | D64: Workforce Portal R2 | E64: 2.0.0 | F64: Major | G64: 46227 | I64: In Progress | J64: Jane Doe | K64: Production
A65: REL0064 | B65: PRJ024 | C65: =IFERROR(VLOOKUP(B65,Projects!$A:$AK,2,FALSE()),"") | D65: Process Mining R1 | E65: 1.0.0 | F65: Minor | G65: 46079 | H65: 46085 | I65: Delivered | J65: Jane Doe | K65: UAT
A66: REL0065 | B66: PRJ024 | C66: =IFERROR(VLOOKUP(B66,Projects!$A:$AK,2,FALSE()),"") | D66: Process Mining R2 | E66: 2.0.0 | F66: Hotfix | G66: 46162 | H66: 46160 | I66: Delivered | J66: Jane Doe | K66: Production
A67: REL0066 | B67: PRJ024 | C67: =IFERROR(VLOOKUP(B67,Projects!$A:$AK,2,FALSE()),"") | D67: Process Mining R3 | E67: 3.0.0 | F67: Hotfix | G67: 46245 | I67: In Progress | J67: Jane Doe | K67: Production
A68: REL0067 | B68: PRJ024 | C68: =IFERROR(VLOOKUP(B68,Projects!$A:$AK,2,FALSE()),"") | D68: Process Mining R4 | E68: 4.0.0 | F68: Hotfix | G68: 46328 | I68: Planned | J68: Jane Doe | K68: Staging
A69: REL0068 | B69: PRJ025 | C69: =IFERROR(VLOOKUP(B69,Projects!$A:$AK,2,FALSE()),"") | D69: Customer Insights R1 | E69: 1.0.0 | F69: Hotfix | G69: 46214 | H69: 46215 | I69: Delivered | J69: Sarah Lee | K69: UAT
A70: REL0069 | B70: PRJ026 | C70: =IFERROR(VLOOKUP(B70,Projects!$A:$AK,2,FALSE()),"") | D70: ERP Modernisation 2 R1 | E70: 1.0.0 | F70: Minor | G70: 45993 | H70: 46002 | I70: Delivered | J70: Carlos Diaz | K70: Production
A71: REL0070 | B71: PRJ026 | C71: =IFERROR(VLOOKUP(B71,Projects!$A:$AK,2,FALSE()),"") | D71: ERP Modernisation 2 R2 | E71: 2.0.0 | F71: Major | G71: 46070 | H71: 46074 | I71: Delivered | J71: Carlos Diaz | K71: Production
A72: REL0071 | B72: PRJ026 | C72: =IFERROR(VLOOKUP(B72,Projects!$A:$AK,2,FALSE()),"") | D72: ERP Modernisation 2 R3 | E72: 3.0.0 | F72: Major | G72: 46147 | H72: 46143 | I72: Delivered | J72: Carlos Diaz | K72: UAT
A73: REL0072 | B73: PRJ027 | C73: =IFERROR(VLOOKUP(B73,Projects!$A:$AK,2,FALSE()),"") | D73: Cyber Program R1 | E73: 1.0.0 | F73: Major | G73: 45847 | H73: 45857 | I73: Delivered | J73: Mike Johnson | K73: Production
A74: REL0073 | B74: PRJ027 | C74: =IFERROR(VLOOKUP(B74,Projects!$A:$AK,2,FALSE()),"") | D74: Cyber Program R2 | E74: 2.0.0 | F74: Major | G74: 45919 | H74: 45922 | I74: Delivered | J74: Mike Johnson | K74: Production
A75: REL0074 | B75: PRJ027 | C75: =IFERROR(VLOOKUP(B75,Projects!$A:$AK,2,FALSE()),"") | D75: Cyber Program R3 | E75: 3.0.0 | F75: Major | G75: 45990 | H75: 45985 | I75: Delivered | J75: Mike Johnson | K75: Staging
A76: REL0075 | B76: PRJ028 | C76: =IFERROR(VLOOKUP(B76,Projects!$A:$AK,2,FALSE()),"") | D76: Mobile App 2 R1 | E76: 1.0.0 | F76: Patch | G76: 45851 | H76: 45852 | I76: Delivered | J76: Carlos Diaz | K76: Production
A77: REL0076 | B77: PRJ028 | C77: =IFERROR(VLOOKUP(B77,Projects!$A:$AK,2,FALSE()),"") | D77: Mobile App 2 R2 | E77: 2.0.0 | F77: Major | G77: 46042 | H77: 46043 | I77: Delivered | J77: Carlos Diaz | K77: UAT
A78: REL0077 | B78: PRJ029 | C78: =IFERROR(VLOOKUP(B78,Projects!$A:$AK,2,FALSE()),"") | D78: Analytics Platform 2 R1 | E78: 1.0.0 | F78: Major | G78: 46097 | H78: 46099 | I78: Delivered | J78: John Smith | K78: Staging
A79: REL0078 | B79: PRJ029 | C79: =IFERROR(VLOOKUP(B79,Projects!$A:$AK,2,FALSE()),"") | D79: Analytics Platform 2 R2 | E79: 2.0.0 | F79: Patch | G79: 46218 | H79: 46217 | I79: Delivered | J79: John Smith | K79: UAT
A80: REL0079 | B80: PRJ030 | C80: =IFERROR(VLOOKUP(B80,Projects!$A:$AK,2,FALSE()),"") | D80: Service Desk 2 R1 | E80: 1.0.0 | F80: Major | G80: 45890 | H80: 45891 | I80: Delivered | J80: Jane Doe | K80: UAT
... A86: REL0085 | B86: PRJ032 | C86: =IFERROR(VLOOKUP(B86,Projects!$A:$AK,2,FALSE()),"") | D86: Compliance Hub R1 | E86: 1.0.0 | F86: Hotfix | G86: 46182 | H86: 46192 | I86: Delivered | J86: Carlos Diaz | K86: UAT
A87: REL0086 | B87: PRJ032 | C87: =IFERROR(VLOOKUP(B87,Projects!$A:$AK,2,FALSE()),"") | D87: Compliance Hub R2 | E87: 2.0.0 | F87: Hotfix | G87: 46354 | I87: Planned | J87: Carlos Diaz | K87: Staging
A88: REL0087 | B88: PRJ033 | C88: =IFERROR(VLOOKUP(B88,Projects!$A:$AK,2,FALSE()),"") | D88: Risk Platform R1 | E88: 1.0.0 | F88: Major | G88: 46119 | H88: 46124 | I88: Delivered | J88: Priya Patel | K88: Staging
A89: REL0088 | B89: PRJ033 | C89: =IFERROR(VLOOKUP(B89,Projects!$A:$AK,2,FALSE()),"") | D89: Risk Platform R2 | E89: 2.0.0 | F89: Hotfix | G89: 46256 | I89: Planned | J89: Priya Patel | K89: UAT
A90: REL0089 | B90: PRJ033 | C90: =IFERROR(VLOOKUP(B90,Projects!$A:$AK,2,FALSE()),"") | D90: Risk Platform R3 | E90: 3.0.0 | F90: Minor | G90: 46392 | I90: Planned | J90: Priya Patel | K90: Staging
A91: REL0090 | B91: PRJ034 | C91: =IFERROR(VLOOKUP(B91,Projects!$A:$AK,2,FALSE()),"") | D91: Treasury Sys R1 | E91: 1.0.0 | F91: Major | G91: 46078 | H91: 46084 | I91: Delivered | J91: Jane Doe | K91: UAT
A92: REL0091 | B92: PRJ034 | C92: =IFERROR(VLOOKUP(B92,Projects!$A:$AK,2,FALSE()),"") | D92: Treasury Sys R2 | E92: 2.0.0 | F92: Major | G92: 46186 | H92: 46186 | I92: Delivered | J92: Jane Doe | K92: Staging
A93: REL0092 | B93: PRJ034 | C93: =IFERROR(VLOOKUP(B93,Projects!$A:$AK,2,FALSE()),"") | D93: Treasury Sys R3 | E93: 3.0.0 | F93: Patch | G93: 46294 | I93: Planned | J93: Jane Doe | K93: Staging
A94: REL0093 | B94: PRJ035 | C94: =IFERROR(VLOOKUP(B94,Projects!$A:$AK,2,FALSE()),"") | D94: Payroll Cloud R1 | E94: 1.0.0 | F94: Patch | G94: 45869 | H94: 45873 | I94: Delivered | J94: Jane Doe | K94: UAT
A95: REL0094 | B95: PRJ035 | C95: =IFERROR(VLOOKUP(B95,Projects!$A:$AK,2,FALSE()),"") | D95: Payroll Cloud R2 | E95: 2.0.0 | F95: Major | G95: 45958 | H95: 45953 | I95: Delivered | J95: Jane Doe | K95: Production
A96: REL0095 | B96: PRJ035 | C96: =IFERROR(VLOOKUP(B96,Projects!$A:$AK,2,FALSE()),"") | D96: Payroll Cloud R3 | E96: 3.0.0 | F96: Hotfix | G96: 46046 | H96: 46051 | I96: Delivered | J96: Jane Doe | K96: Production
A97: REL0096 | B97: PRJ035 | C97: =IFERROR(VLOOKUP(B97,Projects!$A:$AK,2,FALSE()),"") | D97: Payroll Cloud R4 | E97: 4.0.0 | F97: Minor | G97: 46135 | H97: 46141 | I97: Delivered | J97: Jane Doe | K97: Production
A98: REL0097 | B98: PRJ036 | C98: =IFERROR(VLOOKUP(B98,Projects!$A:$AK,2,FALSE()),"") | D98: HR Self-Service R1 | E98: 1.0.0 | F98: Patch | G98: 45855 | H98: 45861 | I98: Delivered | J98: Jane Doe | K98: Production
A99: REL0098 | B99: PRJ036 | C99: =IFERROR(VLOOKUP(B99,Projects!$A:$AK,2,FALSE()),"") | D99: HR Self-Service R2 | E99: 2.0.0 | F99: Major | G99: 45924 | H99: 45929 | I99: Delivered | J99: Jane Doe | K99: Production
A100: REL0099 | B100: PRJ037 | C100: =IFERROR(VLOOKUP(B100,Projects!$A:$AK,2,FALSE()),"") | D100: SAP S/4HANA R1 | E100: 1.0.0 | F100: Patch | G100: 45779 | H100: 45774 | I100: Delivered | J100: John Smith | K100: Production
A101: REL0100 | B101: PRJ037 | C101: =IFERROR(VLOOKUP(B101,Projects!$A:$AK,2,FALSE()),"") | D101: SAP S/4HANA R2 | E101: 2.0.0 | F101: Patch | G101: 45837 | H101: 45846 | I101: Delivered | J101: John Smith | K101: Production
A102: REL0101 | B102: PRJ037 | C102: =IFERROR(VLOOKUP(B102,Projects!$A:$AK,2,FALSE()),"") | D102: SAP S/4HANA R3 | E102: 3.0.0 | F102: Hotfix | G102: 45894 | H102: 45891 | I102: Delivered | J102: John Smith | K102: UAT
A103: REL0102 | B103: PRJ038 | C103: =IFERROR(VLOOKUP(B103,Projects!$A:$AK,2,FALSE()),"") | D103: Salesforce CRM R1 | E103: 1.0.0 | F103: Major | G103: 45951 | H103: 45952 | I103: Delivered | J103: Jane Doe | K103: Staging
A104: REL0103 | B104: PRJ038 | C104: =IFERROR(VLOOKUP(B104,Projects!$A:$AK,2,FALSE()),"") | D104: Salesforce CRM R2 | E104: 2.0.0 | F104: Major | G104: 45993 | H104: 45996 | I104: Delivered | J104: Jane Doe | K104: Staging
A105: REL0104 | B105: PRJ039 | C105: =IFERROR(VLOOKUP(B105,Projects!$A:$AK,2,FALSE()),"") | D105: M365 Rollout R1 | E105: 1.0.0 | F105: Patch | G105: 45999 | H105: 46007 | I105: Delivered | J105: Jane Doe | K105: UAT
...

Sheet Programs
A1: Program | B1: Owner | C1: Sponsor | D1: Budget | E1: Forecast | F1: Start FY | G1: End FY | H1: Status | I1: Notes
A2: Digital Transformation | B2: Mike Johnson | C2: CTO | D2: 20682756 | E2: 19929607 | F2: FY25 | G2: FY26 | H2: Active
A3: Cyber Security | B3: Sarah Lee | C3: CFO | D3: 23048795 | E3: 25365239 | F3: FY25 | G3: FY27 | H3: Active
A4: Cloud Migration | B4: Alex Brown | C4: CIO | D4: 19629127 | E4: 19663839 | F4: FY25 | G4: FY27 | H4: Active
A5: Data & AI | B5: Mike Johnson | C5: CIO | D5: 15462956 | E5: 14369534 | F5: FY25 | G5: FY27 | H5: Active
A6: Customer Experience | B6: Priya Patel | C6: CTO | D6: 10175226 | E6: 10299815 | F6: FY25 | G6: FY26 | H6: Active

Sheet PhaseFinancials
A1: Project ID | B1: Stage | C1: Planned Start | D1: Planned End | E1: Actual Start | F1: Actual End | G1: Phase Budget | H1: Phase Forecast | I1: Phase Actual Spend | J1: Status | K1: Notes
A2: PRJ001 | B2: Discovery | C2: 45702 | D2: 45751 | E2: 45702 | F2: 45751 | G2: 324221 | H2: 371877 | I2: 310352 | J2: Complete
A3: PRJ001 | B3: Business Case / Seed Funding | C3: 45751 | D3: 45800 | E3: 45751 | F3: 45800 | G3: 324221 | H3: 314848 | I3: 286522 | J3: Complete
A4: PRJ001 | B4: Design | C4: 45800 | D4: 45849 | E4: 45800 | F4: 45849 | G4: 324221 | H4: 324448 | I4: 304969 | J4: Complete
A5: PRJ001 | B5: Business Case / Full Funding | C5: 45849 | D5: 45898 | E5: 45849 | F5: 45898 | G5: 324221 | H5: 366210 | I5: 13318 | J5: Complete
A6: PRJ001 | B6: Build | C6: 45898 | D6: 45947 | E6: 45898 | F6: 45947 | G6: 324221 | H6: 344061 | I6: 23644 | J6: Complete
A7: PRJ001 | B7: Testing | C7: 45947 | D7: 45996 | E7: 45947 | F7: 45996 | G7: 324221 | H7: 299509 | I7: 273201 | J7: Complete
A8: PRJ001 | B8: Deployment | C8: 45996 | D8: 46045 | E8: 45996 | F8: 46045 | G8: 324221 | H8: 350422 | I8: 93508 | J8: Complete
A9: PRJ001 | B9: Handover | C9: 46045 | D9: 46094 | E9: 46045 | F9: 46094 | G9: 324221 | H9: 352889 | I9: 136290 | J9: Complete
A10: PRJ002 | B10: Discovery | C10: 45737 | D10: 45762 | E10: 45737 | F10: 45762 | G10: 231489 | H10: 240544 | I10: 76121 | J10: Complete
A11: PRJ002 | B11: Business Case / Seed Funding | C11: 45762 | D11: 45787 | E11: 45762 | F11: 45787 | G11: 231489 | H11: 243777 | I11: 95604 | J11: Complete
A12: PRJ002 | B12: Design | C12: 45787 | D12: 45812 | E12: 45787 | F12: 45812 | G12: 231489 | H12: 248646 | I12: 110492 | J12: Complete
A13: PRJ002 | B13: Business Case / Full Funding | C13: 45812 | D13: 45837 | E13: 45812 | F13: 45837 | G13: 231489 | H13: 257455 | I13: 235080 | J13: Complete
... A30: PRJ004 | B30: Build | C30: 46159 | D30: 46216 | E30: 46159 | F30: 46216 | G30: 192963 | H30: 209994 | I30: 179878 | J30: Complete
A31: PRJ004 | B31: Testing | C31: 46216 | D31: 46273 | E31: 46216 | G31: 192963 | H31: 220260 | I31: 83738 | J31: In Progress
A32: PRJ004 | B32: Deployment | C32: 46273 | D32: 46330 | G32: 192963 | H32: 195220 | I32: 0 | J32: Planned
A33: PRJ004 | B33: Handover | C33: 46330 | D33: 46387 | G33: 192963 | H33: 179570 | I33: 0 | J33: Planned
A34: PRJ005 | B34: Discovery | C34: 45860 | D34: 45927 | E34: 45860 | F34: 45927 | G34: 208068 | H34: 214705 | I34: 126251 | J34: Complete
A35: PRJ005 | B35: Business Case / Seed Funding | C35: 45927 | D35: 45994 | E35: 45927 | F35: 45994 | G35: 208068 | H35: 221658 | I35: 213304 | J35: Complete
A36: PRJ005 | B36: Design | C36: 45994 | D36: 46061 | E36: 45994 | F36: 46061 | G36: 208068 | H36: 204006 | I36: 159673 | J36: Complete
A37: PRJ005 | B37: Business Case / Full Funding | C37: 46061 | D37: 46128 | E37: 46061 | F37: 46128 | G37: 208068 | H37: 199008 | I37: 57635 | J37: Complete
A38: PRJ005 | B38: Build | C38: 46128 | D38: 46195 | E38: 46128 | F38: 46195 | G38: 208068 | H38: 202670 | I38: 18088 | J38: Complete
A39: PRJ005 | B39: Testing | C39: 46195 | D39: 46262 | E39: 46195 | G39: 208068 | H39: 216313 | I39: 190698 | J39: In Progress
A40: PRJ005 | B40: Deployment | C40: 46262 | D40: 46329 | G40: 208068 | H40: 221565 | I40: 0 | J40: Planned
A41: PRJ005 | B41: Handover | C41: 46329 | D41: 46396 | G41: 208068 | H41: 225508 | I41: 0 | J41: Planned
A42: PRJ006 | B42: Discovery | C42: 45736 | D42: 45787 | E42: 45736 | F42: 45787 | G42: 207208 | H42: 197153 | I42: 16974 | J42: Complete
A43: PRJ006 | B43: Business Case / Seed Funding | C43: 45787 | D43: 45838 | E43: 45787 | F43: 45838 | G43: 207208 | H43: 236826 | I43: 13112 | J43: Complete
A44: PRJ006 | B44: Design | C44: 45838 | D44: 45889 | E44: 45838 | F44: 45889 | G44: 207208 | H44: 187167 | I44: 47024 | J44: Complete
A45: PRJ006 | B45: Business Case / Full Funding | C45: 45889 | D45: 45940 | E45: 45889 | F45: 45940 | G45: 207208 | H45: 228887 | I45: 40885 | J45: Complete
A46: PRJ006 | B46: Build | C46: 45940 | D46: 45991 | E46: 45940 | F46: 45991 | G46: 207208 | H46: 191902 | I46: 45398 | J46: Complete
A47: PRJ006 | B47: Testing | C47: 45991 | D47: 46042 | E47: 45991 | F47: 46042 | G47: 207208 | H47: 217077 | I47: 114799 | J47: Complete
A48: PRJ006 | B48: Deployment | C48: 46042 | D48: 46093 | E48: 46042 | F48: 46093 | G48: 207208 | H48: 230957 | I48: 165458 | J48: Complete
A49: PRJ006 | B49: Handover | C49: 46093 | D49: 46144 | E49: 46093 | F49: 46144 | G49: 207208 | H49: 202640 | I49: 98781 | J49: Complete
A50: PRJ007 | B50: Discovery | C50: 45792 | D50: 45865 | E50: 45792 | F50: 45865 | G50: 443834 | H50: 416538 | I50: 235115 | J50: Complete
A51: PRJ007 | B51: Business Case / Seed Funding | C51: 45865 | D51: 45938 | E51: 45865 | F51: 45938 | G51: 443834 | H51: 500881 | I51: 101959 | J51: Complete
A52: PRJ007 | B52: Design | C52: 45938 | D52: 46011 | E52: 45938 | F52: 46011 | G52: 443834 | H52: 439800 | I52: 454406 | J52: Complete
A53: PRJ007 | B53: Business Case / Full Funding | C53: 46011 | D53: 46084 | E53: 46011 | F53: 46084 | G53: 443834 | H53: 495747 | I53: 239288 | J53: Complete
A54: PRJ007 | B54: Build | C54: 46084 | D54: 46157 | E54: 46084 | F54: 46157 | G54: 443834 | H54: 486001 | I54: 87591 | J54: Complete
A55: PRJ007 | B55: Testing | C55: 46157 | D55: 46230 | E55: 46157 | G55: 443834 | H55: 430279 | I55: 76520 | J55: In Progress
A56: PRJ007 | B56: Deployment | C56: 46230 | D56: 46303 | G56: 443834 | H56: 433532 | I56: 0 | J56: Planned
A57: PRJ007 | B57: Handover | C57: 46303 | D57: 46376 | G57: 443834 | H57: 495966 | I57: 0 | J57: Planned
A58: PRJ008 | B58: Discovery | C58: 45780 | D58: 45794 | E58: 45780 | F58: 45794 | G58: 460266 | H58: 488846 | I58: 71182 | J58: Complete
A59: PRJ008 | B59: Business Case / Seed Funding | C59: 45794 | D59: 45808 | E59: 45794 | F59: 45808 | G59: 460266 | H59: 515060 | I59: 360055 | J59: Complete
A60: PRJ008 | B60: Design | C60: 45808 | D60: 45822 | E60: 45808 | F60: 45822 | G60: 460266 | H60: 441920 | I60: 432099 | J60: Complete
A61: PRJ008 | B61: Business Case / Full Funding | C61: 45822 | D61: 45836 | E61: 45822 | F61: 45836 | G61: 460266 | H61: 435760 | I61: 13815 | J61: Complete
A62: PRJ008 | B62: Build | C62: 45836 | D62: 45850 | E62: 45836 | F62: 45850 | G62: 460266 | H62: 490400 | I62: 218752 | J62: Complete
A63: PRJ008 | B63: Testing | C63: 45850 | D63: 45864 | E63: 45850 | F63: 45864 | G63: 460266 | H63: 444798 | I63: 447965 | J63: Complete
A64: PRJ008 | B64: Deployment | C64: 45864 | D64: 45878 | E64: 45864 | F64: 45878 | G64: 460266 | H64: 423912 | I64: 208522 | J64: Complete
A65: PRJ008 | B65: Handover | C65: 45878 | D65: 45892 | E65: 45878 | F65: 45892 | G65: 460266 | H65: 431570 | I65: 242698 | J65: Complete
A66: PRJ009 | B66: Discovery | C66: 46023 | D66: 46054 | E66: 46023 | F66: 46054 | G66: 141715 | H66: 145539 | I66: 7910 | J66: Complete
A67: PRJ009 | B67: Business Case / Seed Funding | C67: 46054 | D67: 46085 | E67: 46054 | F67: 46085 | G67: 141715 | H67: 137201 | I67: 14555 | J67: Complete
A68: PRJ009 | B68: Design | C68: 46085 | D68: 46116 | E68: 46085 | F68: 46116 | G68: 141715 | H68: 150523 | I68: 108922 | J68: Complete
A69: PRJ009 | B69: Business Case / Full Funding | C69: 46116 | D69: 46147 | E69: 46116 | F69: 46147 | G69: 141715 | H69: 142515 | I69: 43748 | J69: Complete
... A71: PRJ009 | B71: Testing | C71: 46178 | D71: 46209 | E71: 46178 | F71: 46209 | G71: 141715 | H71: 146305 | I71: 73451 | J71: Complete
A72: PRJ009 | B72: Deployment | C72: 46209 | D72: 46240 | E72: 46209 | G72: 141715 | H72: 142904 | I72: 101357 | J72: In Progress
A73: PRJ009 | B73: Handover | C73: 46240 | D73: 46271 | G73: 141715 | H73: 150443 | I73: 0 | J73: Planned
A74: PRJ010 | B74: Discovery | C74: 45694 | D74: 45738 | E74: 45694 | F74: 45738 | G74: 299364 | H74: 341199 | I74: 69021 | J74: Complete
A75: PRJ010 | B75: Business Case / Seed Funding | C75: 45738 | D75: 45782 | E75: 45738 | F75: 45782 | G75: 299364 | H75: 273405 | I75: 11218 | J75: Complete
A76: PRJ010 | B76: Design | C76: 45782 | D76: 45826 | E76: 45782 | F76: 45826 | G76: 299364 | H76: 289349 | I76: 20698 | J76: Complete
A77: PRJ010 | B77: Business Case / Full Funding | C77: 45826 | D77: 45870 | E77: 45826 | F77: 45870 | G77: 299364 | H77: 276989 | I77: 71185 | J77: Complete
A78: PRJ010 | B78: Build | C78: 45870 | D78: 45914 | E78: 45870 | F78: 45914 | G78: 299364 | H78: 315846 | I78: 225007 | J78: Complete
A79: PRJ010 | B79: Testing | C79: 45914 | D79: 45958 | E79: 45914 | F79: 45958 | G79: 299364 | H79: 298759 | I79: 31843 | J79: Complete
A80: PRJ010 | B80: Deployment | C80: 45958 | D80: 46002 | E80: 45958 | F80: 46002 | G80: 299364 | H80: 324356 | I80: 276464 | J80: Complete
A81: PRJ010 | B81: Handover | C81: 46002 | D81: 46046 | E81: 46002 | F81: 46046 | G81: 299364 | H81: 289505 | I81: 64660 | J81: Complete
A82: PRJ011 | B82: Discovery | C82: 45988 | D82: 46005 | E82: 45988 | F82: 46005 | G82: 58484 | H82: 64124 | I82: 21347 | J82: Complete
A83: PRJ011 | B83: Business Case / Seed Funding | C83: 46005 | D83: 46022 | E83: 46005 | F83: 46022 | G83: 58484 | H83: 56846 | I83: 36618 | J83: Complete
A84: PRJ011 | B84: Design | C84: 46022 | D84: 46039 | E84: 46022 | F84: 46039 | G84: 58484 | H84: 63366 | I84: 5787 | J84: Complete
A85: PRJ011 | B85: Business Case / Full Funding | C85: 46039 | D85: 46056 | E85: 46039 | F85: 46056 | G85: 58484 | H85: 59993 | I85: 43015 | J85: Complete
... A93: PRJ012 | B93: Business Case / Full Funding | C93: 46126 | D93: 46190 | E93: 46126 | F93: 46190 | G93: 238031 | H93: 218809 | I93: 169755 | J93: Complete
A94: PRJ012 | B94: Build | C94: 46190 | D94: 46254 | E94: 46190 | G94: 238031 | H94: 264993 | I94: 148461 | J94: In Progress
A95: PRJ012 | B95: Testing | C95: 46254 | D95: 46318 | G95: 238031 | H95: 271923 | I95: 0 | J95: Planned
A96: PRJ012 | B96: Deployment | C96: 46318 | D96: 46382 | G96: 238031 | H96: 248931 | I96: 0 | J96: Planned
A97: PRJ012 | B97: Handover | C97: 46382 | D97: 46446 | G97: 238031 | H97: 243286 | I97: 0 | J97: Planned
A98: PRJ013 | B98: Discovery | C98: 45996 | D98: 46053 | E98: 45996 | F98: 46053 | G98: 492838 | H98: 474050 | I98: 56605 | J98: Complete
A99: PRJ013 | B99: Business Case / Seed Funding | C99: 46053 | D99: 46110 | E99: 46053 | F99: 46110 | G99: 492838 | H99: 544454 | I99: 293549 | J99: Complete
A100: PRJ013 | B100: Design | C100: 46110 | D100: 46167 | E100: 46110 | F100: 46167 | G100: 492838 | H100: 565583 | I100: 432282 | J100: Complete
A101: PRJ013 | B101: Business Case / Full Funding | C101: 46167 | D101: 46224 | E101: 46167 | G101: 492838 | H101: 508272 | I101: 86577 | J101: In Progress
A102: PRJ013 | B102: Build | C102: 46224 | D102: 46281 | G102: 492838 | H102: 461615 | I102: 0 | J102: Planned
A103: PRJ013 | B103: Testing | C103: 46281 | D103: 46338 | G103: 492838 | H103: 455125 | I103: 0 | J103: Planned
A104: PRJ013 | B104: Deployment | C104: 46338 | D104: 46395 | G104: 492838 | H104: 481084 | I104: 0 | J104: Planned
A105: PRJ013 | B105: Handover | C105: 46395 | D105: 46452 | G105: 492838 | H105: 534259 | I105: 0 | J105: Planned
A106: PRJ014 | B106: Discovery | C106: 45693 | D106: 45742 | E106: 45693 | F106: 45742 | G106: 297287 | H106: 301197 | I106: 229373 | J106: Complete
A107: PRJ014 | B107: Business Case / Seed Funding | C107: 45742 | D107: 45791 | E107: 45742 | F107: 45791 | G107: 297287 | H107: 341121 | I107: 80329 | J107: Complete
A108: PRJ014 | B108: Design | C108: 45791 | D108: 45840 | E108: 45791 | F108: 45840 | G108: 297287 | H108: 303715 | I108: 113713 | J108: Complete
A109: PRJ014 | B109: Business Case / Full Funding | C109: 45840 | D109: 45889 | E109: 45840 | F109: 45889 | G109: 297287 | H109: 268566 | I109: 110073 | J109: Complete
A110: PRJ014 | B110: Build | C110: 45889 | D110: 45938 | E110: 45889 | F110: 45938 | G110: 297287 | H110: 320338 | I110: 278243 | J110: Complete
A111: PRJ014 | B111: Testing | C111: 45938 | D111: 45987 | E111: 45938 | F111: 45987 | G111: 297287 | H111: 325122 | I111: 267500 | J111: Complete
A112: PRJ014 | B112: Deployment | C112: 45987 | D112: 46036 | E112: 45987 | F112: 46036 | G112: 297287 | H112: 334608 | I112: 185962 | J112: Complete
A113: PRJ014 | B113: Handover | C113: 46036 | D113: 46085 | E113: 46036 | F113: 46085 | G113: 297287 | H113: 275939 | I113: 214068 | J113: Complete
A114: PRJ015 | B114: Discovery | C114: 45811 | D114: 45851 | E114: 45811 | F114: 45851 | G114: 166730 | H114: 180411 | I114: 3629 | J114: Complete
A115: PRJ015 | B115: Business Case / Seed Funding | C115: 45851 | D115: 45891 | E115: 45851 | F115: 45891 | G115: 166730 | H115: 190849 | I115: 149904 | J115: Complete
A116: PRJ015 | B116: Design | C116: 45891 | D116: 45931 | E116: 45891 | F116: 45931 | G116: 166730 | H116: 177541 | I116: 24795 | J116: Complete
A117: PRJ015 | B117: Business Case / Full Funding | C117: 45931 | D117: 45971 | E117: 45931 | F117: 45971 | G117: 166730 | H117: 170808 | I117: 42781 | J117: Complete
... A126: PRJ016 | B126: Build | C126: 46172 | D126: 46217 | E126: 46172 | F126: 46217 | G126: 441921 | H126: 495835 | I126: 181443 | J126: Complete
A127: PRJ016 | B127: Testing | C127: 46217 | D127: 46262 | E127: 46217 | G127: 441921 | H127: 443832 | I127: 461207 | J127: In Progress
A128: PRJ016 | B128: Deployment | C128: 46262 | D128: 46307 | G128: 441921 | H128: 431903 | I128: 0 | J128: Planned
A129: PRJ016 | B129: Handover | C129: 46307 | D129: 46352 | G129: 441921 | H129: 402270 | I129: 0 | J129: Planned
A130: PRJ017 | B130: Discovery | C130: 45705 | D130: 45756 | E130: 45705 | F130: 45756 | G130: 362336 | H130: 373213 | I130: 130600 | J130: Complete
A131: PRJ017 | B131: Business Case / Seed Funding | C131: 45756 | D131: 45807 | E131: 45756 | F131: 45807 | G131: 362336 | H131: 381573 | I131: 164911 | J131: Complete
A132: PRJ017 | B132: Design | C132: 45807 | D132: 45858 | E132: 45807 | F132: 45858 | G132: 362336 | H132: 367321 | I132: 368337 | J132: Complete
...

Sheet ProjectBrief
A1: Project ID | B1: Portfolio / Workstream | C1: Sponsor | D1: Business Owner | E1: Business Solution Manager | F1: Strategic Alignment | G1: Background and Context | H1: Opportunity / Problem Statement | I1: Objective | J1: In Scope | K1: Out of Scope | L1: Assumptions & Constraints | M1: Key Metrics / Success Measures | N1: Approval Type | O1: Funding Ask | P1: Funding Source | Q1: Resource Ask | R1: Estimate Commentary | S1: P&L Benefits Commentary | T1: Delivery Milestones | U1: Project Risks | V1: Dependencies
A2: PRJ001 | C2: =IFERROR(VLOOKUP(A2,Projects!$A:$AK,7,FALSE()),"")
A3: PRJ002 | C3: =IFERROR(VLOOKUP(A3,Projects!$A:$AK,7,FALSE()),"")
A4: PRJ003 | C4: =IFERROR(VLOOKUP(A4,Projects!$A:$AK,7,FALSE()),"")
A5: PRJ004 | C5: =IFERROR(VLOOKUP(A5,Projects!$A:$AK,7,FALSE()),"")
A6: PRJ005 | C6: =IFERROR(VLOOKUP(A6,Projects!$A:$AK,7,FALSE()),"")
A7: PRJ006 | C7: =IFERROR(VLOOKUP(A7,Projects!$A:$AK,7,FALSE()),"")
A8: PRJ007 | C8: =IFERROR(VLOOKUP(A8,Projects!$A:$AK,7,FALSE()),"")
A9: PRJ008 | C9: =IFERROR(VLOOKUP(A9,Projects!$A:$AK,7,FALSE()),"")
A10: PRJ009 | C10: =IFERROR(VLOOKUP(A10,Projects!$A:$AK,7,FALSE()),"")
A11: PRJ010 | C11: =IFERROR(VLOOKUP(A11,Projects!$A:$AK,7,FALSE()),"")
A12: PRJ011 | C12: =IFERROR(VLOOKUP(A12,Projects!$A:$AK,7,FALSE()),"")
A13: PRJ012 | C13: =IFERROR(VLOOKUP(A13,Projects!$A:$AK,7,FALSE()),"")
... A41: PRJ040 | C41: =IFERROR(VLOOKUP(A41,Projects!$A:$AK,7,FALSE()),"")

Sheet ProjectLinks
A1: Project ID | B1: Title | C1: Type | D1: URL | E1: Added By | F1: Added On

Sheet _Stages
A1: Discovery
A2: Business Case / Seed Funding
A3: Design
A4: Business Case / Full Funding
A5: Build
A6: Testing
A7: Deployment
A8: Handover

Sheet FYAllocation
A1: Project ID | B1: Project Name | C1: FY | D1: Budget % | E1: Forecast % | F1: Budget Amount | G1: Forecast Amount | H1: Notes
A2: PRJ001 | B2: Customer Portal | C2: FY25 | D2: 50 | E2: 50 | F2: 1296882 | G2: 1203668 | H2: Auto-split from Projects.Financial Year — edit to revise
A3: PRJ001 | B3: Customer Portal | C3: FY26 | D3: 50 | E3: 50 | F3: 1296882 | G3: 1203668 | H3: Auto-split from Projects.Financial Year — edit to revise
A4: PRJ002 | B4: Cloud Migration | C4: FY25 | D4: 100 | E4: 100 | F4: 1851915 | G4: 2065964 | H4: Auto-split from Projects.Financial Year — edit to revise
A5: PRJ003 | B5: Data Platform | C5: FY25 | D5: 50 | E5: 50 | F5: 1947576 | G5: 2220804 | H5: Auto-split from Projects.Financial Year — edit to revise
A6: PRJ003 | B6: Data Platform | C6: FY26 | D6: 50 | E6: 50 | F6: 1947576 | G6: 2220804 | H6: Auto-split from Projects.Financial Year — edit to revise
A7: PRJ004 | B7: AI Assistant | C7: FY25 | D7: 33.3 | E7: 33.3 | F7: 514569 | G7: 606074 | H7: Auto-split from Projects.Financial Year — edit to revise
A8: PRJ004 | B8: AI Assistant | C8: FY26 | D8: 33.3 | E8: 33.3 | F8: 514569 | G8: 606074 | H8: Auto-split from Projects.Financial Year — edit to revise
A9: PRJ004 | B9: AI Assistant | C9: FY27 | D9: 33.3 | E9: 33.3 | F9: 514569 | G9: 606074 | H9: Auto-split from Projects.Financial Year — edit to revise
A10: PRJ005 | B10: Network Refresh | C10: FY25 | D10: 33.3 | E10: 33.3 | F10: 554848 | G10: 581765 | H10: Auto-split from Projects.Financial Year — edit to revise
A11: PRJ005 | B11: Network Refresh | C11: FY26 | D11: 33.3 | E11: 33.3 | F11: 554848 | G11: 581765 | H11: Auto-split from Projects.Financial Year — edit to revise
A12: PRJ005 | B12: Network Refresh | C12: FY27 | D12: 33.3 | E12: 33.3 | F12: 554848 | G12: 581765 | H12: Auto-split from Projects.Financial Year — edit to revise
A13: PRJ006 | B13: Cyber Security Program | C13: FY25 | D13: 50 | E13: 50 | F13: 828831 | G13: 852316 | H13: Auto-split from Projects.Financial Year — edit to revise
... A83: PRJ040 | B83: Zero-Trust Net | C83: FY26 | D83: 50 | E83: 50 | F83: 846610 | G83: 729290 | H83: Auto-split from Projects.Financial Year — edit to revise
